Workbook

Sheet Portada
B2: DECLARACIÓN DE APLICABILIDAD (SoA) – ESQUEMA NACIONAL DE SEGURIDAD
B3: Real Decreto 311/2022, de 3 de mayo – Anexo II · Categoría del sistema: ALTA
B4: Documento de ejemplo con datos ficticios para uso docente (caso TechServ).
B6: Organización | C6: TechServ Administración, S.L. – B-87.654.321 (ficticio)
B7: Sistema de información | C7: PSTA – Plataforma de Servicios TIC para la Administración Autonómica
B8: Código / versión del documento | C8: SOA-ENS-PSTA · v2.0
B9: Fecha de emisión | C9: 18/09/2026
B10: Categoría del sistema (art. 40, Anexo I) | C10: ALTA (D=ALTO · I=ALTO · C=ALTO · A=ALTO · T=MEDIO) – ver hoja 'Categorización'
B11: Análisis de riesgos de referencia (art. 14, [op.pl.1]) | C11: AR-2026-01 (MAGERIT v3 / PILAR), aprobado por el CSI el 30/06/2026
B12: Elaborada por | C12: Laura Ortega Vidal – Responsable de Seguridad (CISO)
B13: Revisada por | C13: Javier Molina Ruiz – Responsable del Sistema (CTO)
B14: Aprobada por | C14: Comité de Seguridad de la Información (CSI) – reunión trimestral – acta ACTA-CSI-2026-03
B15: Responsables de la Información / del Servicio | C15: Consejería de Hacienda / Consejería de Educación / Consejería de Bienestar Social (Responsables de la Información y del Servicio, art. 11 RD 311/2022)
B16: Delegada de Protección de Datos | C16: Marta Ruiz Salgado – Delegada de Protección de Datos
B17: Firma (art. 28.2 RD 311/2022) | C17: Firmado electrónicamente por la Responsable de Seguridad con certificado cualificado – 18/09/2026
... B19: Infraestructura | C19: CPD principal – Alcobendas (Madrid) CPD de respaldo – Tres Cantos (Madrid), distancia 14 km IaaS/PaaS en proveedor con certificación ENS categoría ALTA (NubeAdmin Cloud, S.A.) para el portal público y copias externas SOC 24x7 subcontratado a SecOps Iberia, S.L. (certificado ENS ALTA, ISO 27001) integrado con el CCN-CERT vía LUCIA/REYES
B21: Contenido del libro
B22: Ámbito y perfil | C22: Ámbito de aplicación (art. 2.3), aplicación total/parcial, perfil de cumplimiento específico (art. 30), criterios de selección (art. 28) y regla de aplicación por dimensión.
B23: Categorización | C23: Valoración de los activos esenciales en las cinco dimensiones (Anexo I) y determinación del nivel por dimensión y de la categoría del sistema.
B24: SoA ENS | C24: Las 73 medidas del Anexo II: dimensiones, exigencia BAJO/MEDIO/ALTO, nivel exigido a TechServ, refuerzos, aplicabilidad y justificación, medidas organizativas y técnicas, evidencias, responsable, estado y equivalencia ISO/IEC 27001:2022 (CCN-STIC 825).
B25: Refuerzos | C25: Detalle de cada requisito de refuerzo Rn: nivel en que se exige, si es exigible a TechServ, alternativa elegida e implementación.
B26: Medidas compensatorias | C26: Registro de medidas compensatorias (art. 28.3) con ámbito, limitación, riesgo, medida, validación y mantenimiento.
B27: Resumen | C27: Indicadores calculados con fórmulas: medidas aplicables, no aplicables, compensadas, estado de implantación y grado de cumplimiento por marco.
B28: Texto Anexo II | C28: Texto normativo de cada medida y de sus refuerzos (RD 311/2022) para consulta.
B29: Leyenda | C29: Códigos de colores, valores permitidos y celdas editables.
B31: Control de cambios
B32: Versión / fecha | C32: Descripción
B33: v1.0 – 15/02/2025 | C33: Primera emisión tras la categorización inicial (categoría MEDIA, T=MEDIO, C=MEDIO).
B34: v1.1 – 10/10/2025 | C34: Actualización tras auditoría de certificación: refuerzos op.acc.6 R6/R7 y op.exp.8 R3.
B35: v2.0 – 18/09/2026 | C35: Re-categorización a ALTA por incorporación de S-03 (datos de salud) y valoración D=ALTO de S-01; nuevo análisis de riesgos AR-2026-01; medidas compensatorias MC-01..04; mapeo ISO 27001:2022.

Sheet Ámbito y perfil
A1: Aspecto | B1: Determinación para TechServ / PSTA
A2: Naturaleza de la entidad | B2: Entidad del sector privado (S.L., 85 empleados) que presta servicios TIC a tres consejerías de una Comunidad Autónoma en virtud de contrato administrativo.
A3: Base jurídica de aplicación del ENS | B3: Art. 2.3 RD 311/2022: el ENS se aplica a los sistemas de información de entidades del sector privado cuando, en virtud de una relación contractual, presten servicios o provean soluciones al sector público para el ejercicio de sus competencias. Los pliegos (PPT cláusula 14) exigen conformidad ENS categoría ALTA con certificación en vigor.
A4: Modalidad de aplicación: TOTAL vs PARCIAL | B4: APLICACIÓN PARCIAL (por alcance): el ENS se aplica a los sistemas que soportan los servicios prestados a las consejerías (sistema PSTA: CPD Alcobendas, CPD Tres Cantos, tenant IaaS NubeAdmin, puestos de administración y operación). NO se incluyen en el alcance ENS los sistemas corporativos internos de TechServ sin relación con el servicio (ERP/facturación, RRHH, web comercial), que se gobiernan bajo el SGSI ISO 27001 de la compañía. La frontera está documentada en DOC-ALC-01 (alcance) y en el diagrama de arquitectura ARQ-02.
A5: Perfil de cumplimiento específico (art. 30 RD 311/2022) | B5: NO APLICA ningún perfil de cumplimiento específico. Los perfiles publicados por el CCN (serie CCN-STIC 88x/89x: p. ej. 881A Universidades, 884 Cloud corporativo Azure, 890A Requisitos esenciales para categoría BÁSICA, 890C) están concebidos para entidades o sectores concretos y/o categorías inferiores. TechServ, como prestador privado de un sistema de categoría ALTA con dimensiones ALTO en D/I/C/A, debe aplicar el Anexo II completo con los refuerzos exigidos para su nivel. Se deja constancia de que, si la Consejería contratante dispusiera de un perfil propio aprobado por el CCN, prevalecería el perfil y esta SoA se re-emitiría.
A6: Criterio de selección de medidas (art. 28.1) | B6: a) Activos que constituyen el sistema (inventario INV-01); b) Categoría del sistema: ALTA (art. 40 y Anexo I), con niveles por dimensión D=ALTO, I=ALTO, C=ALTO, A=ALTO, T=MEDIO; c) Decisiones del análisis de riesgos (AR-2026-01, MAGERIT v3 / PILAR, riesgo residual aceptado por el CSI el 30/06/2026).
A7: Regla de aplicación de cada medida | B7: Si la medida afecta a 'Categoría' (todas las dimensiones) se exige el nivel de la CATEGORÍA del sistema (ALTA). Si la medida afecta a una o varias dimensiones concretas, se exige el nivel MÁS ALTO de esas dimensiones (Anexo II, apdo. 2). Ej.: [op.exp.8] afecta sólo a T → nivel MEDIO → se exigen R1-R4 pero no R5; [mp.info.4] afecta sólo a T y sólo aplica en ALTO → NO APLICA en TechServ; [op.acc.1] afecta a T y A → ALTO.
A8: Declaración de Aplicabilidad (art. 28.2) | B8: Documento formalizado y firmado por la Responsable de Seguridad; revisado al menos anualmente y ante cambios significativos del sistema, del análisis de riesgos o de la categoría.
A9: Medidas compensatorias (art. 28.3) | B9: Cuando una medida o refuerzo no puede implantarse tal como lo describe el Anexo II, se sustituye por medidas compensatorias justificadas documentalmente en la hoja 'Medidas compensatorias' (ámbito, restricción, riesgo, medida, validación, mantenimiento), con aprobación del CSI y verificación en auditoría.
A10: Conformidad y auditoría | B10: Categoría ALTA → auditoría formal bienal (art. 31 y Anexo III) y Certificación de Conformidad por entidad acreditada por ENAC (art. 38; ITS de Conformidad, Res. 13/10/2016). Auditoría intermedia de seguimiento anual. Se usa CCN-STIC 808 como cuestionario de verificación y CCN-STIC 804 como guía de implantación.
A11: Instrucciones Técnicas de Seguridad aplicables | B11: ITS de Conformidad con el ENS; ITS de Auditoría de la Seguridad; ITS de Notificación de Incidentes de Seguridad (vía CCN-CERT / LUCIA, art. 33); ITS de Informe del Estado de la Seguridad (INES, art. 32).
A12: Guías CCN-STIC de referencia | B12: 800 (glosario), 801 (roles), 802 (auditoría), 803 (valoración), 804 (implantación), 805 (política), 806 (plan de adecuación), 808 (verificación), 809 (declaración/certificación), 810 (medidas en la nube), 811 (interconexión), 815 (métricas), 817 (ciberincidentes), 821 (normas de seguridad), 823 (cloud), 824 (informe estado seguridad), 825 (ENS ↔ ISO 27001), 827 (RD 311 categorización), 830 (ámbito y contratación).

Sheet Categorización
A1: Categorización del sistema PSTA – Anexo I RD 311/2022 (CCN-STIC 803 / 827)
A2: Criterio Anexo I: BAJO = perjuicio limitado · MEDIO = perjuicio grave · ALTO = perjuicio muy grave, sobre las funciones de la organización, los activos o las personas. El nivel de cada dimensión del sistema es el MÁXIMO de los activos esenciales; la categoría es ALTA si alguna dimensión es ALTO (art. 40).
A4: Tipo | B4: ID | C4: Activo esencial (servicio / información) | D4: Responsable de la Información / Servicio | E4: D | F4: I | G4: C | H4: A | I4: T | J4: Justificación de la valoración (Anexo I)
A5: Servicio | B5: S-01 | C5: Sede tributaria electrónica (autoliquidaciones, pagos, notificaciones) | D5: Consejería de Hacienda | E5: m | F5: ALTO | G5: ALTO | H5: ALTO | I5: MEDIO | J5: D: la interrupción en campaña impide el cumplimiento de obligaciones tributarias de >2M contribuyentes (perjuicio muy grave, Anexo I). I/A: la alteración o suplantación de una autoliquidación tiene efectos jurídicos directos. C: datos tributarios (art. 95 LGT). T: se exige reconstruir quién hizo qué, pero un fallo aislado del registro tiene consecuencias graves, no muy graves.
A6: Servicio | B6: S-02 | C6: Plataforma de gestión académica y becas | D6: Consejería de Educación | E6: MEDIO | F6: ALTO | G6: ALTO | H6: MEDIO | I6: MEDIO | J6: D: tolera 24-48 h de parada fuera de matriculación. I: la manipulación de expedientes/calificaciones tiene efectos legales. C: datos de menores y situación socioeconómica de familias. A/T: consecuencias graves pero recuperables.
A7: Servicio | B7: S-03 | C7: Gestión de expedientes de dependencia y prestaciones sociales | D7: Consejería de Bienestar Social | E7: MEDIO | F7: ALTO | G7: ALTO | H7: MEDIO | I7: MEDIO | J7: C: datos de salud y situación de vulnerabilidad (categorías especiales, art. 9 RGPD) → ALTO. I: la alteración de un grado de dependencia altera prestaciones económicas. D: proceso administrativo con tolerancia de 48 h.
A8: Servicio | B8: S-04 | C8: Servicios transversales (Directorio, correo corporativo, VPN, PKI interna, monitorización) | D8: TechServ (Responsable del Sistema) | E8: m | F8: ALTO | G8: ALTO | H8: ALTO | I8: MEDIO | J8: Hereda el máximo de los servicios que soporta (dependencia funcional, Anexo I apdo. 4).
A9: Información | B9: I-01 | C9: Datos tributarios y de recaudación | D9: Consejería de Hacienda | E9: MEDIO | F9: ALTO | G9: ALTO | H9: ALTO | I9: MEDIO | J9: Información con reserva legal (art. 95 LGT). Su divulgación causa perjuicio muy grave a los derechos de los contribuyentes.
A10: Información | B10: I-02 | C10: Datos de salud / dependencia (categoría especial) | D10: Consejería de Bienestar Social | E10: MEDIO | F10: ALTO | G10: ALTO | H10: MEDIO | I10: MEDIO | J10: Categoría especial de datos (art. 9 RGPD); DPIA realizada (REG-RGPD-07).
A11: Información | B11: I-03 | C11: Datos académicos y socioeconómicos de menores | D11: Consejería de Educación | E11: BAJO | F11: ALTO | G11: ALTO | H11: MEDIO | I11: MEDIO | J11: Datos de menores: divulgación con perjuicio muy grave para los afectados.
A12: Información | B12: I-04 | C12: Credenciales, claves criptográficas y configuración de seguridad | D12: TechServ | E12: ALTO | F12: ALTO | G12: ALTO | H12: ALTO | I12: MEDIO | J12: Su compromiso afecta a todos los servicios (activo de soporte crítico).
A13: RESULTADO | C13: Nivel del sistema por dimensión (fórmula: máximo de los activos) | E13: =IF(COUNTIF(E5:E12,"ALTO")>0,"ALTO",IF(COUNTIF(E5:E12,"MEDIO")>0,"MEDIO","BAJO")) -> ALTO | F13: =IF(COUNTIF(F5:F12,"ALTO")>0,"ALTO",IF(COUNTIF(F5:F12,"MEDIO")>0,"MEDIO","BAJO")) -> ALTO | G13: =IF(COUNTIF(G5:G12,"ALTO")>0,"ALTO",IF(COUNTIF(G5:G12,"MEDIO")>0,"MEDIO","BAJO")) -> ALTO | H13: =IF(COUNTIF(H5:H12,"ALTO")>0,"ALTO",IF(COUNTIF(H5:H12,"MEDIO")>0,"MEDIO","BAJO")) -> ALTO | I13: =IF(COUNTIF(I5:I12,"ALTO")>0,"ALTO",IF(COUNTIF(I5:I12,"MEDIO")>0,"MEDIO","BAJO")) -> MEDIO | J13: Calculado automáticamente a partir de la tabla. Debe coincidir con la decisión formal del CSI (fila siguiente).
A14: DECISIÓN CSI | C14: Nivel aprobado por el Comité de Seguridad (ACTA-CSI-2026-03) | E14: ALTO | F14: ALTO | G14: ALTO | H14: ALTO | I14: MEDIO | J14: Estos valores alimentan la hoja 'SoA ENS' (columna 'Nivel exigido'). Celdas editables (amarillo).
A15: CATEGORÍA | C15: Categoría del sistema (art. 40): ALTA si alguna dimensión es ALTO; MEDIA si alguna es MEDIO; BÁSICA en otro caso | E15: =IF(COUNTIF(E14:I14,"ALTO")>0,"ALTA",IF(COUNTIF(E14:I14,"MEDIO")>0,"MEDIA","BÁSICA")) -> ALTA
A17: Consecuencias de la categorización sobre la SoA
A18: • Medidas que afectan a 'Categoría' (todas las dimensiones): se exige el nivel ALTA → columna 'Nivel ALTO' del Anexo II.
A19: • Medidas que afectan a dimensiones concretas: se exige el máximo de los niveles de esas dimensiones. Con T = MEDIO: [op.exp.8] (T) → MEDIO (R1-R4, sin R5); [mp.info.4] (T, sólo ALTO) → NO APLICA; [op.acc.1] (T y A) → ALTO por A.
A20: • Cambio de nivel en cualquier dimensión ⇒ re-emisión de la SoA, revisión del análisis de riesgos y comunicación a las consejerías (art. 28 / Anexo II apdo. 2).
A21: • Categoría ALTA ⇒ certificación de conformidad obligatoria por entidad acreditada y auditoría bienal (art. 31 y 38; ITS Conformidad / Auditoría).

Sheet SoA ENS
A1: Marco / familia | B1: Código | C1: Medida de seguridad | D1: Dimensiones afectadas (Anexo II) | E1: Nivel BAJO | F1: Nivel MEDIO | G1: Nivel ALTO | H1: Nivel exigido a TechServ | I1: Regla aplicada | J1: Exigencia aplicable (Anexo II) | K1: Refuerzos exigidos (Rn) | L1: Refuerzos / alternativa elegida | M1: ¿Aplica? | N1: Justificación de aplicabilidad / exclusión | O1: Medidas ORGANIZATIVAS implantadasPortal de firma de normativas (registro de aceptación); banner de aviso en el inicio de sesión. | P1: Medidas TÉCNICAS implantadas | Q1: Medida compensatoria (ref.) | R1: Estado de implantación | S1: % implantación | T1: Evidencias / documentos | U1: Responsable | V1: Control ISO/IEC 27001:2022 equivalente (CCN-STIC 825) | W1: Guías CCN-STIC / verificación | X1: Observaciones / PTR
A2: Marco organizativo | B2: org.2 | C2: Normativa de seguridad | D2: Categoría | E2: aplica | F2: aplica | G2: aplica | H2: =IF('Categorización'!$E$15="ALTA","ALTO",IF('Categorización'!$E$15="MEDIA","MEDIO","BAJO")) -> ALTO | I2: Categoría del sistema = ALTA | J2: =IF(H2="ALTO",G2,IF(H2="MEDIO",F2,E2)) -> aplica | K2: — | L2: — | M2: SÍ | N2: APLICA: medida exigida para la categoría ALTA del sistema (afecta a todas las dimensiones). Exigencia: 'aplica'. Riesgos tratados según AR-2026-01. CCN-STIC 808: 3 requisitos de verificación (2 esenciales). | O2: Normativas de seguridad NOR-01 Uso aceptable de recursos TIC, NOR-02 Puesto de trabajo y teletrabajo, NOR-03 Dispositivos móviles, NOR-04 Clasificación y manejo de la información, NOR-05 Contraseñas y autenticación; régimen disciplinario vinculado al convenio y contratos. Aceptación firmada por todo el personal y terceros. | P2: Portal de firma de normativas (registro de aceptación); banner de aviso en el inicio de sesión. | Q2: — | R2: Implantada | S2: 1 | T2: NOR-01..05; REG-ACEPT-NOR (aceptaciones); PRO-RRHH-02 | U2: Responsable de Seguridad | V2: 5.1 Políticas; 5.10 Uso aceptable; 5.36 Cumplimiento de políticas; 6.7 Trabajo remoto; 7.7 Escritorio y pantalla despejados; 8.1 Dispositivos de usuario | W2: CCN-STIC 801, 805, 821, 804/808
A3: Marco organizativo | B3: org.3 | C3: Procedimientos de seguridad | D3: Categoría | E3: aplica | F3: aplica | G3: aplica | H3: =IF('Categorización'!$E$15="ALTA","ALTO",IF('Categorización'!$E$15="MEDIA","MEDIO","BAJO")) -> ALTO | I3: Categoría del sistema = ALTA | J3: =IF(H3="ALTO",G3,IF(H3="MEDIO",F3,E3)) -> aplica | K3: — | L3: — | M3: SÍ | N3: APLICA: medida exigida para la categoría ALTA del sistema (afecta a todas las dimensiones). Exigencia: 'aplica'. Riesgos tratados según AR-2026-01. CCN-STIC 808: 7 requisitos de verificación (2 esenciales). | O3: Catálogo de procedimientos operativos PRO-xx (altas/bajas de usuarios, copias, cambios, incidentes, parches, gestión de soportes, acceso físico, notificación a CCN-CERT, etc.) con propietario, revisión anual y validación por el Resp. de Seguridad. | P3: Repositorio documental con flujo de aprobación y control de versiones; enlaces desde la herramienta ITSM. | Q3: — | R3: Implantada | S3: 1 | T3: Índice documental IDX-01 (48 procedimientos); PRO-GEST-01 Gestión documental | U3: Responsable del Sistema | V3: 5.37 Procedimientos operativos documentados; 5.5 Contacto con autoridades; 5.14 Transferencia de información; 5.24 Planificación de la gestión de incidentes | W3: CCN-STIC 801, 805, 821, 804/808
A4: Marco organizativo | B4: org.4 | C4: Proceso de autorización | D4: Categoría | E4: aplica | F4: aplica | G4: aplica | H4: =IF('Categorización'!$E$15="ALTA","ALTO",IF('Categorización'!$E$15="MEDIA","MEDIO","BAJO")) -> ALTO | I4: Categoría del sistema = ALTA | J4: =IF(H4="ALTO",G4,IF(H4="MEDIO",F4,E4)) -> aplica | K4: — | L4: — | M4: SÍ | N4: APLICA: medida exigida para la categoría ALTA del sistema (afecta a todas las dimensiones). Exigencia: 'aplica'. Riesgos tratados según AR-2026-01. CCN-STIC 808: 10 requisitos de verificación (4 esenciales). | O4: Procedimiento de autorización PRO-AUT-01: entrada en producción de instalaciones, equipos, aplicaciones, interconexiones, medios de comunicación, soportes y sistemas de terceros; matriz de autorización (Resp. Sistema autoriza, Resp. Seguridad informa favorablemente). | P4: Flujo de autorización en ITSM (ServiceDesk) con evidencias adjuntas; CMDB bloquea activos no autorizados (estado 'pendiente de autorización'). | Q4: — | R4: Implantada | S4: 1 | T4: PRO-AUT-01; REG-AUT-2026 (registro de autorizaciones); tickets ITSM | U4: Responsable del Sistema | V4: 5.2 Roles y responsabilidades; 8.19 Instalación de software; 8.20 Seguridad de redes; 8.32 Gestión de cambios; 5.10 Uso aceptable | W4: CCN-STIC 801, 805, 821, 804/808
A5: Planificación | B5: op.pl.3 | C5: Adquisición de nuevos componentes | D5: Categoría | E5: aplica | F5: aplica | G5: aplica | H5: =IF('Categorización'!$E$15="ALTA","ALTO",IF('Categorización'!$E$15="MEDIA","MEDIO","BAJO")) -> ALTO | I5: Categoría del sistema = ALTA | J5: =IF(H5="ALTO",G5,IF(H5="MEDIO",F5,E5)) -> aplica | K5: — | L5: — | M5: SÍ | N5: APLICA: medida exigida para la categoría ALTA del sistema (afecta a todas las dimensiones). Exigencia: 'aplica'. Riesgos tratados según AR-2026-01. CCN-STIC 808: 4 requisitos de verificación (1 esenciales). | O5: Procedimiento de adquisición PRO-COMP-02: requisitos de seguridad en pliegos internos, preferencia por productos CPSTIC, evaluación por el Resp. de Seguridad antes de la compra; alineado con la planificación de capacidad. | P5: Checklist de requisitos de seguridad en el módulo de compras del ERP. | Q5: — | R5: Implantada | S5: 1 | T5: PRO-COMP-02; REG-COMP-2026 (evaluaciones) | U5: Compras / Resp. Seguridad | V5: 5.8 Seguridad en la gestión de proyectos; 5.19/5.20 Seguridad en las relaciones con proveedores; 8.29 Pruebas de seguridad en desarrollo y aceptación | W5: CCN-STIC 803, 806, 827, 804/808
A6: Control de acceso | B6: op.acc.3 | C6: Segregación de funciones y tareas | D6: ICAT | E6: n.a. | F6: aplica | G6: + R1 | H6: =IF(OR('Categorización'!F$14="ALTO",'Categorización'!G$14="ALTO",'Categorización'!H$14="ALTO",'Categorización'!I$14="ALTO"),"ALTO",IF(OR('Categorización'!F$14="MEDIO",'Categorización'!G$14="MEDIO",'Categorización'!H$14="MEDIO",'Categorización'!I$14="MEDIO"),"MEDIO","BAJO")) -> ALTO | I6: máx(I=ALTO, C=ALTO, A=ALTO, T=MEDIO) = ALTO | J6: =IF(H6="ALTO",G6,IF(H6="MEDIO",F6,E6)) -> + R1 | K6: R1 Segregación rigurosa | L6: — | M6: SÍ | N6: APLICA: medida vinculada a la(s) dimensión(es) ICAT; nivel exigido ALTO (máx(I=ALTO, C=ALTO, A=ALTO, T=MEDIO) = ALTO). Exigencia: '+ R1'. Riesgos tratados según AR-2026-01. CCN-STIC 808: 6 requisitos de verificación (0 esenciales). | O6: Segregación rigurosa (R1): desarrollo / operación / auditoría de seguridad en equipos distintos; configuración de seguridad ≠ operación; nadie audita su propia actividad; matriz SoD revisada semestralmente. | P6: Controles SoD en IGA (reglas de incompatibilidad); entornos separados; acceso de auditoría de solo lectura a logs (SIEM). | Q6: — | R6: Implantada | S6: 1 | T6: MAT-SOD-01; informe semestral SoD (IGA) | U6: Responsable de Seguridad | V6: 5.3 Segregación de funciones; 8.2 Derechos de acceso privilegiado | W6: CCN-STIC 804/808, 821
A7: Control de acceso | B7: op.acc.4 | C7: Proceso de gestión de derechos de acceso | D7: ICAT | E7: aplica | F7: aplica | G7: aplica | H7: =IF(OR('Categorización'!F$14="ALTO",'Categorización'!G$14="ALTO",'Categorización'!H$14="ALTO",'Categorización'!I$14="ALTO"),"ALTO",IF(OR('Categorización'!F$14="MEDIO",'Categorización'!G$14="MEDIO",'Categorización'!H$14="MEDIO",'Categorización'!I$14="MEDIO"),"MEDIO","BAJO")) -> ALTO | I7: máx(I=ALTO, C=ALTO, A=ALTO, T=MEDIO) = ALTO | J7: =IF(H7="ALTO",G7,IF(H7="MEDIO",F7,E7)) -> aplica | K7: — | L7: — | M7: SÍ | N7: APLICA: medida vinculada a la(s) dimensión(es) ICAT; nivel exigido ALTO (máx(I=ALTO, C=ALTO, A=ALTO, T=MEDIO) = ALTO). Exigencia: 'aplica'. Riesgos tratados según AR-2026-01. CCN-STIC 808: 6 requisitos de verificación (4 esenciales). | O7: Procedimiento PRO-IAM-03: solicitud-aprobación-provisión-revisión-revocación; aprobación del propietario del activo; revisión semestral de accesos (recertificación) y trimestral de privilegiados. | P7: Workflow de aprobación en IGA; recertificación automática; revocación inmediata al causar baja en RRHH. | Q7: — | R7: Implantada | S7: 1 | T7: PRO-IAM-03; campañas de recertificación 2026-S1; tickets | U7: Responsable del Sistema | V7: 5.18 Derechos de acceso; 8.2 Derechos de acceso privilegiado; 5.15 Control de acceso | W7: CCN-STIC 804/808, 821
A8: Explotación | B8: op.exp.1 | C8: Inventario de activos | D8: Categoría | E8: aplica | F8: aplica | G8: aplica | H8: =IF('Categorización'!$E$15="ALTA","ALTO",IF('Categorización'!$E$15="MEDIA","MEDIO","BAJO")) -> ALTO | I8: Categoría del sistema = ALTA | J8: =IF(H8="ALTO",G8,IF(H8="MEDIO",F8,E8)) -> aplica | K8: — | L8: — | M8: SÍ | N8: APLICA: medida exigida para la categoría ALTA del sistema (afecta a todas las dimensiones). Exigencia: 'aplica'. Riesgos tratados según AR-2026-01. CCN-STIC 808: 3 requisitos de verificación (2 esenciales). | O8: Inventario de activos INV-01 (hardware, software, información, servicios, comunicaciones, instalaciones, personal) con responsable, ubicación, categoría y dependencias; actualización con cada cambio autorizado; reconciliación trimestral. | P8: CMDB (ITSM) alimentada por descubrimiento automático (agentes + escaneo de red) y gestión de licencias; SBOM para software propio. | Q8: — | R8: Implantada | S8: 1 | T8: INV-01 (export CMDB 09/2026); PRO-INV-01; informe de reconciliación | U8: Jefe de Operaciones TI | V8: 5.9 Inventario de información y otros activos; 5.12 Clasificación | W8: CCN-STIC 804/808, 817, 5xx/6xx
A9: Explotación | B9: op.exp.2 | C9: Configuración de seguridad | D9: Categoría | E9: aplica | F9: aplica | G9: aplica | H9: =IF('Categorización'!$E$15="ALTA","ALTO",IF('Categorización'!$E$15="MEDIA","MEDIO","BAJO")) -> ALTO | I9: Categoría del sistema = ALTA | J9: =IF(H9="ALTO",G9,IF(H9="MEDIO",F9,E9)) -> aplica | K9: — | L9: — | M9: SÍ | N9: APLICA: medida exigida para la categoría ALTA del sistema (afecta a todas las dimensiones). Exigencia: 'aplica'. Riesgos tratados según AR-2026-01. CCN-STIC 808: 4 requisitos de verificación (3 esenciales). | O9: Guías de bastionado por tecnología (CCN-STIC 5xx/6xx y CIS Benchmarks) aprobadas; mínima funcionalidad; cuentas por defecto retiradas; principio de seguridad por defecto; checklist obligatoria antes del paso a producción. | P9: Imágenes maestras bastionadas (golden images); GPO/Ansible para configuración; escaneo de cumplimiento de configuración (SCAP) semanal; DLP en endpoints. | Q9: — | R9: Implantada | S9: 1 | T9: PRO-HARD-01; checklists CFG-xx; informes SCAP | U9: Jefe de Operaciones TI | V9: 8.9 Gestión de la configuración; 8.19 Instalación de software; 8.12 Prevención de fuga de datos | W9: CCN-STIC 804/808, 817, 5xx/6xx
A10: Explotación | B10: op.exp.5 | C10: Gestión de cambios | D10: Categoría | E10: n.a. | F10: aplica | G10: + R1 | H10: =IF('Categorización'!$E$15="ALTA","ALTO",IF('Categorización'!$E$15="MEDIA","MEDIO","BAJO")) -> ALTO | I10: Categoría del sistema = ALTA | J10: =IF(H10="ALTO",G10,IF(H10="MEDIO",F10,E10)) -> + R1 | K10: R1 Prevención de fallos | L10: — | M10: SÍ | N10: APLICA: medida exigida para la categoría ALTA del sistema (afecta a todas las dimensiones). Exigencia: '+ R1'. Riesgos tratados según AR-2026-01. CCN-STIC 808: 10 requisitos de verificación (0 esenciales). | O10: Gestión de cambios PRO-CHG-01: CAB semanal, evaluación de impacto en seguridad, plan de marcha atrás, cambios de emergencia; prevención de fallos (R1) mediante pruebas obligatorias y análisis de riesgos del cambio. | P10: Módulo de cambios en ITSM con aprobación electrónica; entornos dev/pre/pro; despliegues automatizados con rollback. | Q10: — | R10: Implantada | S10: 1 | T10: PRO-CHG-01; actas CAB; RFC-2026-xxx | U10: Responsable del Sistema | V10: 8.32 Gestión de cambios; 8.29 Pruebas de seguridad; 8.31 Separación de entornos | W10: CCN-STIC 804/808, 817, 5xx/6xx
A11: Explotación | B11: op.exp.9 | C11: Registro de la gestión de incidentes | D11: Categoría | E11: aplica | F11: aplica | G11: aplica | H11: =IF('Categorización'!$E$15="ALTA","ALTO",IF('Categorización'!$E$15="MEDIA","MEDIO","BAJO")) -> ALTO | I11: Categoría del sistema = ALTA | J11: =IF(H11="ALTO",G11,IF(H11="MEDIO",F11,E11)) -> aplica | K11: — | L11: — | M11: SÍ | N11: APLICA: medida exigida para la categoría ALTA del sistema (afecta a todas las dimensiones). Exigencia: 'aplica'. Riesgos tratados según AR-2026-01. CCN-STIC 808: 5 requisitos de verificación (3 esenciales). | O11: Registro de la gestión de incidentes: apertura, cronología, decisiones, evidencias, cierre, lecciones aprendidas; alimenta el análisis de riesgos y las métricas; conservación 5 años. | P11: Módulo de incidentes en ITSM enlazado con el SIEM; custodia de evidencias con cadena de custodia (hash, firma) según PRO-INC-02. | Q11: — | R11: Implantada | S11: 1 | T11: REG-INC-2026 (37 incidentes); informes post-incidente; PRO-INC-02 | U11: SOC (SecOps Iberia) / Resp. Seguridad | V11: 5.26 Respuesta a incidentes; 5.27 Aprender de incidentes; 5.28 Recogida de evidencias | W11: CCN-STIC 804/808, 817, 5xx/6xx
A12: Recursos externos | B12: op.ext.1 | C12: Contratación y acuerdos de nivel de servicio | D12: Categoría | E12: n.a. | F12: aplica | G12: aplica | H12: =IF('Categorización'!$E$15="ALTA","ALTO",IF('Categorización'!$E$15="MEDIA","MEDIO","BAJO")) -> ALTO | I12: Categoría del sistema = ALTA | J12: =IF(H12="ALTO",G12,IF(H12="MEDIO",F12,E12)) -> aplica | K12: — | L12: — | M12: SÍ | N12: APLICA: medida exigida para la categoría ALTA del sistema (afecta a todas las dimensiones). Exigencia: 'aplica'. Riesgos tratados según AR-2026-01. CCN-STIC 808: 2 requisitos de verificación (0 esenciales). | O12: Contratación de terceros con cláusulas ENS/RGPD (modelo CON-SEC-01): roles y responsabilidades, medidas exigidas, ANS con penalizaciones, derecho de auditoría, notificación de incidentes ≤24 h, subcontratación autorizada; acuerdos de confidencialidad. | P12: Registro de proveedores en el ERP con estado de evaluación de seguridad; portal de intercambio seguro. | Q12: — | R12: Implantada | S12: 1 | T12: Contratos SecOps Iberia, NubeAdmin, custodia de soportes; CON-SEC-01; REG-PROV-01 | U12: Compras / Resp. Seguridad | V12: 5.19 Seguridad en relaciones con proveedores; 5.20 Seguridad en acuerdos con proveedores; 6.6 Acuerdos de confidencialidad; 5.14 Transferencia de información | W12: CCN-STIC 811, 830, 804/808
A13: Recursos externos | B13: op.ext.2 | C13: Gestión diaria | D13: Categoría | E13: n.a. | F13: aplica | G13: aplica | H13: =IF('Categorización'!$E$15="ALTA","ALTO",IF('Categorización'!$E$15="MEDIA","MEDIO","BAJO")) -> ALTO | I13: Categoría del sistema = ALTA | J13: =IF(H13="ALTO",G13,IF(H13="MEDIO",F13,E13)) -> aplica | K13: — | L13: — | M13: SÍ | N13: APLICA: medida exigida para la categoría ALTA del sistema (afecta a todas las dimensiones). Exigencia: 'aplica'. Riesgos tratados según AR-2026-01. CCN-STIC 808: 4 requisitos de verificación (0 esenciales). | O13: Gestión diaria de servicios externos (PRO-PROV-02): responsable interno por proveedor, seguimiento mensual de ANS e indicadores, gestión de incidencias y cambios del proveedor, reuniones de servicio. | P13: Cuadro de mando de ANS (Power BI) con datos del ITSM; canal cifrado para coordinación de incidentes. | Q13: — | R13: Implantada | S13: 1 | T13: Informes mensuales de servicio; actas de seguimiento | U13: Jefe de Operaciones TI | V13: 5.22 Seguimiento, revisión y gestión de cambios de servicios de proveedores | W13: CCN-STIC 811, 830, 804/808
A14: Continuidad del servicio | B14: op.cont.2 | C14: Plan de continuidad | D14: D | E14: n.a. | F14: n.a. | G14: aplica | H14: =IF(OR('Categorización'!E$14="ALTO"),"ALTO",IF(OR('Categorización'!E$14="MEDIO"),"MEDIO","BAJO")) -> ALTO | I14: máx(D=ALTO) = ALTO | J14: =IF(H14="ALTO",G14,IF(H14="MEDIO",F14,E14)) -> aplica | K14: — | L14: — | M14: SÍ | N14: APLICA: medida vinculada a la(s) dimensión(es) D; nivel exigido ALTO (máx(D=ALTO) = ALTO). Exigencia: 'aplica'. Riesgos tratados según AR-2026-01. CCN-STIC 808: 7 requisitos de verificación (0 esenciales). | O14: Plan de Continuidad PCN-01 y Plan de Recuperación ante Desastres DRP-01: activación, roles, comunicación, procedimientos de recuperación por servicio, retorno a la normalidad; plan de emergencia y contingencia integrado; revisión anual. | P14: Replicación síncrona de almacenamiento entre CPD (14 km), orquestación de conmutación, copias inmutables externas; runbooks automatizados. | Q14: — | R14: Implantada | S14: 1 | T14: PCN-01 v3; DRP-01; árbol de llamadas | U14: Responsable del Sistema | V14: 5.29 Seguridad durante la disrupción; 5.30 Preparación TIC continuidad | W14: CCN-STIC 804/808; ISO 22301
A15: Continuidad del servicio | B15: op.cont.3 | C15: Pruebas periódicas | D15: D | E15: n.a. | F15: n.a. | G15: aplica | H15: =IF(OR('Categorización'!E$14="ALTO"),"ALTO",IF(OR('Categorización'!E$14="MEDIO"),"MEDIO","BAJO")) -> ALTO | I15: máx(D=ALTO) = ALTO | J15: =IF(H15="ALTO",G15,IF(H15="MEDIO",F15,E15)) -> aplica | K15: — | L15: — | M15: SÍ | N15: APLICA: medida vinculada a la(s) dimensión(es) D; nivel exigido ALTO (máx(D=ALTO) = ALTO). Exigencia: 'aplica'. Riesgos tratados según AR-2026-01. CCN-STIC 808: 5 requisitos de verificación (0 esenciales). | O15: Programa anual de pruebas: prueba de mesa (T1), conmutación parcial de servicio (T2), conmutación completa de CPD (T4); informe y acciones correctivas; participación de las consejerías. | P15: Entorno de pruebas de recuperación aislado; automatización de restauraciones. | Q15: — | R15: Implantada | S15: 1 | T15: REG-CONT-03 (pruebas 2025-2026); informe de conmutación 11/2025 | U15: Jefe de Operaciones TI | V15: 5.30 Preparación TIC continuidad (pruebas); 8.14 Redundancia | W15: CCN-STIC 804/808; ISO 22301
A16: Continuidad del servicio | B16: op.cont.4 | C16: Medios alternativos | D16: D | E16: n.a. | F16: n.a. | G16: aplica | H16: =IF(OR('Categorización'!E$14="ALTO"),"ALTO",IF(OR('Categorización'!E$14="MEDIO"),"MEDIO","BAJO")) -> ALTO | I16: máx(D=ALTO) = ALTO | J16: =IF(H16="ALTO",G16,IF(H16="MEDIO",F16,E16)) -> aplica | K16: — | L16: — | M16: SÍ | N16: APLICA: medida vinculada a la(s) dimensión(es) D; nivel exigido ALTO (máx(D=ALTO) = ALTO). Exigencia: 'aplica'. Riesgos tratados según AR-2026-01. CCN-STIC 808: 3 requisitos de verificación (0 esenciales). | O16: Medios alternativos garantizados: CPD de respaldo activo-pasivo, personal alternativo formado (matriz de sustitución), instalaciones alternativas de trabajo (teletrabajo seguro + oficina de respaldo), proveedores alternativos de comunicaciones, contratos de continuidad con SecOps y NubeAdmin. | P16: Doble operador de comunicaciones con rutas físicas distintas; capacidad de reserva en cloud ENS ALTA; VPN dimensionada para el 100 % de la plantilla. | Q16: — | R16: Implantada | S16: 1 | T16: DRP-01 anexo B (medios alternativos); contratos; MAT-SUST-01 | U16: Responsable del Sistema | V16: 8.14 Redundancia de instalaciones de tratamiento; 5.30 Preparación TIC continuidad | W16: CCN-STIC 804/808; ISO 22301
A17: Protección de las instalaciones e infraestructuras | B17: mp.if.1 | C17: Áreas separadas y con control de acceso | D17: Categoría | E17: aplica | F17: aplica | G17: aplica | H17: =IF('Categorización'!$E$15="ALTA","ALTO",IF('Categorización'!$E$15="MEDIA","MEDIO","BAJO")) -> ALTO | I17: Categoría del sistema = ALTA | J17: =IF(H17="ALTO",G17,IF(H17="MEDIO",F17,E17)) -> aplica | K17: — | L17: — | M17: SÍ | N17: APLICA: medida exigida para la categoría ALTA del sistema (afecta a todas las dimensiones). Exigencia: 'aplica'. Riesgos tratados según AR-2026-01. CCN-STIC 808: 4 requisitos de verificación (2 esenciales). | O17: Zonificación de instalaciones (pública, oficinas, salas técnicas, CPD) con control de acceso por zona y autorización nominal; visitantes acompañados; revisión trimestral de accesos. | P17: Control de acceso con tarjeta + PIN en oficinas; tarjeta + biometría en CPD y salas técnicas; esclusa en CPD; CCTV con retención 30 días. | Q17: — | R17: Implantada | S17: 1 | T17: PRO-FIS-01; planos de zonificación; REG-ACC-FIS | U17: Facilities / Resp. del Sistema | V17: 7.1 Perímetros de seguridad física; 7.2 Entradas físicas; 7.3 Oficinas, salas e instalaciones; 7.4 Vigilancia física; 7.6 Trabajo en áreas seguras | W17: CCN-STIC 804/808
A18: Protección de las instalaciones e infraestructuras | B18: mp.if.2 | C18: Identificación de las personas | D18: Categoría | E18: aplica | F18: aplica | G18: aplica | H18: =IF('Categorización'!$E$15="ALTA","ALTO",IF('Categorización'!$E$15="MEDIA","MEDIO","BAJO")) -> ALTO | I18: Categoría del sistema = ALTA | J18: =IF(H18="ALTO",G18,IF(H18="MEDIO",F18,E18)) -> aplica | K18: — | L18: — | M18: SÍ | N18: APLICA: medida exigida para la categoría ALTA del sistema (afecta a todas las dimensiones). Exigencia: 'aplica'. Riesgos tratados según AR-2026-01. CCN-STIC 808: 3 requisitos de verificación (1 esenciales). | O18: Identificación de todas las personas: tarjeta visible, registro de visitas (nombre, empresa, motivo, hora, acompañante), identificación del personal de proveedores. | P18: Sistema de gestión de visitas con registro electrónico; tornos en recepción. | Q18: — | R18: Implantada | S18: 1 | T18: REG-VIS-2026; PRO-FIS-01 | U18: Facilities / Resp. del Sistema | V18: 7.2 Controles físicos de entrada; 7.4 Vigilancia de la seguridad física | W18: CCN-STIC 804/808
A19: Protección de las instalaciones e infraestructuras | B19: mp.if.3 | C19: Acondicionamiento de los locales | D19: Categoría | E19: aplica | F19: aplica | G19: aplica | H19: =IF('Categorización'!$E$15="ALTA","ALTO",IF('Categorización'!$E$15="MEDIA","MEDIO","BAJO")) -> ALTO | I19: Categoría del sistema = ALTA | J19: =IF(H19="ALTO",G19,IF(H19="MEDIO",F19,E19)) -> aplica | K19: — | L19: — | M19: SÍ | N19: APLICA: medida exigida para la categoría ALTA del sistema (afecta a todas las dimensiones). Exigencia: 'aplica'. Riesgos tratados según AR-2026-01. CCN-STIC 808: 5 requisitos de verificación (2 esenciales). | O19: Acondicionamiento de locales según buenas prácticas (TIA-942 Tier III en CPD): temperatura y humedad controladas, protección del cableado, protección frente a interferencias, no señalización de la sala. | P19: Climatización redundante N+1; monitorización ambiental (DCIM) con alertas; cableado estructurado en bandejas cerradas y etiquetado. | Q19: — | R19: Implantada | S19: 1 | T19: Informe DCIM; certificado de instalación | U19: Facilities / Resp. del Sistema | V19: 7.5 Protección contra amenazas físicas y ambientales; 7.8 Ubicación y protección de equipos; 7.12 Seguridad del cableado | W19: CCN-STIC 804/808
A20: Protección de las instalaciones e infraestructuras | B20: mp.if.5 | C20: Protección frente a incendios | D20: D | E20: aplica | F20: aplica | G20: aplica | H20: =IF(OR('Categorización'!E$14="ALTO"),"ALTO",IF(OR('Categorización'!E$14="MEDIO"),"MEDIO","BAJO")) -> ALTO | I20: máx(D=ALTO) = ALTO | J20: =IF(H20="ALTO",G20,IF(H20="MEDIO",F20,E20)) -> aplica | K20: — | L20: — | M20: SÍ | N20: APLICA: medida vinculada a la(s) dimensión(es) D; nivel exigido ALTO (máx(D=ALTO) = ALTO). Exigencia: 'aplica'. Riesgos tratados según AR-2026-01. CCN-STIC 808: 3 requisitos de verificación (3 esenciales). | O20: Protección contra incendios conforme a normativa (CTE, RIPCI): plan de autoprotección, inspecciones anuales, formación de equipos de emergencia. | P20: Detección temprana por aspiración (VESDA), extinción por gas inerte en CPD, extintores y BIE en oficinas, sectorización RF-90. | Q20: — | R20: Implantada | S20: 1 | T20: Certificado de mantenimiento PCI 2026; plan de autoprotección | U20: Facilities / Resp. del Sistema | V20: 7.5 Protección contra amenazas físicas y ambientales | W20: CCN-STIC 804/808
A21: Protección de las instalaciones e infraestructuras | B21: mp.if.7 | C21: Registro de entrada y salida de equipamiento | D21: Categoría | E21: aplica | F21: aplica | G21: aplica | H21: =IF('Categorización'!$E$15="ALTA","ALTO",IF('Categorización'!$E$15="MEDIA","MEDIO","BAJO")) -> ALTO | I21: Categoría del sistema = ALTA | J21: =IF(H21="ALTO",G21,IF(H21="MEDIO",F21,E21)) -> aplica | K21: — | L21: — | M21: SÍ | N21: APLICA: medida exigida para la categoría ALTA del sistema (afecta a todas las dimensiones). Exigencia: 'aplica'. Riesgos tratados según AR-2026-01. CCN-STIC 808: 2 requisitos de verificación (1 esenciales). | O21: Registro de entrada y salida de equipamiento (PRO-FIS-02): autorización previa, identificación del equipo (etiqueta/serie), portador, fecha/hora, destino. | P21: Registro electrónico en el ITSM enlazado con la CMDB; etiquetas RFID en activos del CPD con detección en puertas. | Q21: — | R21: Implantada | S21: 1 | T21: REG-EQ-2026; PRO-FIS-02 | U21: Facilities / Resp. del Sistema | V21: 7.2 Controles físicos de entrada; 7.9 Seguridad de activos fuera de las instalaciones; 7.10 Soportes de almacenamiento | W21: CCN-STIC 804/808
A22: Gestión del personal | B22: mp.per.1 | C22: Caracterización del puesto de trabajo | D22: Categoría | E22: n.a. | F22: aplica | G22: aplica | H22: =IF('Categorización'!$E$15="ALTA","ALTO",IF('Categorización'!$E$15="MEDIA","MEDIO","BAJO")) -> ALTO | I22: Categoría del sistema = ALTA | J22: =IF(H22="ALTO",G22,IF(H22="MEDIO",F22,E22)) -> aplica | K22: — | L22: — | M22: SÍ | N22: APLICA: medida exigida para la categoría ALTA del sistema (afecta a todas las dimensiones). Exigencia: 'aplica'. Riesgos tratados según AR-2026-01. CCN-STIC 808: 2 requisitos de verificación (0 esenciales). | O22: Descripción de cada puesto con responsabilidades de seguridad, nivel de acceso a información y requisitos (habilitación, antecedentes cuando lo permite la ley, cláusulas); selección con verificación de referencias y titulación; puestos de confianza (administradores, SOC) con requisitos reforzados. | P22: Perfiles de puesto en el sistema de RRHH vinculados a roles IGA. | Q22: — | R22: Implantada | S22: 1 | T22: Catálogo de puestos CAT-PUE-01; PRO-RRHH-01 selección | U22: Dirección de Personas (RRHH) | V22: 6.1 Selección (cribado); 6.2 Términos y condiciones de empleo; 5.2 Roles y responsabilidades | W22: CCN-STIC 804/808, 821
A23: Gestión del personal | B23: mp.per.3 | C23: Concienciación | D23: Categoría | E23: aplica | F23: aplica | G23: aplica | H23: =IF('Categorización'!$E$15="ALTA","ALTO",IF('Categorización'!$E$15="MEDIA","MEDIO","BAJO")) -> ALTO | I23: Categoría del sistema = ALTA | J23: =IF(H23="ALTO",G23,IF(H23="MEDIO",F23,E23)) -> aplica | K23: — | L23: — | M23: SÍ | N23: APLICA: medida exigida para la categoría ALTA del sistema (afecta a todas las dimensiones). Exigencia: 'aplica'. Riesgos tratados según AR-2026-01. CCN-STIC 808: 4 requisitos de verificación (3 esenciales). | O23: Programa de concienciación anual: normativa, gestión de incidentes (cómo reportar), phishing, uso de dispositivos; sesiones de acogida; campañas trimestrales; medición de eficacia. | P23: Plataforma de e-learning y simulaciones de phishing (tasa de clic 3,1 % en 2026-Q2); comunicaciones internas. | Q23: — | R23: Implantada | S23: 1 | T23: PLAN-CONC-2026; registros de asistencia; informes de simulación | U23: Responsable de Seguridad | V23: 6.3 Concienciación, educación y formación en seguridad | W23: CCN-STIC 804/808, 821
A24: Gestión del personal | B24: mp.per.4 | C24: Formación | D24: Categoría | E24: aplica | F24: aplica | G24: aplica | H24: =IF('Categorización'!$E$15="ALTA","ALTO",IF('Categorización'!$E$15="MEDIA","MEDIO","BAJO")) -> ALTO | I24: Categoría del sistema = ALTA | J24: =IF(H24="ALTO",G24,IF(H24="MEDIO",F24,E24)) -> aplica | K24: — | L24: — | M24: SÍ | N24: APLICA: medida exigida para la categoría ALTA del sistema (afecta a todas las dimensiones). Exigencia: 'aplica'. Riesgos tratados según AR-2026-01. CCN-STIC 808: 6 requisitos de verificación (2 esenciales). | O24: Plan de formación específico por rol (administradores, desarrolladores, SOC, gestores): configuración segura, detección y reacción a incidentes, gestión de la información y soportes, desarrollo seguro; formación ENS (CCN) para el equipo de seguridad. | P24: Registro de competencias en RRHH; certificaciones (CCN-CERT Ángeles, ISO 27001 LA, SANS). | Q24: — | R24: Implantada | S24: 1 | T24: PLAN-FORM-2026; registros de formación; matriz de competencias | U24: Dirección de Personas (RRHH) | V24: 6.3 Concienciación, educación y formación; Cl. 7.2 Competencia | W24: CCN-STIC 804/808, 821
A25: Protección de las comunicaciones | B25: mp.com.1 | C25: Perímetro seguro | D25: Categoría | E25: aplica | F25: aplica | G25: aplica | H25: =IF('Categorización'!$E$15="ALTA","ALTO",IF('Categorización'!$E$15="MEDIA","MEDIO","BAJO")) -> ALTO | I25: Categoría del sistema = ALTA | J25: =IF(H25="ALTO",G25,IF(H25="MEDIO",F25,E25)) -> aplica | K25: — | L25: — | M25: SÍ | N25: APLICA: medida exigida para la categoría ALTA del sistema (afecta a todas las dimensiones). Exigencia: 'aplica'. Riesgos tratados según AR-2026-01. CCN-STIC 808: 4 requisitos de verificación (3 esenciales). | O25: Perímetro seguro: toda conexión al exterior pasa por cortafuegos; flujos autorizados y documentados; revisión trimestral de reglas; dos líneas de defensa de fabricantes distintos. | P25: Cortafuegos NG en alta disponibilidad (CPSTIC), IPS, DMZ multicapa, proxy saliente, DNS seguro; gestión de reglas con herramienta de análisis. | Q25: — | R25: Implantada | S25: 1 | T25: ARQ-02; REG-FW-REV (revisiones trimestrales) | U25: Jefe de Operaciones TI | V25: 8.20 Seguridad de redes; 8.21 Seguridad de servicios de red; 8.22 Segregación de redes | W25: CCN-STIC 807, 811, 804/808
A26: Protección de los soportes de información | B26: mp.si.3 | C26: Custodia | D26: Categoría | E26: aplica | F26: aplica | G26: aplica | H26: =IF('Categorización'!$E$15="ALTA","ALTO",IF('Categorización'!$E$15="MEDIA","MEDIO","BAJO")) -> ALTO | I26: Categoría del sistema = ALTA | J26: =IF(H26="ALTO",G26,IF(H26="MEDIO",F26,E26)) -> aplica | K26: — | L26: — | M26: SÍ | N26: APLICA: medida exigida para la categoría ALTA del sistema (afecta a todas las dimensiones). Exigencia: 'aplica'. Riesgos tratados según AR-2026-01. CCN-STIC 808: 3 requisitos de verificación (1 esenciales). | O26: Custodia de soportes: control de acceso a armarios ignífugos y sala de soportes, responsable de custodia, registro de entrega/devolución, respeto de condiciones del fabricante. | P26: Armarios ignífugos con cerradura electrónica y registro; sala de soportes bajo control de acceso biométrico; custodia externa con empresa certificada. | Q26: — | R26: Implantada | S26: 1 | T26: PRO-SOP-01; REG-CUST-SOP | U26: Jefe de Operaciones TI | V26: 7.10 Soportes de almacenamiento; 5.9 Inventario; 5.10 Uso aceptable | W26: CCN-STIC 807, 804/808
A27: Protección de los soportes de información | B27: mp.si.4 | C27: Transporte | D27: Categoría | E27: aplica | F27: aplica | G27: aplica | H27: =IF('Categorización'!$E$15="ALTA","ALTO",IF('Categorización'!$E$15="MEDIA","MEDIO","BAJO")) -> ALTO | I27: Categoría del sistema = ALTA | J27: =IF(H27="ALTO",G27,IF(H27="MEDIO",F27,E27)) -> aplica | K27: — | L27: — | M27: SÍ | N27: APLICA: medida exigida para la categoría ALTA del sistema (afecta a todas las dimensiones). Exigencia: 'aplica'. Riesgos tratados según AR-2026-01. CCN-STIC 808: 6 requisitos de verificación (1 esenciales). | O27: Transporte de soportes (PRO-SOP-02): registro de salida/entrada, responsable designado, cifrado, precinto, empresa de transporte con contrato de seguridad, verificación de recepción. | P27: Maletines con cierre y precinto numerado; geolocalización del transporte; cinta cifrada. | Q27: — | R27: Implantada | S27: 1 | T27: REG-TRANS-SOP; contrato de custodia externa | U27: Jefe de Operaciones TI | V27: 7.10 Soportes de almacenamiento; 7.9 Activos fuera de las instalaciones; 5.14 Transferencia | W27: CCN-STIC 807, 804/808
A28: Protección de la información | B28: mp.info.1 | C28: Datos personales | D28: Categoría | E28: aplica | F28: aplica | G28: aplica | H28: =IF('Categorización'!$E$15="ALTA","ALTO",IF('Categorización'!$E$15="MEDIA","MEDIO","BAJO")) -> ALTO | I28: Categoría del sistema = ALTA | J28: =IF(H28="ALTO",G28,IF(H28="MEDIO",F28,E28)) -> aplica | K28: — | L28: — | M28: SÍ | N28: APLICA: medida exigida para la categoría ALTA del sistema (afecta a todas las dimensiones). Exigencia: 'aplica'. Riesgos tratados según AR-2026-01. CCN-STIC 808: 8 requisitos de verificación (3 esenciales). | O28: Cumplimiento RGPD/LOPDGDD: registro de actividades de tratamiento, contratos de encargado con las consejerías, DPIA para S-02 y S-03, DPD nombrado, procedimiento de brechas (72 h a la AEPD vía el responsable), minimización y limitación de acceso; coordinación DPD–Resp. Seguridad. | P28: Cifrado y seudonimización de datos de categoría especial en BD; enmascaramiento en entornos no productivos; registro de accesos a datos personales (auditoría en BD). | Q28: — | R28: Implantada | S28: 1 | T28: RAT-2026; DPIA-S02, DPIA-S03; contratos de encargado; PRO-BRECHA-01 | U28: DPD / Resp. Seguridad | V28: 5.34 Privacidad y protección de la PII; 5.31 Requisitos legales; 8.11 Enmascaramiento | W28: CCN-STIC 807, 804/808
A29: Protección de los servicios | B29: mp.s.1 | C29: Protección del correo electrónico | D29: Categoría | E29: aplica | F29: aplica | G29: aplica | H29: =IF('Categorización'!$E$15="ALTA","ALTO",IF('Categorización'!$E$15="MEDIA","MEDIO","BAJO")) -> ALTO | I29: Categoría del sistema = ALTA | J29: =IF(H29="ALTO",G29,IF(H29="MEDIO",F29,E29)) -> aplica | K29: — | L29: — | M29: SÍ | N29: APLICA: medida exigida para la categoría ALTA del sistema (afecta a todas las dimensiones). Exigencia: 'aplica'. Riesgos tratados según AR-2026-01. CCN-STIC 808: 6 requisitos de verificación (4 esenciales). | O29: Protección del correo: normas de uso, prohibición de reenvío automático externo, cifrado para información CONFIDENCIAL/RESERVADA, concienciación anti-phishing. | P29: Pasarela de correo con antispam/antimalware/sandbox; SPF, DKIM, DMARC (p=reject); cifrado S/MIME y TLS obligatorio con las consejerías; DLP saliente; limpieza de metadatos. | Q29: — | R29: Implantada | S29: 1 | T29: Configuración de pasarela; informe DMARC; NOR-01 | U29: Jefe de Operaciones TI | V29: 5.14 Transferencia de información; 8.7 Malware; 8.24 Criptografía; 8.23 Filtrado web | W29: CCN-STIC 804/808, 807
A30: Control de acceso | B30: op.acc.5 | C30: Mecanismo de autenticación (usuarios externos) | D30: ICAT | E30: + [R1 o R2 o R3 o R4] | F30: + [R2 o R3 o R4] + R5 | G30: + [R2 o R3 o R4] + R5 | H30: =IF(OR('Categorización'!F$14="ALTO",'Categorización'!G$14="ALTO",'Categorización'!H$14="ALTO",'Categorización'!I$14="ALTO"),"ALTO",IF(OR('Categorización'!F$14="MEDIO",'Categorización'!G$14="MEDIO",'Categorización'!H$14="MEDIO",'Categorización'!I$14="MEDIO"),"MEDIO","BAJO")) -> ALTO | I30: máx(I=ALTO, C=ALTO, A=ALTO, T=MEDIO) = ALTO | J30: =IF(H30="ALTO",G30,IF(H30="MEDIO",F30,E30)) -> + [R2 o R3 o R4] + R5 | K30: [R2 Contraseña + OTP o R3 Certificados o R4 Certificados en dispositivo físico] R5 Registro | L30: Alternativa elegida: R2 (Cl@ve PIN/permanente) y R3/R4 (certificado/DNIe); + R5 registro. Cumple '[R2 o R3 o R4] + R5'. | M30: SÍ | N30: APLICA: medida vinculada a la(s) dimensión(es) ICAT; nivel exigido ALTO (máx(I=ALTO, C=ALTO, A=ALTO, T=MEDIO) = ALTO). Exigencia: '+ [R2 o R3 o R4] + R5'. Riesgos tratados según AR-2026-01. CCN-STIC 808: 14 requisitos de verificación (10 esenciales). | O30: Usuarios externos (ciudadanos y empleados públicos de las consejerías): política de autenticación NOR-05; registro previo de identidad (R5) mediante Cl@ve / certificado o presencial en oficinas de la consejería; información sobre obligaciones y último acceso. | P30: Integración con Cl@ve (Cl@ve PIN/permanente con OTP = R2; certificado electrónico cualificado = R3; DNIe = R4) para ciudadanos; empleados de las consejerías vía federación SAML con MFA de su organismo; bloqueo tras 5 intentos; sin contraseñas por defecto. | Q30: — | R30: Implantada | S30: 1 | T30: NOR-05; diseño de integración Cl@ve DIS-CLAVE-01; convenio de federación | U30: Responsable del Sistema | V30: 5.17 Información de autenticación; 8.5 Autenticación segura; 5.16 Gestión de identidades | W30: CCN-STIC 804/808, 821
A31: Protección de las comunicaciones | B31: mp.com.4 | C31: Separación de flujos de información en la red | D31: Categoría | E31: n.a. | F31: + [R1 o R2 o R3] | G31: + [R2 o R3] + R4 | H31: =IF('Categorización'!$E$15="ALTA","ALTO",IF('Categorización'!$E$15="MEDIA","MEDIO","BAJO")) -> ALTO | I31: Categoría del sistema = ALTA | J31: =IF(H31="ALTO",G31,IF(H31="MEDIO",F31,E31)) -> + [R2 o R3] + R4 | K31: [R2 Segmentación lógica avanzada o R3 Segmentación física] R4 Puntos de interconexión | L31: Alternativa elegida: R2 (segmentación lógica avanzada) + R4; R3 físico adicional para gestión. Cumple '[R2 o R3] + R4'. | M31: SÍ | N31: APLICA: medida exigida para la categoría ALTA del sistema (afecta a todas las dimensiones). Exigencia: '+ [R2 o R3] + R4'. Riesgos tratados según AR-2026-01. CCN-STIC 808: 6 requisitos de verificación (0 esenciales). | O31: Separación de flujos: segmentación lógica avanzada (R2) por función y nivel (usuarios, administración, servidores por servicio, DMZ, gestión, backup, OT/IoT); control de puntos de interconexión (R4) entre segmentos con cortafuegos y monitorización; segmentación física (R3) para la red de gestión fuera de banda. | P31: VLAN + VRF + microsegmentación (NSX) con políticas por carga; cortafuegos internos entre zonas; red de gestión OOB física; NAC. | Q31: — | R31: Implantada | S31: 1 | T31: ARQ-02 (matriz de zonas y flujos); revisión semestral de políticas de microsegmentación | U31: Jefe de Operaciones TI | V31: 8.22 Segregación de redes; 8.20 Seguridad de redes | W31: CCN-STIC 807, 811, 804/808
A32: Control de acceso | B32: op.acc.6 | C32: Mecanismo de autenticación (usuarios de la organización) | D32: ICAT | E32: + [R1 o R2 o R3 o R4] + R8 + R9 | F32: + [R1 o R2 o R3 o R4] + R5 + R8 + R9 | G32: + [R1 o R2 o R3 o R4] + R5 + R6 + R7 + R8 + R9 | H32: =IF(OR('Categorización'!F$14="ALTO",'Categorización'!G$14="ALTO",'Categorización'!H$14="ALTO",'Categorización'!I$14="ALTO"),"ALTO",IF(OR('Categorización'!F$14="MEDIO",'Categorización'!G$14="MEDIO",'Categorización'!H$14="MEDIO",'Categorización'!I$14="MEDIO"),"MEDIO","BAJO")) -> ALTO | I32: máx(I=ALTO, C=ALTO, A=ALTO, T=MEDIO) = ALTO | J32: =IF(H32="ALTO",G32,IF(H32="MEDIO",F32,E32)) -> + [R1 o R2 o R3 o R4] + R5 + R6 + R7 + R8 + R9 | K32: [R1 Contraseñas o R2 Contraseña + otro factor de autenticación o R3 Certificados o R4 Certificados en dispositivo físico] R5 Registro R6 Limitación de la ventana de acceso R7 Suspensión por no utilización R8 Doble factor para acceso desde o a través de zonas no controladas R9 Acceso remoto (todos los niveles) | L32: Alternativa elegida: R2 para todo el personal y R4 para administradores. Cumple '[R1 o R2 o R3 o R4] + R5 + R6 + R7 + R8 + R9'. | M32: SÍ | N32: APLICA: medida vinculada a la(s) dimensión(es) ICAT; nivel exigido ALTO (máx(I=ALTO, C=ALTO, A=ALTO, T=MEDIO) = ALTO). Exigencia: '+ [R1 o R2 o R3 o R4] + R5 + R6 + R7 + R8 + R9'. Riesgos tratados según AR-2026-01. CCN-STIC 808: 14 requisitos de verificación (7 esenciales). | O32: Usuarios de TechServ: NOR-05 (contraseñas ≥14 caracteres, no reutilización, cambio ante sospecha); registro previo (R5) por RRHH; ventana de acceso limitada por horario y rol para administradores (R6); suspensión a los 45 días sin uso (R7); acceso remoto sólo por VPN con MFA (R8/R9). | P32: MFA obligatorio para todos (R2: contraseña + token FIDO2/app); administradores con certificado en tarjeta criptográfica (R4); AD con políticas de contraseñas y bloqueo; PAM; VPN con MFA y posture check; políticas de horario en AD/PAM; script de suspensión por inactividad. | Q32: — | R32: Implantada | S32: 1 | T32: NOR-05; GPO-AUTH-01; informe PAM; REG-IAM-SUSP | U32: Responsable del Sistema | V32: 8.5 Autenticación segura; 5.17 Información de autenticación; 6.7 Trabajo remoto; 8.1 Dispositivos de usuario | W32: CCN-STIC 804/808, 821
A33: Recursos externos | B33: op.ext.3 | C33: Protección de la cadena de suministro | D33: Categoría | E33: n.a. | F33: n.a. | G33: aplica | H33: =IF('Categorización'!$E$15="ALTA","ALTO",IF('Categorización'!$E$15="MEDIA","MEDIO","BAJO")) -> ALTO | I33: Categoría del sistema = ALTA | J33: =IF(H33="ALTO",G33,IF(H33="MEDIO",F33,E33)) -> aplica | K33: — | L33: Aplica sólo en categoría ALTA → aplica. | M33: SÍ | N33: APLICA: medida exigida para la categoría ALTA del sistema (afecta a todas las dimensiones). Exigencia: 'aplica'. Riesgos tratados según AR-2026-01. CCN-STIC 808: 5 requisitos de verificación (0 esenciales). | O33: Protección de la cadena de suministro: due diligence de seguridad antes de contratar (cuestionario CCN-STIC 830 / ISO 27036), verificación de certificaciones (ENS, 27001), plan de contingencia por proveedor crítico, exigencia de SBOM a desarrolladores externos, revisión anual de riesgos de la cadena. | P33: Análisis de composición de software (SCA) en el pipeline; monitorización de exposición de proveedores (rating externo). | Q33: — | R33: Implantada | S33: 1 | T33: Evaluaciones de proveedores 2026; plan de contingencia PROV-CONT-01; informes SCA | U33: Responsable de Seguridad | V33: 5.21 Seguridad en la cadena de suministro TIC; 5.29 Seguridad durante la disrupción; 5.30 Preparación de las TIC para la continuidad | W33: CCN-STIC 811, 830, 804/808
A34: Protección de los equipos | B34: mp.eq.2 | C34: Bloqueo de puesto de trabajo | D34: A | E34: n.a. | F34: aplica | G34: + R1 | H34: =IF(OR('Categorización'!H$14="ALTO"),"ALTO",IF(OR('Categorización'!H$14="MEDIO"),"MEDIO","BAJO")) -> ALTO | I34: máx(A=ALTO) = ALTO | J34: =IF(H34="ALTO",G34,IF(H34="MEDIO",F34,E34)) -> + R1 | K34: R1 Cierre de sesiones | L34: Dimensión A = ALTO → R1 exigido → cumplido. | M34: SÍ | N34: APLICA: medida vinculada a la(s) dimensión(es) A; nivel exigido ALTO (máx(A=ALTO) = ALTO). Exigencia: '+ R1'. Riesgos tratados según AR-2026-01. CCN-STIC 808: 1 requisitos de verificación (1 esenciales). | O34: Bloqueo de sesión por inactividad y cierre de sesiones (R1) al final de la jornada o tras inactividad prolongada; obligación de bloquear al ausentarse. | P34: GPO: bloqueo a 5 min (puestos) y 2 min (consolas de administración); cierre de sesión forzado a las 8 h; PAM cierra sesiones privilegiadas inactivas a los 10 min. | Q34: — | R34: Implantada | S34: 1 | T34: GPO-LOCK-01; informes de cumplimiento | U34: Jefe de Operaciones TI | V34: 7.7 Escritorio y pantalla despejados; 8.1 Dispositivos de usuario | W34: CCN-STIC 804/808, 5xx
A35: Protección de los soportes de información | B35: mp.si.1 | C35: Marcado de soportes | D35: C | E35: n.a. | F35: aplica | G35: aplica | H35: =IF(OR('Categorización'!G$14="ALTO"),"ALTO",IF(OR('Categorización'!G$14="MEDIO"),"MEDIO","BAJO")) -> ALTO | I35: máx(C=ALTO) = ALTO | J35: =IF(H35="ALTO",G35,IF(H35="MEDIO",F35,E35)) -> aplica | K35: — | L35: Dimensión C = ALTO → aplica. | M35: SÍ | N35: APLICA: medida vinculada a la(s) dimensión(es) C; nivel exigido ALTO (máx(C=ALTO) = ALTO). Exigencia: 'aplica'. Riesgos tratados según AR-2026-01. CCN-STIC 808: 6 requisitos de verificación (0 esenciales). | O35: Marcado de soportes según el nivel de calificación de la información (NOR-04): etiqueta con nivel, propietario e identificador; los usuarios conocen el significado de las etiquetas. | P35: Etiquetas físicas normalizadas; etiquetado lógico (metadatos) en cintas y discos extraíbles; inventario en CMDB. | Q35: — | R35: Implantada | S35: 1 | T35: NOR-04; inventario de soportes INV-SOP | U35: Jefe de Operaciones TI | V35: 5.13 Etiquetado de la información; 7.10 Soportes de almacenamiento | W35: CCN-STIC 807, 804/808
A36: Protección de la información | B36: mp.info.2 | C36: Calificación de la información | D36: C | E36: n.a. | F36: aplica | G36: aplica | H36: =IF(OR('Categorización'!G$14="ALTO"),"ALTO",IF(OR('Categorización'!G$14="MEDIO"),"MEDIO","BAJO")) -> ALTO | I36: máx(C=ALTO) = ALTO | J36: =IF(H36="ALTO",G36,IF(H36="MEDIO",F36,E36)) -> aplica | K36: — | L36: Dimensión C = ALTO → aplica. | M36: SÍ | N36: APLICA: medida vinculada a la(s) dimensión(es) C; nivel exigido ALTO (máx(C=ALTO) = ALTO). Exigencia: 'aplica'. Riesgos tratados según AR-2026-01. CCN-STIC 808: 7 requisitos de verificación (2 esenciales). | O36: Política de calificación de la información NOR-04: niveles (PÚBLICO, USO INTERNO, CONFIDENCIAL, RESERVADO) alineados con el nivel de C del Anexo I; el Responsable de la Información califica; procedimientos de manejo por nivel (etiquetado, acceso, cifrado, transmisión, destrucción). | P36: Etiquetado de documentos (MIP/AIP) con DLP asociado; clasificación en repositorios. | Q36: — | R36: Implantada | S36: 1 | T36: NOR-04; guía de manejo por nivel; informes DLP | U36: Responsable de Seguridad | V36: 5.12 Clasificación de la información; 5.13 Etiquetado | W36: CCN-STIC 807, 804/808
A37: Protección de la información | B37: mp.info.5 | C37: Limpieza de documentos | D37: C | E37: aplica | F37: aplica | G37: aplica | H37: =IF(OR('Categorización'!G$14="ALTO"),"ALTO",IF(OR('Categorización'!G$14="MEDIO"),"MEDIO","BAJO")) -> ALTO | I37: máx(C=ALTO) = ALTO | J37: =IF(H37="ALTO",G37,IF(H37="MEDIO",F37,E37)) -> aplica | K37: — | L37: Dimensión C = ALTO → aplica. | M37: SÍ | N37: APLICA: medida vinculada a la(s) dimensión(es) C; nivel exigido ALTO (máx(C=ALTO) = ALTO). Exigencia: 'aplica'. Riesgos tratados según AR-2026-01. CCN-STIC 808: 2 requisitos de verificación (1 esenciales). | O37: Limpieza de documentos: procedimiento de retirada de metadatos, comentarios, cambios y campos ocultos antes de publicar o transferir documentos fuera del nivel de calificación; formación a usuarios. | P37: Limpieza automática de metadatos en la pasarela de correo y en el portal de publicación (herramienta OlvidoMeta / DLP); plantillas corporativas sin campos ocultos. | Q37: — | R37: Implantada | S37: 1 | T37: PRO-INFO-02; configuración DLP | U37: Responsable de Seguridad | V37: 5.14 Transferencia de información; 8.10 Borrado de información (sin equivalente directo) | W37: CCN-STIC 807, 804/808
A38: Protección de los equipos | B38: mp.eq.4 | C38: Otros dispositivos conectados a la red | D38: C | E38: aplica | F38: + R1 | G38: + R1 | H38: =IF(OR('Categorización'!G$14="ALTO"),"ALTO",IF(OR('Categorización'!G$14="MEDIO"),"MEDIO","BAJO")) -> ALTO | I38: máx(C=ALTO) = ALTO | J38: =IF(H38="ALTO",G38,IF(H38="MEDIO",F38,E38)) -> + R1 | K38: R1 Productos certificados | L38: Dimensión C = ALTO → R1 exigido → cumplido. | M38: SÍ | N38: APLICA: medida vinculada a la(s) dimensión(es) C; nivel exigido ALTO (máx(C=ALTO) = ALTO). Exigencia: '+ R1'. Riesgos tratados según AR-2026-01. CCN-STIC 808: 2 requisitos de verificación (1 esenciales). | O38: Otros dispositivos conectados (impresoras, IoT, cámaras, sondas): inventario, autorización, bastionado, segmentación, productos certificados (R1) cuando existan en el CPSTIC; borrado de datos residuales en impresoras. | P38: Segmento de red dedicado con NAC (802.1X / MAB); impresoras con cifrado de disco y borrado automático; firmware actualizado. | Q38: — | R38: Implantada | S38: 1 | T38: INV-01 (categoría 'otros dispositivos'); política NAC; informe de cumplimiento | U38: Jefe de Operaciones TI | V38: 8.1 Dispositivos de usuario; 8.20 Seguridad de redes; 5.9 Inventario | W38: CCN-STIC 804/808, 5xx
A39: Protección de los soportes de información | B39: mp.si.5 | C39: Borrado y destrucción | D39: C | E39: aplica | F39: + R1 | G39: + R1 | H39: =IF(OR('Categorización'!G$14="ALTO"),"ALTO",IF(OR('Categorización'!G$14="MEDIO"),"MEDIO","BAJO")) -> ALTO | I39: máx(C=ALTO) = ALTO | J39: =IF(H39="ALTO",G39,IF(H39="MEDIO",F39,E39)) -> + R1 | K39: R1 Productos certificados | L39: Dimensión C = ALTO → R1 exigido → cumplido. | M39: SÍ | N39: APLICA: medida vinculada a la(s) dimensión(es) C; nivel exigido ALTO (máx(C=ALTO) = ALTO). Exigencia: '+ R1'. Riesgos tratados según AR-2026-01. CCN-STIC 808: 4 requisitos de verificación (1 esenciales). | O39: Borrado y destrucción: procedimiento por tipo de soporte (borrado seguro, desmagnetización, destrucción física) con certificado; productos certificados (R1) para borrado; registro de destrucciones; destrucción de soportes de nivel ALTO siempre física. | P39: Software de borrado cualificado; desmagnetizador; trituradora de discos y cintas (DIN 66399 H-5); certificados de la empresa destructora. | Q39: — | R39: Implantada | S39: 1 | T39: PRO-SOP-03; REG-DEST-2026; certificados de destrucción | U39: Jefe de Operaciones TI | V39: 7.10 Soportes; 7.14 Eliminación segura o reutilización de equipos; 8.10 Borrado de información | W39: CCN-STIC 807, 804/808
A40: Continuidad del servicio | B40: op.cont.1 | C40: Análisis de impacto | D40: D | E40: n.a. | F40: aplica | G40: aplica | H40: =IF(OR('Categorización'!E$14="ALTO"),"ALTO",IF(OR('Categorización'!E$14="MEDIO"),"MEDIO","BAJO")) -> ALTO | I40: máx(D=ALTO) = ALTO | J40: =IF(H40="ALTO",G40,IF(H40="MEDIO",F40,E40)) -> aplica | K40: — | L40: Dimensión D = ALTO → aplica. | M40: SÍ | N40: APLICA: medida vinculada a la(s) dimensión(es) D; nivel exigido ALTO (máx(D=ALTO) = ALTO). Exigencia: 'aplica'. Riesgos tratados según AR-2026-01. CCN-STIC 808: 2 requisitos de verificación (0 esenciales). | O40: Análisis de impacto en el negocio BIA-2026 (ISO 22301): procesos y servicios, dependencias, RTO/RPO por servicio (S-01 RTO 4 h/RPO 15 min; S-02/S-03 RTO 24 h/RPO 1 h), recursos mínimos; aprobado por las consejerías. | P40: Plantilla BIA en RiskHub; mapa de dependencias desde la CMDB. | Q40: — | R40: Implantada | S40: 1 | T40: BIA-2026; ACTA-CSI-2026-02 | U40: Responsable de Seguridad | V40: 5.29 Seguridad durante la disrupción; 5.30 Preparación de las TIC para la continuidad (BIA – ISO 22301) | W40: CCN-STIC 804/808; ISO 22301
A41: Planificación | B41: op.pl.4 | C41: Dimensionamiento/gestión de la capacidad | D41: D | E41: aplica | F41: + R1 | G41: + R1 | H41: =IF(OR('Categorización'!E$14="ALTO"),"ALTO",IF(OR('Categorización'!E$14="MEDIO"),"MEDIO","BAJO")) -> ALTO | I41: máx(D=ALTO) = ALTO | J41: =IF(H41="ALTO",G41,IF(H41="MEDIO",F41,E41)) -> + R1 | K41: R1 Mejora continua de la gestión de la capacidad | L41: Dimensión D = ALTO → R1 exigido → cumplido. | M41: SÍ | N41: APLICA: medida vinculada a la(s) dimensión(es) D; nivel exigido ALTO (máx(D=ALTO) = ALTO). Exigencia: '+ R1'. Riesgos tratados según AR-2026-01. CCN-STIC 808: 7 requisitos de verificación (1 esenciales). | O41: Estudio de capacidad previo a la puesta en producción (PRO-CAP-01): procesamiento, almacenamiento, comunicaciones, personal e instalaciones; revisión continua trimestral con umbrales y mejora continua (R1). | P41: Monitorización de capacidad (Zabbix/Grafana) con alertas al 70/85 %; informes trimestrales de tendencia; autoescalado en el tenant cloud. | Q41: — | R41: Implantada | S41: 1 | T41: INF-CAP-2026-Q1..Q3; PRO-CAP-01 | U41: Jefe de Operaciones TI | V41: 8.6 Gestión de la capacidad; 8.14 Redundancia de instalaciones | W41: CCN-STIC 803, 806, 827, 804/808
A42: Protección de las instalaciones e infraestructuras | B42: mp.if.4 | C42: Energía eléctrica | D42: D | E42: aplica | F42: + R1 | G42: + R1 | H42: =IF(OR('Categorización'!E$14="ALTO"),"ALTO",IF(OR('Categorización'!E$14="MEDIO"),"MEDIO","BAJO")) -> ALTO | I42: máx(D=ALTO) = ALTO | J42: =IF(H42="ALTO",G42,IF(H42="MEDIO",F42,E42)) -> + R1 | K42: R1 Suministro eléctrico de emergencia | L42: Dimensión D = ALTO → R1 exigido → cumplido. | M42: SÍ | N42: APLICA: medida vinculada a la(s) dimensión(es) D; nivel exigido ALTO (máx(D=ALTO) = ALTO). Exigencia: '+ R1'. Riesgos tratados según AR-2026-01. CCN-STIC 808: 3 requisitos de verificación (0 esenciales). | O42: Garantía de suministro eléctrico y suministro de emergencia (R1): contrato con dos acometidas, mantenimiento preventivo de SAI y grupo, pruebas mensuales de grupo electrógeno. | P42: Doble acometida, SAI redundantes (autonomía 30 min), grupo electrógeno con 48 h de combustible y contrato de reposición; apagado ordenado automatizado. | Q42: — | R42: Implantada | S42: 1 | T42: REG-MANT-ELEC; pruebas mensuales de grupo | U42: Facilities / Resp. del Sistema | V42: 7.11 Servicios de suministro; 7.5 Amenazas físicas y ambientales | W42: CCN-STIC 804/808
A43: Protección de los servicios | B43: mp.s.4 | C43: Protección frente a denegación de servicio | D43: D | E43: n.a. | F43: aplica | G43: + R1 | H43: =IF(OR('Categorización'!E$14="ALTO"),"ALTO",IF(OR('Categorización'!E$14="MEDIO"),"MEDIO","BAJO")) -> ALTO | I43: máx(D=ALTO) = ALTO | J43: =IF(H43="ALTO",G43,IF(H43="MEDIO",F43,E43)) -> + R1 | K43: R1 Detección y reacción | L43: Dimensión D = ALTO → R1 exigido → cumplido. | M43: SÍ | N43: APLICA: medida vinculada a la(s) dimensión(es) D; nivel exigido ALTO (máx(D=ALTO) = ALTO). Exigencia: '+ R1'. Riesgos tratados según AR-2026-01. CCN-STIC 808: 5 requisitos de verificación (0 esenciales). | O43: Protección frente a denegación de servicio: planificación de capacidad, tecnologías anti-DoS en el perímetro y en el proveedor de comunicaciones, detección y reacción (R1) con procedimiento específico y contacto con el operador y el CCN-CERT. | P43: Servicio anti-DDoS del operador + scrubbing center; rate limiting y WAF; anycast DNS; alertas de anomalía de tráfico en el NDR; runbook de mitigación. | Q43: — | R43: Implantada | S43: 1 | T43: Contrato anti-DDoS; PRO-INC-05 (DoS); prueba de mitigación 03/2026 | U43: SOC (SecOps Iberia) / Resp. Seguridad | V43: 8.6 Gestión de la capacidad; 8.16 Monitorización; 8.14 Redundancia; 5.30 Continuidad TIC | W43: CCN-STIC 804/808, 807
A44: Protección de la información | B44: mp.info.6 | C44: Copias de seguridad | D44: D | E44: aplica | F44: + R1 | G44: + R1 + R2 | H44: =IF(OR('Categorización'!E$14="ALTO"),"ALTO",IF(OR('Categorización'!E$14="MEDIO"),"MEDIO","BAJO")) -> ALTO | I44: máx(D=ALTO) = ALTO | J44: =IF(H44="ALTO",G44,IF(H44="MEDIO",F44,E44)) -> + R1 + R2 | K44: R1 Pruebas de recuperación R2 Protección de las copias de seguridad | L44: Dimensión D = ALTO → R1+R2 exigidos → cumplidos. | M44: SÍ | N44: APLICA: medida vinculada a la(s) dimensión(es) D; nivel exigido ALTO (máx(D=ALTO) = ALTO). Exigencia: '+ R1 + R2'. Riesgos tratados según AR-2026-01. CCN-STIC 808: 11 requisitos de verificación (2 esenciales). | O44: Política de copias de seguridad: cobertura de información, configuraciones, claves y software; frecuencia según RPO; retención; pruebas de recuperación (R1) mensuales; protección de las copias (R2) con el mismo nivel que los originales (cifrado, control de acceso, copia inmutable off-site). | P44: Backup 3-2-1-1-0: replicación entre CPD, copia inmutable en cloud ENS ALTA, cintas cifradas off-site; restauraciones automatizadas de prueba; monitorización de jobs. | Q44: — | R44: Implantada | S44: 1 | T44: POL-BCK-01; REG-REST-2026 (pruebas de restauración); informes de backup | U44: Jefe de Operaciones TI | V44: 8.13 Copias de seguridad de la información; 8.14 Redundancia | W44: CCN-STIC 807, 804/808
A45: Explotación | B45: op.exp.8 | C45: Registro de la actividad | D45: T | E45: aplica | F45: + R1 + R2 + R3 + R4 | G45: + R1 + R2 + R3 + R4 + R5 | H45: =IF(OR('Categorización'!I$14="ALTO"),"ALTO",IF(OR('Categorización'!I$14="MEDIO"),"MEDIO","BAJO")) -> MEDIO | I45: máx(T=MEDIO) = MEDIO | J45: =IF(H45="ALTO",G45,IF(H45="MEDIO",F45,E45)) -> + R1 + R2 + R3 + R4 | K45: R1 Revisión de los registros R2 Sincronización del reloj del sistema R3 Retención de registros R4 Control de acceso | L45: Dimensión T = MEDIO → exigidos R1-R4; R5 (revisión automática y correlación) no exigido pero implantado voluntariamente (exceso de cumplimiento). | M45: SÍ | N45: APLICA: medida vinculada a la(s) dimensión(es) T; nivel exigido MEDIO (máx(T=MEDIO) = MEDIO). Exigencia: '+ R1 + R2 + R3 + R4'. Riesgos tratados según AR-2026-01. CCN-STIC 808: 20 requisitos de verificación (2 esenciales). | O45: Política de registro de actividad: quién, cuándo, qué, resultado; revisión de registros (R1) diaria por el SOC; sincronización de reloj (R2); retención (R3) 2 años (online 12 meses + archivo); control de acceso a los logs (R4) sólo lectura para auditoría. | P45: SIEM centralizado con recolección desde todas las fuentes; NTP interno sincronizado con ROA/stratum-1; almacenamiento WORM; cifrado e integridad (hash encadenado); correlación automática (R5) implantada aunque no exigida. | Q45: — | R45: Implantada | S45: 1 | T45: POL-LOG-01; arquitectura SIEM; informe de retención; REG-LOG-REV | U45: SOC (SecOps Iberia) / Resp. Seguridad | V45: 8.15 Registro de eventos; 8.17 Sincronización de relojes; 8.16 Monitorización | W45: CCN-STIC 804/808, 817, 5xx/6xx
A46: Protección de la información | B46: mp.info.3 | C46: Firma electrónica | D46: IA | E46: aplica | F46: + R1 + R2 + R3 | G46: + R1 + R2 + R3 + R4 | H46: =IF(OR('Categorización'!F$14="ALTO",'Categorización'!H$14="ALTO"),"ALTO",IF(OR('Categorización'!F$14="MEDIO",'Categorización'!H$14="MEDIO"),"MEDIO","BAJO")) -> ALTO | I46: máx(I=ALTO, A=ALTO) = ALTO | J46: =IF(H46="ALTO",G46,IF(H46="MEDIO",F46,E46)) -> + R1 + R2 + R3 + R4 | K46: R1 Certificados cualificados R2 Algoritmos y parámetros autorizados R3 Verificación y validación de firma R4 Firma electrónica avanzada basada en certificados cualificados | L46: Dimensiones I/A = ALTO → R1+R2+R3+R4 exigidos → cumplidos. | M46: SÍ | N46: APLICA: medida vinculada a la(s) dimensión(es) IA; nivel exigido ALTO (máx(I=ALTO, A=ALTO) = ALTO). Exigencia: '+ R1 + R2 + R3 + R4'. Riesgos tratados según AR-2026-01. CCN-STIC 808: 4 requisitos de verificación (2 esenciales). | O46: Política de firma electrónica: uso de certificados cualificados (R1) para actos administrativos con efectos jurídicos y para la firma del personal de TechServ; algoritmos y parámetros autorizados (R2); verificación y validación de firmas (R3) mediante plataforma de validación (@firma / TSA); firma electrónica avanzada basada en certificados cualificados (R4) para los empleados públicos que firman en las aplicaciones. | P46: Integración con @firma / AutoFirma / Cl@ve Firma; PKI interna con HSM para sello de órgano; verificación de firmas longevas (XAdES/PAdES-LT). | Q46: — | R46: Implantada | S46: 1 | T46: POL-FIRMA-01; DIS-FIRMA-01; informes de validación | U46: Responsable del Sistema | V46: 8.24 Uso de criptografía; 8.26 Requisitos de seguridad de aplicaciones; 5.31 Requisitos legales (Reglamento eIDAS) | W46: CCN-STIC 807, 804/808
A47: Control de acceso | B47: op.acc.1 | C47: Identificación | D47: AT | E47: aplica | F47: + R1 | G47: + R1 | H47: =IF(OR('Categorización'!H$14="ALTO",'Categorización'!I$14="ALTO"),"ALTO",IF(OR('Categorización'!H$14="MEDIO",'Categorización'!I$14="MEDIO"),"MEDIO","BAJO")) -> ALTO | I47: máx(A=ALTO, T=MEDIO) = ALTO | J47: =IF(H47="ALTO",G47,IF(H47="MEDIO",F47,E47)) -> + R1 | K47: R1 Identificación avanzada | L47: Dimensiones T (MEDIO) y A (ALTO) → nivel ALTO → R1 exigido → cumplido. | M47: SÍ | N47: APLICA: medida vinculada a la(s) dimensión(es) AT; nivel exigido ALTO (máx(A=ALTO, T=MEDIO) = ALTO). Exigencia: '+ R1'. Riesgos tratados según AR-2026-01. CCN-STIC 808: 8 requisitos de verificación (3 esenciales). | O47: Identificador único por persona/proceso (PRO-IAM-01); prohibición de cuentas compartidas; cuentas de servicio con propietario; bajas en ≤24 h; conservación de cuentas deshabilitadas para trazabilidad; identificación avanzada (R1) mediante vinculación a la identidad verificada de RRHH y a la PKI corporativa. | P47: Directorio corporativo (AD) integrado con RRHH (ciclo de vida automatizado); IGA (SailPoint) para gobierno de identidades; identidad de dispositivos mediante certificados. | Q47: — | R47: Implantada | S47: 1 | T47: PRO-IAM-01; REG-IAM (altas/bajas); informe trimestral de revisión de cuentas | U47: Responsable del Sistema | V47: 5.16 Gestión de identidades; 5.17 Información de autenticación; 8.15 Registro de eventos | W47: CCN-STIC 804/808, 821
A48: Protección de la información | B48: mp.info.4 | C48: Sellos de tiempo | D48: T | E48: n.a. | F48: n.a. | G48: aplica | H48: =IF(OR('Categorización'!I$14="ALTO"),"ALTO",IF(OR('Categorización'!I$14="MEDIO"),"MEDIO","BAJO")) -> MEDIO | I48: máx(T=MEDIO) = MEDIO | J48: =IF(H48="ALTO",G48,IF(H48="MEDIO",F48,E48)) -> n.a. | K48: n.a. | L48: Exclusión justificada por nivel de dimensión (T = MEDIO). Si T pasara a ALTO, la medida pasaría a exigible. | M48: NO | N48: NO APLICA: la medida afecta a la(s) dimensión(es) T, cuyo nivel es MEDIO, y el Anexo II sólo la exige en nivel ALTO. Exclusión formal registrada; se revisará si cambia el nivel de la dimensión. | O48: Sellos de tiempo cualificados: NO EXIGIDO (la medida afecta sólo a la dimensión T, cuyo nivel es MEDIO, y la medida sólo aplica en nivel ALTO). No obstante, las firmas de actos administrativos incorporan sello de tiempo de TSA cualificada por exigencia de la Ley 39/2015 y eIDAS (control voluntario, fuera de la SoA ENS). | P48: TSA cualificada integrada en @firma (uso voluntario). | Q48: — | R48: No aplica | T48: N/A para ENS; DIS-FIRMA-01 | U48: Responsable del Sistema | V48: 8.24 Uso de criptografía; 8.17 Sincronización de relojes; 8.26 Requisitos de aplicaciones | W48: CCN-STIC 807, 804/808
A49: mp – Medidas de protección
A50: mp.com – Protección de las comunicaciones
A51: mp.eq – Protección de los equipos
A52: mp.if – Protección de las instalaciones e infraestructuras
A53: mp.info – Protección de la información
A54: mp.per – Gestión del personal
A55: mp.s – Protección de los servicios
A56: mp.si – Protección de los soportes de información
A57: mp.sw – Protección de las aplicaciones informáticas
A58: op – Marco operacional
A59: op.acc – Control de acceso
A60: op.cont – Continuidad del servicio
... A66: org – Marco organizativo
A67: Explotación | B67: op.exp.10 | C67: Protección de claves criptográficas | D67: Categoría | E67: aplica | F67: + R1 | G67: + R1 | H67: =IF('Categorización'!$E$15="ALTA","ALTO",IF('Categorización'!$E$15="MEDIA","MEDIO","BAJO")) -> ALTO | I67: Categoría del sistema = ALTA | J67: =IF(H67="ALTO",G67,IF(H67="MEDIO",F67,E67)) -> + R1 | K67: R1 Algoritmos autorizados | L67: R1 exigido → cumplido. | M67: SÍ | N67: APLICA: medida exigida para la categoría ALTA del sistema (afecta a todas las dimensiones). Exigencia: '+ R1'. Riesgos tratados según AR-2026-01. CCN-STIC 808: 3 requisitos de verificación (1 esenciales). | O67: Política de gestión de claves PRO-CRYPT-01: generación, custodia, distribución, uso, rotación y destrucción; roles y doble control para claves raíz; algoritmos autorizados (R1) según CCN-STIC 807. | P67: HSM cualificado (FIPS 140-3 L3 / CPSTIC) para la PKI interna y claves de cifrado; KMS del proveedor cloud ENS ALTA; rotación automática; inventario de certificados. | Q67: — | R67: Implantada | S67: 1 | T67: PRO-CRYPT-01; inventario de claves y certificados; ceremonia de claves 2025 | U67: Responsable de Seguridad | V67: 8.24 Uso de criptografía; 5.17 Información de autenticación | W67: CCN-STIC 804/808, 817, 5xx/6xx
A68: Recursos externos | B68: op.ext.4 | C68: Interconexión de sistemas | D68: Categoría | E68: n.a. | F68: aplica | G68: + R1 | H68: =IF('Categorización'!$E$15="ALTA","ALTO",IF('Categorización'!$E$15="MEDIA","MEDIO","BAJO")) -> ALTO | I68: Categoría del sistema = ALTA | J68: =IF(H68="ALTO",G68,IF(H68="MEDIO",F68,E68)) -> + R1 | K68: R1 Coordinación de actividades | L68: R1 exigido → cumplido. | M68: SÍ | N68: APLICA: medida exigida para la categoría ALTA del sistema (afecta a todas las dimensiones). Exigencia: '+ R1'. Riesgos tratados según AR-2026-01. CCN-STIC 808: 2 requisitos de verificación (0 esenciales). | O68: Interconexiones con las consejerías, Red SARA, Cl@ve, AEAT y proveedores documentadas y autorizadas (org.4); acuerdo de interconexión por cada una (CCN-STIC 811); coordinación de actividades (R1) mediante comité técnico con las consejerías y procedimientos conjuntos de cambio e incidente. | P68: Pasarelas dedicadas por interconexión; cortafuegos + IPS; listas blancas; VPN site-to-site; monitorización de flujos. | Q68: — | R68: Implantada | S68: 1 | T68: ACU-INT-01..06 (acuerdos de interconexión); ARQ-02; actas comité técnico | U68: Responsable del Sistema | V68: 8.20 Seguridad de redes; 8.21 Seguridad de servicios de red; 8.22 Segregación de redes; 5.14 Transferencia de información | W68: CCN-STIC 811, 830, 804/808
A69: Gestión del personal | B69: mp.per.2 | C69: Deberes y obligaciones | D69: Categoría | E69: aplica | F69: + R1 | G69: + R1 | H69: =IF('Categorización'!$E$15="ALTA","ALTO",IF('Categorización'!$E$15="MEDIA","MEDIO","BAJO")) -> ALTO | I69: Categoría del sistema = ALTA | J69: =IF(H69="ALTO",G69,IF(H69="MEDIO",F69,E69)) -> + R1 | K69: R1 Confirmación expresa | L69: R1 exigido → cumplido. | M69: SÍ | N69: APLICA: medida exigida para la categoría ALTA del sistema (afecta a todas las dimensiones). Exigencia: '+ R1'. Riesgos tratados según AR-2026-01. CCN-STIC 808: 4 requisitos de verificación (2 esenciales). | O69: Deberes y obligaciones informados y aceptados por escrito: confidencialidad (vigente tras la baja), uso aceptable, protección de datos, régimen disciplinario; confirmación expresa (R1) firmada al incorporarse y renovada anualmente; personal externo con las mismas obligaciones vía contrato. | P69: Firma electrónica de compromisos en el portal del empleado; recordatorio anual automatizado. | Q69: — | R69: Implantada | S69: 1 | T69: Compromisos firmados (100 % plantilla, REG-ACEPT-NOR); cláusulas en contratos de proveedores | U69: Dirección de Personas (RRHH) | V69: 6.2 Términos y condiciones; 6.4 Proceso disciplinario; 6.5 Responsabilidades tras la finalización; 6.6 Acuerdos de confidencialidad; 5.11 Devolución de activos | W69: CCN-STIC 804/808, 821
A70: Protección de los equipos | B70: mp.eq.1 | C70: Puesto de trabajo despejado | D70: Categoría | E70: aplica | F70: + R1 | G70: + R1 | H70: =IF('Categorización'!$E$15="ALTA","ALTO",IF('Categorización'!$E$15="MEDIA","MEDIO","BAJO")) -> ALTO | I70: Categoría del sistema = ALTA | J70: =IF(H70="ALTO",G70,IF(H70="MEDIO",F70,E70)) -> + R1 | K70: R1 Almacenamiento del material | L70: R1 exigido → cumplido. | M70: SÍ | N70: APLICA: medida exigida para la categoría ALTA del sistema (afecta a todas las dimensiones). Exigencia: '+ R1'. Riesgos tratados según AR-2026-01. CCN-STIC 808: 1 requisitos de verificación (1 esenciales). | O70: Norma de puesto despejado NOR-02: sólo el material necesario para la actividad en curso; almacenamiento del material (R1) en armarios/cajones con llave al finalizar la jornada; inspecciones aleatorias. | P70: Armarios con cerradura en todos los puestos; impresión segura con liberación por tarjeta. | Q70: — | R70: Implantada | S70: 1 | T70: NOR-02; REG-INSP-PUESTO (inspecciones trimestrales) | U70: Responsable de Seguridad | V70: 7.7 Escritorio y pantalla despejados | W70: CCN-STIC 804/808, 5xx
A71: Protección de las aplicaciones informáticas | B71: mp.sw.2 | C71: Aceptación y puesta en servicio | D71: Categoría | E71: aplica | F71: + R1 | G71: + R1 | H71: =IF('Categorización'!$E$15="ALTA","ALTO",IF('Categorización'!$E$15="MEDIA","MEDIO","BAJO")) -> ALTO | I71: Categoría del sistema = ALTA | J71: =IF(H71="ALTO",G71,IF(H71="MEDIO",F71,E71)) -> + R1 | K71: R1 Pruebas | L71: R1 exigido → cumplido. | M71: SÍ | N71: APLICA: medida exigida para la categoría ALTA del sistema (afecta a todas las dimensiones). Exigencia: '+ R1'. Riesgos tratados según AR-2026-01. CCN-STIC 808: 5 requisitos de verificación (3 esenciales). | O71: Aceptación y puesta en servicio (PRO-DEV-02): criterios de aceptación de seguridad, pruebas (R1) funcionales y de seguridad en preproducción con datos no reales, análisis de vulnerabilidades y pentest antes del paso a producción de cambios mayores; aprobación formal. | P71: Entornos separados; DAST y pentest en pre; gate de calidad en el pipeline (bloqueo si vulnerabilidades altas). | Q71: — | R71: Implantada | S71: 1 | T71: Actas de aceptación 2026; informes de pruebas | U71: Jefe de Desarrollo | V71: 8.29 Pruebas de seguridad en desarrollo y aceptación; 8.31 Separación de entornos; 8.33 Información de pruebas; 8.11 Enmascaramiento de datos | W71: CCN-STIC 804/808; OWASP SAMM
A72: Protección de los servicios | B72: mp.s.3 | C72: Protección de la navegación web | D72: Categoría | E72: aplica | F72: aplica | G72: + R1 | H72: =IF('Categorización'!$E$15="ALTA","ALTO",IF('Categorización'!$E$15="MEDIA","MEDIO","BAJO")) -> ALTO | I72: Categoría del sistema = ALTA | J72: =IF(H72="ALTO",G72,IF(H72="MEDIO",F72,E72)) -> + R1 | K72: R1 Monitorización | L72: R1 exigido → cumplido. | M72: SÍ | N72: APLICA: medida exigida para la categoría ALTA del sistema (afecta a todas las dimensiones). Exigencia: '+ R1'. Riesgos tratados según AR-2026-01. CCN-STIC 808: 9 requisitos de verificación (3 esenciales). | O72: Protección de la navegación: uso de proxy obligatorio, filtrado por categorías y reputación, bloqueo de descargas peligrosas, monitorización (R1) del tráfico de navegación con alertas al SOC. | P72: Proxy web seguro con inspección TLS (excepciones documentadas), aislamiento de navegación para administradores, DNS filtering, integración con SIEM. | Q72: — | R72: Implantada | S72: 1 | T72: Política de proxy; informes de navegación; excepciones aprobadas | U72: Jefe de Operaciones TI | V72: 8.23 Filtrado web; 8.7 Malware; 8.16 Monitorización | W72: CCN-STIC 804/808, 807
A73: Control de acceso | B73: op.acc.2 | C73: Requisitos de acceso | D73: ICAT | E73: aplica | F73: aplica | G73: + R1 | H73: =IF(OR('Categorización'!F$14="ALTO",'Categorización'!G$14="ALTO",'Categorización'!H$14="ALTO",'Categorización'!I$14="ALTO"),"ALTO",IF(OR('Categorización'!F$14="MEDIO",'Categorización'!G$14="MEDIO",'Categorización'!H$14="MEDIO",'Categorización'!I$14="MEDIO"),"MEDIO","BAJO")) -> ALTO | I73: máx(I=ALTO, C=ALTO, A=ALTO, T=MEDIO) = ALTO | J73: =IF(H73="ALTO",G73,IF(H73="MEDIO",F73,E73)) -> + R1 | K73: R1 Privilegios de acceso | L73: R1 Privilegios de acceso exigido en ALTO → cumplido. | M73: SÍ | N73: APLICA: medida vinculada a la(s) dimensión(es) ICAT; nivel exigido ALTO (máx(I=ALTO, C=ALTO, A=ALTO, T=MEDIO) = ALTO). Exigencia: '+ R1'. Riesgos tratados según AR-2026-01. CCN-STIC 808: 5 requisitos de verificación (1 esenciales). | O73: Matriz de roles y permisos por aplicación (RBAC) aprobada por el Responsable de la Información de cada consejería; mínimo privilegio y necesidad de conocer; separación de privilegios de acceso: los administradores no operan con cuentas privilegiadas en el día a día (R1). | P73: Cuentas privilegiadas gestionadas en PAM (CyberArk) con check-out, grabación de sesión y aprobación; restricción de utilidades privilegiadas; acceso al código fuente limitado por Git con revisión. | Q73: — | R73: Implantada | S73: 1 | T73: MAT-RBAC-S01..S04; PRO-IAM-02; informes PAM | U73: Responsable del Sistema | V73: 5.15 Control de acceso; 8.3 Restricción de acceso a la información; 8.18 Programas de utilidad privilegiados; 8.4 Acceso al código fuente | W73: CCN-STIC 804/808, 821
A74: Protección de los soportes de información | B74: mp.si.2 | C74: Criptografía | D74: IC | E74: n.a. | F74: aplica | G74: + R1 + R2 | H74: =IF(OR('Categorización'!F$14="ALTO",'Categorización'!G$14="ALTO"),"ALTO",IF(OR('Categorización'!F$14="MEDIO",'Categorización'!G$14="MEDIO"),"MEDIO","BAJO")) -> ALTO | I74: máx(I=ALTO, C=ALTO) = ALTO | J74: =IF(H74="ALTO",G74,IF(H74="MEDIO",F74,E74)) -> + R1 + R2 | K74: R1 Productos certificados R2 Copias de seguridad | L74: R1 productos certificados para cintas → medida compensatoria MC-04; R2 cumplido. | M74: SÍ (compensada) | N74: APLICA: medida vinculada a la(s) dimensión(es) IC; nivel exigido ALTO (máx(I=ALTO, C=ALTO) = ALTO). Exigencia: '+ R1 + R2'. Riesgos tratados según AR-2026-01. CCN-STIC 808: 2 requisitos de verificación (0 esenciales). | O74: Cifrado obligatorio de soportes extraíbles y copias de seguridad con algoritmos autorizados; productos certificados (R1) salvo excepción compensada; copias de seguridad cifradas y con la misma protección que la información original (R2). | P74: USB sólo con cifrado hardware (dispositivos CPSTIC); cintas LTO cifradas (AES-256, claves en HSM); backups en cloud cifrados con BYOK; bloqueo de soportes no autorizados en endpoints (DLP). | Q74: MC-04 | R74: Parcial (compensada) | S74: 0.9 | T74: PRO-CRYPT-01; MC-04; inventario de soportes cifrados | U74: Jefe de Operaciones TI | V74: 8.24 Uso de criptografía; 7.10 Soportes de almacenamiento; 8.12 Prevención de fuga de datos | W74: CCN-STIC 807, 804/808
A75: Explotación | B75: op.exp.4 | C75: Mantenimiento y actualizaciones de seguridad | D75: Categoría | E75: aplica | F75: + R1 | G75: + R1 + R2 | H75: =IF('Categorización'!$E$15="ALTA","ALTO",IF('Categorización'!$E$15="MEDIA","MEDIO","BAJO")) -> ALTO | I75: Categoría del sistema = ALTA | J75: =IF(H75="ALTO",G75,IF(H75="MEDIO",F75,E75)) -> + R1 + R2 | K75: R1 Pruebas en preproducción R2 Prevención de fallos | L75: R1+R2 exigidos → cumplidos. | M75: SÍ | N75: APLICA: medida exigida para la categoría ALTA del sistema (afecta a todas las dimensiones). Exigencia: '+ R1 + R2'. Riesgos tratados según AR-2026-01. CCN-STIC 808: 3 requisitos de verificación (2 esenciales). | O75: Política de parches PRO-PATCH-01: seguimiento de avisos (CCN-CERT, fabricantes, CVE), SLAs (críticas ≤72 h, altas ≤15 d), pruebas en preproducción (R1), análisis de riesgo antes de aplicar (R2), ventanas de mantenimiento; planes de contingencia ante fallo de actualización. | P75: WSUS/SCCM, gestor de parches Linux, escáner de vulnerabilidades (Tenable) semanal, entorno de preproducción idéntico; snapshots antes de actualizar. | Q75: — | R75: Implantada | S75: 1 | T75: PRO-PATCH-01; informe mensual de vulnerabilidades; tickets de cambio | U75: Jefe de Operaciones TI | V75: 8.8 Gestión de vulnerabilidades técnicas; 7.13 Mantenimiento de equipos; 8.31 Separación de entornos | W75: CCN-STIC 804/808, 817, 5xx/6xx
A76: Servicios en la nube | B76: op.nub.1 | C76: Protección de servicios en la nube | D76: Categoría | E76: aplica | F76: + R1 | G76: + R1 + R2 | H76: =IF('Categorización'!$E$15="ALTA","ALTO",IF('Categorización'!$E$15="MEDIA","MEDIO","BAJO")) -> ALTO | I76: Categoría del sistema = ALTA | J76: =IF(H76="ALTO",G76,IF(H76="MEDIO",F76,E76)) -> + R1 + R2 | K76: R1 Servicios certificados R2 Guías de Configuración de Seguridad Específicas | L76: R1+R2 exigidos → cumplidos. | M76: SÍ | N76: APLICA: medida exigida para la categoría ALTA del sistema (afecta a todas las dimensiones). Exigencia: '+ R1 + R2'. Riesgos tratados según AR-2026-01. CCN-STIC 808: 4 requisitos de verificación (2 esenciales). | O76: Uso de servicios cloud sólo con certificación ENS ALTA (R1) y ubicación de datos en la UE; análisis de riesgos específico; guías de configuración segura específicas del proveedor (R2, CCN-STIC 884-like / benchmarks del proveedor); contrato con cláusulas ENS/RGPD; estrategia de salida. | P76: Landing zone bastionada; CSPM para control continuo de configuración; cifrado con claves propias (BYOK); logs del proveedor integrados en el SIEM. | Q76: — | R76: Implantada | S76: 1 | T76: Certificado ENS ALTA de NubeAdmin; GUI-CLOUD-01; informes CSPM | U76: Responsable del Sistema | V76: 5.23 Seguridad para el uso de servicios en la nube; 5.19/5.20 Proveedores | W76: CCN-STIC 810, 823, 884, 804/808
A77: Monitorización del sistema | B77: op.mon.1 | C77: Detección de intrusión | D77: Categoría | E77: aplica | F77: + R1 | G77: + R1 + R2 | H77: =IF('Categorización'!$E$15="ALTA","ALTO",IF('Categorización'!$E$15="MEDIA","MEDIO","BAJO")) -> ALTO | I77: Categoría del sistema = ALTA | J77: =IF(H77="ALTO",G77,IF(H77="MEDIO",F77,E77)) -> + R1 + R2 | K77: R1 Detección basada en reglas R2 Procedimientos de respuesta | L77: R1+R2 exigidos → cumplidos. | M77: SÍ | N77: APLICA: medida exigida para la categoría ALTA del sistema (afecta a todas las dimensiones). Exigencia: '+ R1 + R2'. Riesgos tratados según AR-2026-01. CCN-STIC 808: 2 requisitos de verificación (1 esenciales). | O77: Detección de intrusión con reglas actualizadas (R1) y procedimientos de respuesta (R2) integrados en PRO-INC-01; revisión mensual de reglas y falsos positivos. | P77: IDS/IPS de red (producto CPSTIC), NDR, EDR con detección basada en reglas y comportamiento; honeypots internos; alertas al SOC con playbooks. | Q77: — | R77: Implantada | S77: 1 | T77: Arquitectura de detección DET-01; informes mensuales del SOC | U77: SOC (SecOps Iberia) / Resp. Seguridad | V77: 8.16 Actividades de monitorización; 8.20 Seguridad de redes; 8.15 Registro | W77: CCN-STIC 815, 817, 804/808
A78: Monitorización del sistema | B78: op.mon.2 | C78: Sistema de métricas | D78: Categoría | E78: aplica | F78: + R1 + R2 | G78: + R1 + R2 | H78: =IF('Categorización'!$E$15="ALTA","ALTO",IF('Categorización'!$E$15="MEDIA","MEDIO","BAJO")) -> ALTO | I78: Categoría del sistema = ALTA | J78: =IF(H78="ALTO",G78,IF(H78="MEDIO",F78,E78)) -> + R1 + R2 | K78: R1 Efectividad del sistema de gestión de incidentes R2 Eficiencia del sistema de gestión de la seguridad | L78: R1+R2 exigidos → cumplidos. | M78: SÍ | N78: APLICA: medida exigida para la categoría ALTA del sistema (afecta a todas las dimensiones). Exigencia: '+ R1 + R2'. Riesgos tratados según AR-2026-01. CCN-STIC 808: 2 requisitos de verificación (0 esenciales). | O78: Sistema de métricas (CCN-STIC 815): grado de implantación de medidas, efectividad de la gestión de incidentes (R1: tiempo de detección, contención y resolución, reincidencia), eficiencia del SGSI (R2: recursos, coste por incidente, cumplimiento de PTR); reporte trimestral al CSI e INES anual. | P78: Cuadro de mando en RiskHub/Power BI con datos del SIEM e ITSM. | Q78: — | R78: Implantada | S78: 1 | T78: MET-2026-Q1..Q3; informe INES 2025 | U78: Responsable de Seguridad | V78: Cl. 9.1 Seguimiento, medición, análisis y evaluación; 5.36 Cumplimiento de políticas | W78: CCN-STIC 815, 817, 804/808
A79: Protección de los equipos | B79: mp.eq.3 | C79: Protección de dispositivos portátiles | D79: Categoría | E79: aplica | F79: aplica | G79: + R1 + R2 | H79: =IF('Categorización'!$E$15="ALTA","ALTO",IF('Categorización'!$E$15="MEDIA","MEDIO","BAJO")) -> ALTO | I79: Categoría del sistema = ALTA | J79: =IF(H79="ALTO",G79,IF(H79="MEDIO",F79,E79)) -> + R1 + R2 | K79: R1 Cifrado del disco R2 Entornos protegidos | L79: R1+R2 exigidos → cumplidos. | M79: SÍ | N79: APLICA: medida exigida para la categoría ALTA del sistema (afecta a todas las dimensiones). Exigencia: '+ R1 + R2'. Riesgos tratados según AR-2026-01. CCN-STIC 808: 7 requisitos de verificación (4 esenciales). | O79: Norma de dispositivos móviles NOR-03: inventario, autorización, protección fuera de las instalaciones, comunicación inmediata de pérdida/robo, limitación de la información almacenada; cifrado de disco (R1); entornos protegidos (R2) para acceso remoto a información ALTA. | P79: MDM/UEM con borrado remoto; cifrado completo de disco (BitLocker con TPM + PIN / FileVault) con claves en escrow; VPN always-on; acceso a información ALTA sólo mediante escritorio virtual (VDI) sin persistencia local (R2). | Q79: — | R79: Implantada | S79: 1 | T79: NOR-03; consola MDM (cobertura 100 %); REG-PERD-DISP | U79: Jefe de Operaciones TI | V79: 8.1 Dispositivos de usuario; 7.9 Activos fuera de las instalaciones; 6.7 Trabajo remoto; 8.24 Criptografía | W79: CCN-STIC 804/808, 5xx
A80: Explotación | B80: op.exp.3 | C80: Gestión de la configuración de seguridad | D80: Categoría | E80: aplica | F80: + R1 | G80: + R1 + R2 + R3 | H80: =IF('Categorización'!$E$15="ALTA","ALTO",IF('Categorización'!$E$15="MEDIA","MEDIO","BAJO")) -> ALTO | I80: Categoría del sistema = ALTA | J80: =IF(H80="ALTO",G80,IF(H80="MEDIO",F80,E80)) -> + R1 + R2 + R3 | K80: R1 Mantenimiento regular de la configuración R2 Responsabilidad de la configuración R3 Copias de seguridad | L80: R1+R2+R3 exigidos → cumplidos. | M80: SÍ | N80: APLICA: medida exigida para la categoría ALTA del sistema (afecta a todas las dimensiones). Exigencia: '+ R1 + R2 + R3'. Riesgos tratados según AR-2026-01. CCN-STIC 808: 13 requisitos de verificación (5 esenciales). | O80: Gestión continua de la configuración de seguridad (PRO-CFG-02): mantenimiento regular (R1), responsable designado por plataforma (R2), copias de seguridad de configuraciones (R3); revisión ante cambios, incidentes y vulnerabilidades. | P80: Gestión de configuración con Ansible/GitOps (configuración como código, control de versiones); backup diario de configuraciones de red/seguridad (Oxidized); detección de desviaciones. | Q80: — | R80: Implantada | S80: 1 | T80: PRO-CFG-02; repositorio Git de configuración; REG-CFG-BK | U80: Jefe de Operaciones TI | V80: 8.9 Gestión de la configuración; 8.32 Gestión de cambios; 8.13 Copias de seguridad | W80: CCN-STIC 804/808, 817, 5xx/6xx
A81: Explotación | B81: op.exp.7 | C81: Gestión de incidentes | D81: Categoría | E81: aplica | F81: + R1 + R2 | G81: + R1 + R2 + R3 | H81: =IF('Categorización'!$E$15="ALTA","ALTO",IF('Categorización'!$E$15="MEDIA","MEDIO","BAJO")) -> ALTO | I81: Categoría del sistema = ALTA | J81: =IF(H81="ALTO",G81,IF(H81="MEDIO",F81,E81)) -> + R1 + R2 + R3 | K81: R1 Notificación R2 Detección y Respuesta R3 Reconfiguración dinámica | L81: R1+R2+R3 exigidos → cumplidos. | M81: SÍ | N81: APLICA: medida exigida para la categoría ALTA del sistema (afecta a todas las dimensiones). Exigencia: '+ R1 + R2 + R3'. Riesgos tratados según AR-2026-01. CCN-STIC 808: 8 requisitos de verificación (2 esenciales). | O81: Proceso de gestión de incidentes PRO-INC-01 (CCN-STIC 817): detección, clasificación por taxonomía y peligrosidad, respuesta, notificación a las consejerías, al CCN-CERT (R1, obligatoria vía LUCIA), a la AEPD y afectados si procede; detección y respuesta (R2) por SOC 24x7; reconfiguración dinámica (R3) mediante SOAR/EDR. | P81: SIEM + SOAR; integración LUCIA/REYES; playbooks; aislamiento automático de hosts; cuadernos de crisis. | Q81: — | R81: Implantada | S81: 1 | T81: PRO-INC-01; REG-INC-2026; evidencias de notificación LUCIA; ejercicio de mesa 05/2026 | U81: SOC (SecOps Iberia) / Resp. Seguridad | V81: 5.24 Planificación gestión incidentes; 5.25 Evaluación de eventos; 5.26 Respuesta; 5.27 Aprender de incidentes; 5.28 Recogida de evidencias; 6.8 Notificación de eventos | W81: CCN-STIC 804/808, 817, 5xx/6xx
A82: Protección de las comunicaciones | B82: mp.com.2 | C82: Protección de la confidencialidad | D82: C | E82: aplica | F82: + R1 | G82: + R1 + R2 + R3 | H82: =IF(OR('Categorización'!G$14="ALTO"),"ALTO",IF(OR('Categorización'!G$14="MEDIO"),"MEDIO","BAJO")) -> ALTO | I82: máx(C=ALTO) = ALTO | J82: =IF(H82="ALTO",G82,IF(H82="MEDIO",F82,E82)) -> + R1 + R2 + R3 | K82: R1 Algoritmos y parámetros autorizados R2 Dispositivos hardware R3 Productos certificados | L82: R1+R2+R3 exigidos → cumplidos. | M82: SÍ | N82: APLICA: medida vinculada a la(s) dimensión(es) C; nivel exigido ALTO (máx(C=ALTO) = ALTO). Exigencia: '+ R1 + R2 + R3'. Riesgos tratados según AR-2026-01. CCN-STIC 808: 4 requisitos de verificación (0 esenciales). | O82: Protección de la confidencialidad de las comunicaciones: cifrado obligatorio fuera de la zona de confianza y en toda red no controlada; algoritmos y parámetros autorizados (R1) CCN-STIC 807; dispositivos hardware (R2) y productos certificados (R3) en las pasarelas de los CPD. | P82: TLS 1.2/1.3 con suites 807; IPsec en concentradores cualificados con HSM; VPN de acceso remoto con producto CPSTIC; cifrado WPA3-Enterprise; DNS-over-TLS. | Q82: — | R82: Implantada | S82: 1 | T82: PRO-CRYPT-01; inventario de túneles; informe de cumplimiento TLS (escaneo mensual) | U82: Jefe de Operaciones TI | V82: 8.24 Uso de criptografía; 8.20/8.21 Redes; 5.14 Transferencia de información | W82: CCN-STIC 807, 811, 804/808
A83: Planificación | B83: op.pl.2 | C83: Arquitectura de Seguridad | D83: Categoría | E83: aplica | F83: + R1 | G83: + R1 + R2 + R3 | H83: =IF('Categorización'!$E$15="ALTA","ALTO",IF('Categorización'!$E$15="MEDIA","MEDIO","BAJO")) -> ALTO | I83: Categoría del sistema = ALTA | J83: =IF(H83="ALTO",G83,IF(H83="MEDIO",F83,E83)) -> + R1 + R2 + R3 | K83: R1 Sistema de gestión R2 Sistema de gestión de la seguridad con mejora continua R3 Validación de datos | L83: R1+R2+R3 exigidos en ALTA → cumplidos. | M83: SÍ | N83: APLICA: medida exigida para la categoría ALTA del sistema (afecta a todas las dimensiones). Exigencia: '+ R1 + R2 + R3'. Riesgos tratados según AR-2026-01. CCN-STIC 808: 7 requisitos de verificación (3 esenciales). | O83: Documento de arquitectura de seguridad ARQ-02: instalaciones y puntos de acceso, inventario de sistemas y redes, esquema de líneas de defensa (perímetro, DMZ, segmentación, EDR), sistema de I+A (AD/LDAP + PKI + MFA); sistema de gestión (SGSI ISO 27001 certificado) con revisión y aprobación anual (R1, R2); controles técnicos internos de validación de datos en aplicaciones (R3). | P83: Diagramas de red con direccionamiento (custodiados como CONFIDENCIAL); firewalls de nueva generación en doble capa de fabricantes distintos; WAF; validación de entradas/salidas en el framework de desarrollo. | Q83: — | R83: Implantada | S83: 1 | T83: ARQ-02 v3; certificado ISO 27001:2022 nº ES-27001-4521; PRO-DEV-03 validación de datos | U83: Responsable del Sistema | V83: 5.9 Inventario de activos; 8.20 Seguridad de redes; 8.22 Segregación de redes; 8.27 Arquitectura y principios de ingeniería segura; 8.26 Requisitos de seguridad de aplicaciones | W83: CCN-STIC 803, 806, 827, 804/808
A84: Explotación | B84: op.exp.6 | C84: Protección frente a código dañino | D84: Categoría | E84: aplica | F84: + R1 + R2 | G84: + R1 + R2 + R3 + R4 | H84: =IF('Categorización'!$E$15="ALTA","ALTO",IF('Categorización'!$E$15="MEDIA","MEDIO","BAJO")) -> ALTO | I84: Categoría del sistema = ALTA | J84: =IF(H84="ALTO",G84,IF(H84="MEDIO",F84,E84)) -> + R1 + R2 + R3 + R4 | K84: R1 Escaneo periódico R2 Revisión preventiva del sistema R3 Lista blanca R4 Capacidad de respuesta en caso de incidente | L84: R1+R2+R3+R4 exigidos → cumplidos. | M84: SÍ | N84: APLICA: medida exigida para la categoría ALTA del sistema (afecta a todas las dimensiones). Exigencia: '+ R1 + R2 + R3 + R4'. Riesgos tratados según AR-2026-01. CCN-STIC 808: 12 requisitos de verificación (4 esenciales). | O84: Política antimalware; escaneo periódico (R1); revisión preventiva del sistema tras incidentes o cambios relevantes (R2); lista blanca de aplicaciones en servidores y puestos críticos (R3); capacidad de respuesta 24x7 (R4) con el SOC. | P84: EDR/XDR (producto CPSTIC) en todos los endpoints y servidores; sandboxing de correo; application control (AppLocker/WDAC) en modo bloqueo; integración con SIEM/SOAR para contención automática. | Q84: — | R84: Implantada | S84: 1 | T84: POL-MALW-01; consola EDR (cobertura 100 %); informes semanales SOC | U84: SOC (SecOps Iberia) / Resp. Seguridad | V84: 8.7 Protección contra malware; 8.19 Instalación de software; 8.16 Monitorización | W84: CCN-STIC 804/808, 817, 5xx/6xx
A85: Protección de las aplicaciones informáticas | B85: mp.sw.1 | C85: Desarrollo de aplicaciones | D85: Categoría | E85: n.a. | F85: + R1 + R2 + R3 + R4 | G85: + R1 + R2 + R3 + R4 | H85: =IF('Categorización'!$E$15="ALTA","ALTO",IF('Categorización'!$E$15="MEDIA","MEDIO","BAJO")) -> ALTO | I85: Categoría del sistema = ALTA | J85: =IF(H85="ALTO",G85,IF(H85="MEDIO",F85,E85)) -> + R1 + R2 + R3 + R4 | K85: R1 Mínimo privilegio R2 Metodología de desarrollo seguro R3 Seguridad desde el diseño R4 Datos de pruebas | L85: R1+R2+R3+R4 exigidos. R3: modelado de amenazas completado en S-01 y S-04; pendiente S-02/S-03 (PTR-2026-09, 30/11/2026). | M85: SÍ | N85: APLICA: medida exigida para la categoría ALTA del sistema (afecta a todas las dimensiones). Exigencia: '+ R1 + R2 + R3 + R4'. Riesgos tratados según AR-2026-01. CCN-STIC 808: 12 requisitos de verificación (0 esenciales). | O85: Metodología de desarrollo seguro (R2) documentada (PRO-DEV-01, basada en OWASP SAMM y CCN-STIC): seguridad desde el diseño (R3) con modelado de amenazas, requisitos de seguridad, revisión de código, gestión de vulnerabilidades del código; mínimo privilegio (R1) en la arquitectura de aplicaciones; datos de prueba (R4) sintéticos o enmascarados, nunca datos reales de producción; desarrollo subcontratado sujeto a los mismos requisitos. | P85: Pipeline CI/CD con SAST, SCA, DAST y secret scanning; pre-producción separada; enmascaramiento de datos automatizado; SBOM. | Q85: — | R85: Parcial | S85: 0.85 | T85: PRO-DEV-01; informes SAST/DAST; modelos de amenazas por aplicación; PTR-2026-09 | U85: Jefe de Desarrollo | V85: 8.25 Ciclo de vida de desarrollo seguro; 8.26 Requisitos de seguridad de aplicaciones; 8.27 Arquitectura segura; 8.28 Codificación segura; 8.30 Desarrollo externalizado; 8.4 Código fuente | W85: CCN-STIC 804/808; OWASP SAMM
A86: Planificación | B86: op.pl.1 | C86: Análisis de riesgos | D86: Categoría | E86: aplica | F86: + R1 | G86: + R2 | H86: =IF('Categorización'!$E$15="ALTA","ALTO",IF('Categorización'!$E$15="MEDIA","MEDIO","BAJO")) -> ALTO | I86: Categoría del sistema = ALTA | J86: =IF(H86="ALTO",G86,IF(H86="MEDIO",F86,E86)) -> + R2 | K86: R2 Análisis de riesgos formal | L86: R2 análisis formal exigido en ALTA → cumplido (PILAR, modo formal). | M86: SÍ | N86: APLICA: medida exigida para la categoría ALTA del sistema (afecta a todas las dimensiones). Exigencia: '+ R2'. Riesgos tratados según AR-2026-01. CCN-STIC 808: 14 requisitos de verificación (5 esenciales). | O86: Metodología MAGERIT v3 con herramienta PILAR (licencia CCN). Análisis formal (R2): valoración cuantitativa/cualitativa de activos, amenazas del catálogo, salvaguardas y riesgo residual; criterios de aceptación aprobados por el CSI; revisión anual y ante cambios significativos. | P86: PILAR 7.x; exportación al Plan de Tratamiento (PTR-2026) y seguimiento en RiskHub. | Q86: — | R86: Implantada | S86: 1 | T86: AR-2026-01 (informe PILAR); PTR-2026; ACTA-CSI-2026-02 (aceptación riesgo residual) | U86: Responsable de Seguridad | V86: Cl. 6.1.2 Evaluación de riesgos; Cl. 6.1.3 Tratamiento de riesgos; Cl. 8.2/8.3; 5.7 Inteligencia de amenazas | W86: CCN-STIC 803, 806, 827, 804/808
A87: Protección de los servicios | B87: mp.s.2 | C87: Protección de servicios y aplicaciones web | D87: Categoría | E87: + [R1 o R2] | F87: + [R1 o R2] | G87: + R2 + R3 | H87: =IF('Categorización'!$E$15="ALTA","ALTO",IF('Categorización'!$E$15="MEDIA","MEDIO","BAJO")) -> ALTO | I87: Categoría del sistema = ALTA | J87: =IF(H87="ALTO",G87,IF(H87="MEDIO",F87,E87)) -> + R2 + R3 | K87: R2 Auditorías de seguridad avanzada R3 Protección de las cachés | L87: R2+R3 exigidos en ALTO → cumplidos. | M87: SÍ | N87: APLICA: medida exigida para la categoría ALTA del sistema (afecta a todas las dimensiones). Exigencia: '+ R2 + R3'. Riesgos tratados según AR-2026-01. CCN-STIC 808: 11 requisitos de verificación (6 esenciales). | O87: Protección de servicios web: análisis de vulnerabilidades y pentest anual (R1, incluido en R2); auditorías de seguridad avanzada (R2) con pruebas manuales OWASP y revisión de código de cambios mayores; protección de cachés (R3) evitando datos sensibles en cachés y CDN; prevención de manipulación de URL, cookies, inyección, escalada; autenticación de doble factor para accesos a información ALTA. | P87: WAF (CPSTIC) en modo bloqueo; cabeceras de seguridad; TLS 1.3; gestión de sesiones segura; cachés con Cache-Control: no-store para contenido autenticado; CDN sin cacheo de respuestas autenticadas; escaneo DAST continuo. | Q87: — | R87: Implantada | S87: 1 | T87: Informe pentest 2026 (S-01, S-02, S-03); configuración WAF; PRO-WEB-01 | U87: Jefe de Desarrollo | V87: 8.26 Requisitos de seguridad de aplicaciones; 8.29 Pruebas de seguridad; 8.8 Vulnerabilidades técnicas; 8.25 SDLC | W87: CCN-STIC 804/808, 807
A88: Protección de las comunicaciones | B88: mp.com.3 | C88: Protección de la integridad y de la autenticidad | D88: IA | E88: aplica | F88: + R1 + R2 | G88: + R1 + R2 + R3 + R4 | H88: =IF(OR('Categorización'!F$14="ALTO",'Categorización'!H$14="ALTO"),"ALTO",IF(OR('Categorización'!F$14="MEDIO",'Categorización'!H$14="MEDIO"),"MEDIO","BAJO")) -> ALTO | I88: máx(I=ALTO, A=ALTO) = ALTO | J88: =IF(H88="ALTO",G88,IF(H88="MEDIO",F88,E88)) -> + R1 + R2 + R3 + R4 | K88: R1 Redes privadas virtuales R2 Algoritmos y parámetros autorizados R3 Dispositivos hardware R4 Productos certificados | L88: R3 dispositivos hardware en el extremo cloud → medida compensatoria MC-03. | M88: SÍ (compensada) | N88: APLICA: medida vinculada a la(s) dimensión(es) IA; nivel exigido ALTO (máx(I=ALTO, A=ALTO) = ALTO). Exigencia: '+ R1 + R2 + R3 + R4'. Riesgos tratados según AR-2026-01. CCN-STIC 808: 11 requisitos de verificación (2 esenciales). | O88: Protección de integridad y autenticidad: autenticación mutua de extremos, prevención de manipulación/inyección/secuestro; VPN (R1); algoritmos autorizados (R2); dispositivos hardware (R3) y productos certificados (R4) en los CPD; excepción compensada en el lado cloud. | P88: IPsec/IKEv2 con autenticación por certificado; mTLS entre servicios; firmado de mensajes en interconexiones (WS-Security/JWS); concentradores VPN CPSTIC con HSM. | Q88: MC-03 | R88: Parcial (compensada) | S88: 0.9 | T88: ARQ-02; MC-03; informes de auditoría de configuración 807 | U88: Jefe de Operaciones TI | V88: 8.24 Uso de criptografía; 8.20/8.21 Redes; 6.7 Trabajo remoto (VPN) | W88: CCN-STIC 807, 811, 804/808
A89: Monitorización del sistema | B89: op.mon.3 | C89: Vigilancia | D89: Categoría | E89: aplica | F89: + R1 + R2 | G89: + R1 + R2 + R3 + R4 + R5 + R6 | H89: =IF('Categorización'!$E$15="ALTA","ALTO",IF('Categorización'!$E$15="MEDIA","MEDIO","BAJO")) -> ALTO | I89: Categoría del sistema = ALTA | J89: =IF(H89="ALTO",G89,IF(H89="MEDIO",F89,E89)) -> + R1 + R2 + R3 + R4 + R5 + R6 | K89: R1 Correlación de eventos R2 Análisis dinámico R3 Ciberamenazas avanzadas R4 Observatorios digitales R5 Minería de datos R6 Inspecciones de seguridad | L89: R5 minería de datos en despliegue (data lake) → PTR-2026-07, fecha objetivo 31/12/2026. R1-R4 y R6 cumplidos. | M89: SÍ | N89: APLICA: medida exigida para la categoría ALTA del sistema (afecta a todas las dimensiones). Exigencia: '+ R1 + R2 + R3 + R4 + R5 + R6'. Riesgos tratados según AR-2026-01. CCN-STIC 808: 10 requisitos de verificación (1 esenciales). | O89: Vigilancia continua: correlación de eventos (R1), análisis dinámico de comportamiento (R2), suscripción a inteligencia de ciberamenazas avanzadas del CCN-CERT y proveedores (R3), observatorios digitales / vigilancia de marca y fuga de credenciales (R4), minería de datos sobre los registros (R5), inspecciones de seguridad periódicas: pentest anual, revisiones de configuración y ejercicio de red team bienal (R6). | P89: SIEM con UEBA; plataforma de threat intelligence (MISP) integrada con REYES; servicio de vigilancia digital; analítica sobre data lake de logs (en despliegue); escáner continuo de superficie de ataque. | Q89: — | R89: Parcial | S89: 0.8 | T89: Contrato SOC; informes TI; informe pentest 2026; plan de despliegue analítica DL-01 | U89: SOC (SecOps Iberia) / Resp. Seguridad | V89: 5.7 Inteligencia de amenazas; 8.16 Actividades de monitorización; 8.8 Vulnerabilidades técnicas | W89: CCN-STIC 815, 817, 804/808
A90: Marco organizativo | B90: org.1 | C90: Política de seguridad | D90: Categoría | E90: aplica | F90: aplica | G90: aplica | H90: =IF('Categorización'!$E$15="ALTA","ALTO",IF('Categorización'!$E$15="MEDIA","MEDIO","BAJO")) -> ALTO | I90: Categoría del sistema = ALTA | J90: =IF(H90="ALTO",G90,IF(H90="MEDIO",F90,E90)) -> aplica | K90: — | L90: Revisión anual (próxima 01/2027). | M90: SÍ | N90: APLICA: medida exigida para la categoría ALTA del sistema (afecta a todas las dimensiones). Exigencia: 'aplica'. Riesgos tratados según AR-2026-01. CCN-STIC 808: 10 requisitos de verificación (6 esenciales). | O90: Política de Seguridad de la Información PSI-01 v4 aprobada por el Consejo de Administración (30/01/2026) y adherida por las tres consejerías; define misión, marco legal (ENS, RGPD/LOPDGDD, LGT, Ley 39/2015, contratos), roles (Resp. Información/Servicio/Sistema/Seguridad, DPD), Comité de Seguridad, estructura documental y revisión anual. | P90: Publicación en la intranet con control de versiones (DMS); firma electrónica del acta de aprobación. | Q90: — | R90: Implantada | S90: 1 | T90: PSI-01; ACTA-CA-2026-01; REG-COM-04 (difusión); nombramientos NOM-01..05 | U90: Responsable de Seguridad | V90: 5.1 Políticas de seguridad de la información; 5.2 Roles y responsabilidades; 5.4 Responsabilidades de la dirección; 5.31 Requisitos legales y contractuales; Cl. 5.2 Política | W90: CCN-STIC 801, 805, 821, 804/808
A91: Planificación | B91: op.pl.5 | C91: Componentes certificados | D91: Categoría | E91: n.a. | F91: aplica | G91: aplica | H91: =IF('Categorización'!$E$15="ALTA","ALTO",IF('Categorización'!$E$15="MEDIA","MEDIO","BAJO")) -> ALTO | I91: Categoría del sistema = ALTA | J91: =IF(H91="ALTO",G91,IF(H91="MEDIO",F91,E91)) -> aplica | K91: — | L91: Ver medida compensatoria MC-01 (sustitución 2027, PTR-2026-11). | M91: SÍ (compensada) | N91: APLICA: medida exigida para la categoría ALTA del sistema (afecta a todas las dimensiones). Exigencia: 'aplica'. Riesgos tratados según AR-2026-01. CCN-STIC 808: 4 requisitos de verificación (2 esenciales). | O91: Política de uso de productos cualificados (CPSTIC) en op.pl.3; inventario de componentes de seguridad con su estado de cualificación; plan de sustitución. | P91: Cortafuegos, VPN, EDR, HSM y cifradores del CPD principal son productos cualificados CPSTIC; excepción documentada para el clúster de cortafuegos del CPD de respaldo. | Q91: MC-01 | R91: Parcial (compensada) | S91: 0.85 | T91: INV-SEC-01 (componentes de seguridad y cualificación); MC-01 | U91: Responsable de Seguridad | V91: 5.21 Seguridad en la cadena de suministro TIC; 8.9 Gestión de la configuración (sin equivalente directo – CPSTIC) | W91: CCN-STIC 803, 806, 827, 804/808
A92: Protección de las instalaciones e infraestructuras | B92: mp.if.6 | C92: Protección frente a inundaciones | D92: D | E92: n.a. | F92: aplica | G92: aplica | H92: =IF(OR('Categorización'!E$14="ALTO"),"ALTO",IF(OR('Categorización'!E$14="MEDIO"),"MEDIO","BAJO")) -> ALTO | I92: máx(D=ALTO) = ALTO | J92: =IF(H92="ALTO",G92,IF(H92="MEDIO",F92,E92)) -> aplica | K92: — | L92: Ver medida compensatoria MC-02. | M92: SÍ (compensada) | N92: APLICA: medida vinculada a la(s) dimensión(es) D; nivel exigido ALTO (máx(D=ALTO) = ALTO). Exigencia: 'aplica'. Riesgos tratados según AR-2026-01. CCN-STIC 808: 3 requisitos de verificación (0 esenciales). | O92: Evaluación del riesgo de inundación; medidas compensatorias documentadas para el CPD principal (planta baja); CPD de respaldo en planta 2 sin riesgo. | P92: Suelo técnico elevado, sensores de agua, válvulas de corte, ausencia de conducciones sobre la sala. | Q92: MC-02 | R92: Parcial (compensada) | S92: 0.9 | T92: MC-02; informe de riesgo hidráulico; REG-MANT-SENS | U92: Facilities / Resp. del Sistema | V92: 7.5 Protección contra amenazas físicas y ambientales | W92: CCN-STIC 804/808

Sheet Refuerzos
A1: Código medida | B1: Medida | C1: Refuerzo | D1: Nombre del refuerzo | E1: Nivel(es) en que se exige (Anexo II) | F1: Nivel exigido a TechServ | G1: ¿Exigible a TechServ? | H1: Texto del refuerzo (RD 311/2022) | I1: Implementación / alternativa elegida (ver SoA)
A2: op.pl.1 | B2: Análisis de riesgos | C2: R2 | D2: Análisis de riesgos formal | E2: ALTO | F2: ALTO | G2: Sí | H2: R2-Análisis de riesgos formal. Se deberá realizar un análisis formal, usando un lenguaje específico, con un fundamento matemático reconocido internacionalmente, que: – [op.pl.1.r2.1] Valore cualitativamente los activos más valiosos del sistema. – [op.pl.1.r2.2] Cuantifique las amenazas posibles. – [op.pl.1.r2.3] Valore y priorice las salvaguardas adecuadas. – [op.pl.1.r2.4] Valore y asuma formalmente el riesgo residual. | I2: R2 análisis formal exigido en ALTA → cumplido (PILAR, modo formal).
A3: op.pl.1 | B3: Análisis de riesgos | C3: R1 | D3: Análisis de riesgos semiformal | E3: MEDIO | F3: ALTO | G3: No | H3: R1-Análisis de riesgos semiformal. Se deberá realizar un análisis de riesgos semiformal, usando un lenguaje específico, con un catálogo básico de amenazas y una semántica definida. Es decir, una presentación con tablas que: – [op.pl.1.r1.1] Valore cualitativamente los activos más valiosos del sistema. – [op.pl.1.r1.2] Cuantifique las amenazas más probables. – [op.pl.1.r1.3] Valore las salvaguardas que protegen de dichas amenazas. – [op.pl.1.r1.4] Valore el riesgo residual. | I3: —
A4: op.pl.2 | B4: Arquitectura de Seguridad | C4: R1 | D4: Sistema de gestión | E4: MEDIO/ALTO | F4: ALTO | G4: Sí | H4: R1-Sistema de gestión. [op.pl.2.r1.1] Sistema de gestión, relativo a la planificación, organización y control de los recursos relativos a la seguridad de la información. | I4: R1+R2+R3 exigidos en ALTA → cumplidos.
A5: op.pl.2 | B5: Arquitectura de Seguridad | C5: R2 | D5: Sistema de gestión de la seguridad con mejora continua | E5: ALTO | F5: ALTO | G5: Sí | H5: R2-Sistema de gestión de la seguridad con mejora continua. [op.pl.2.r2.1] Sistema de gestión de la seguridad de la información, con actualización y aprobación periódica. | I5: R1+R2+R3 exigidos en ALTA → cumplidos.
A6: op.pl.2 | B6: Arquitectura de Seguridad | C6: R3 | D6: Validación de datos | E6: ALTO | F6: ALTO | G6: Sí | H6: R3-Validación de datos. [op.pl.2.r3.1] Controles técnicos internos, incluyendo la validación de datos de entrada, salida y datos intermedios. | I6: R1+R2+R3 exigidos en ALTA → cumplidos.
A7: op.pl.4 | B7: Dimensionamiento/gestión de la capacidad | C7: R1 | D7: Mejora continua de la gestión de la capacidad | E7: MEDIO/ALTO | F7: ALTO | G7: Sí | H7: R1 –Mejora continua de la gestión de la capacidad. – [op.pl.4.r1.1] Se realizará una previsión de la capacidad y se mantendrá actualizada durante todo el ciclo de vida del sistema. – [op.pl.4.r1.2] Se emplearán herramientas y recursos para la monitorización de la capacidad. | I7: Dimensión D = ALTO → R1 exigido → cumplido.
A8: op.acc.1 | B8: Identificación | C8: R1 | D8: Identificación avanzada | E8: MEDIO/ALTO | F8: ALTO | G8: Sí | H8: R1-Identificación avanzada. – [op.acc.1.r1.1] La identificación del usuario permitirá al Responsable del Sistema, al Responsable de la Seguridad o a sus respectivos administradores delegados, singularizar a la persona asociada al mismo, así como sus responsabilidades en el sistema. – [op.acc.1.r1.2] Los datos de identificación serán utilizados por el sistema para determinar los privilegios del usuario conforme a los requisitos de control de acceso establecidos en la documentación de seguridad. – [op.acc.1.r1.3] Se asegurará la existencia de una lista actualizada de usuarios autorizados y mantenida por el administrador del sistema/de la seguridad del sistema. | I8: Dimensiones T (MEDIO) y A (ALTO) → nivel ALTO → R1 exigido → cumplido.
A9: op.acc.2 | B9: Requisitos de acceso | C9: R1 | D9: Privilegios de acceso | E9: ALTO | F9: ALTO | G9: Sí | H9: R1-Privilegios de acceso. – [op.acc.2.r1.1] Todos los usuarios autorizados deben tener un conjunto de atributos de seguridad (privilegios) que puedan ser mantenidos individualmente. – [op.acc.2.r1.2] Los privilegios de acceso se implementarán para restringir el tipo de acceso que un usuario puede tener (lectura, escritura, modificación, borrado, etc.). | I9: R1 Privilegios de acceso exigido en ALTO → cumplido.
A10: op.acc.3 | B10: Segregación de funciones y tareas | C10: R1 | D10: Segregación rigurosa | E10: ALTO | F10: ALTO | G10: Sí | H10: R1-Segregación rigurosa. – [op.acc.3.r1.1] Siempre que sea posible, la misma persona no aunará funciones de configuración y mantenimiento del sistema. – [op.acc.3.r1.2] La misma persona no puede aunar funciones de auditoría o supervisión con cualquier otra función.
A11: op.acc.5 | B11: Mecanismo de autenticación (usuarios externos) | C11: R2 | D11: Contraseña + OTP | E11: BAJO/MEDIO/ALTO | F11: ALTO | G11: Alternativa (elegir ≥1 del grupo) | H11: R2-Contraseña + OTP. – [op.acc.5.r2.1] Se requerirá una contraseña de un solo uso (OTP, en inglés) como complemento a la contraseña de usuario. | I11: Alternativa elegida: R2 (Cl@ve PIN/permanente) y R3/R4 (certificado/DNIe); + R5 registro. Cumple '[R2 o R3 o R4] + R5'.
A12: op.acc.5 | B12: Mecanismo de autenticación (usuarios externos) | C12: R3 | D12: Certificados | E12: BAJO/MEDIO/ALTO | F12: ALTO | G12: Alternativa (elegir ≥1 del grupo) | H12: R3-Certificados. – [op.acc.5.r3.1] Se emplearán certificados cualificados como mecanismo de autenticación. – [op.acc.5.r3.2] El uso del certificado estará protegido por un segundo factor, del tipo PIN o biométrico. – [op.acc.5.r3.3] Las credenciales utilizadas deberán haber sido obtenidas tras un registro previo presencial, o bien telemático, usando un certificado electrónico cualificado. | I12: Alternativa elegida: R2 (Cl@ve PIN/permanente) y R3/R4 (certificado/DNIe); + R5 registro. Cumple '[R2 o R3 o R4] + R5'.
A13: op.acc.5 | B13: Mecanismo de autenticación (usuarios externos) | C13: R4 | D13: Certificados en dispositivo físico | E13: BAJO/MEDIO/ALTO | F13: ALTO | G13: Alternativa (elegir ≥1 del grupo) | H13: R4-Certificados en dispositivo físico. – [op.acc.5.r4.1] Se emplearán certificados cualificados como mecanismo de autenticación, en soporte físico (tarjeta o similar) usando algoritmos, parámetros y dispositivos autorizados por el CCN. – [op.acc.5.r4.2] El uso del certificado estará protegido por un segundo factor, del tipo PIN o biométrico. – [op.acc.5.r4.3] Las credenciales utilizadas deberán haber sido obtenidas tras un registro previo presencial, o bien telemático, usando certificado electrónico cualificado. | I13: Alternativa elegida: R2 (Cl@ve PIN/permanente) y R3/R4 (certificado/DNIe); + R5 registro. Cumple '[R2 o R3 o R4] + R5'.
A14: op.acc.5 | B14: Mecanismo de autenticación (usuarios externos) | C14: R5 | D14: Registro | E14: MEDIO/ALTO | F14: ALTO | G14: Sí | H14: R5-Registro. – [op.acc.5.r5.1] Se registrarán los accesos con éxito y los fallidos. – [op.acc.5.r5.2] Se informará al usuario del último acceso efectuado con su identidad. | I14: Alternativa elegida: R2 (Cl@ve PIN/permanente) y R3/R4 (certificado/DNIe); + R5 registro. Cumple '[R2 o R3 o R4] + R5'.
A15: op.acc.5 | B15: Mecanismo de autenticación (usuarios externos) | C15: R1 | D15: Contraseñas | E15: BAJO | F15: ALTO | G15: No | H15: R1-Contraseñas. – [op.acc.5.r1.1] Se empleará una contraseña como mecanismo de autenticación. – [op.acc.5.r1.2] Se impondrán normas de complejidad mínima y robustez frente a ataques de adivinación (ver guías CCN-STIC). | I15: —
A16: op.acc.6 | B16: Mecanismo de autenticación (usuarios de la organización) | C16: R1 | D16: Contraseñas | E16: BAJO/MEDIO/ALTO | F16: ALTO | G16: Alternativa (elegir ≥1 del grupo) | H16: R1-Contraseñas. – [op.acc.6.r1.1] Se empleará una contraseña como mecanismo de autenticación cuando el acceso se realiza desde zonas controladas y sin atravesar zonas no controladas (véase refuerzo R8). – [op.acc.6.r1.2] Se impondrán normas de complejidad mínima y robustez frente a ataques de adivinación (ver guías CCN-STIC). | I16: Alternativa elegida: R2 para todo el personal y R4 para administradores. Cumple '[R1 o R2 o R3 o R4] + R5 + R6 + R7 + R8 + R9'.
A17: op.acc.6 | B17: Mecanismo de autenticación (usuarios de la organización) | C17: R2 | D17: Contraseña + otro factor de autenticación | E17: BAJO/MEDIO/ALTO | F17: ALTO | G17: Alternativa (elegir ≥1 del grupo) | H17: R2-Contraseña + otro factor de autenticación. – [op.acc.6.r2.1] Se requerirá un segundo factor tal como «algo que se tiene», es decir, un dispositivo, una contraseña de un solo uso (OTP, en inglés) como complemento a la contraseña de usuario, o «algo que se es». | I17: Alternativa elegida: R2 para todo el personal y R4 para administradores. Cumple '[R1 o R2 o R3 o R4] + R5 + R6 + R7 + R8 + R9'.
A18: op.acc.6 | B18: Mecanismo de autenticación (usuarios de la organización) | C18: R3 | D18: Certificados | E18: BAJO/MEDIO/ALTO | F18: ALTO | G18: Alternativa (elegir ≥1 del grupo) | H18: R3-Certificados. – [op.acc.6.r3.1] Se emplearán certificados cualificados como mecanismo de autenticación. – [op.acc.6.r3.2] El uso del certificado estará protegido por un segundo factor, del tipo PIN o biométrico. | I18: Alternativa elegida: R2 para todo el personal y R4 para administradores. Cumple '[R1 o R2 o R3 o R4] + R5 + R6 + R7 + R8 + R9'.
A19: op.acc.6 | B19: Mecanismo de autenticación (usuarios de la organización) | C19: R4 | D19: Certificados en dispositivo físico | E19: BAJO/MEDIO/ALTO | F19: ALTO | G19: Alternativa (elegir ≥1 del grupo) | H19: R4-Certificados en dispositivo físico. – [op.acc.6.r4.1] Se emplearán certificados cualificados como mecanismo de autenticación, en soporte físico (tarjeta o similar) usando algoritmos, parámetros y dispositivos autorizados por el CCN. – [op.acc.6.r4.2] El uso del certificado estará protegido por un segundo factor, del tipo PIN o biométrico. | I19: Alternativa elegida: R2 para todo el personal y R4 para administradores. Cumple '[R1 o R2 o R3 o R4] + R5 + R6 + R7 + R8 + R9'.
A20: op.acc.6 | B20: Mecanismo de autenticación (usuarios de la organización) | C20: R5 | D20: Registro | E20: MEDIO/ALTO | F20: ALTO | G20: Sí | H20: R5-Registro. – [op.acc.6.r5.1] Se registrarán los accesos con éxito y los fallidos. – [op.acc.6.r5.2] Se informará al usuario del último acceso efectuado con su identidad. | I20: Alternativa elegida: R2 para todo el personal y R4 para administradores. Cumple '[R1 o R2 o R3 o R4] + R5 + R6 + R7 + R8 + R9'.
A21: op.acc.6 | B21: Mecanismo de autenticación (usuarios de la organización) | C21: R6 | D21: Limitación de la ventana de acceso | E21: ALTO | F21: ALTO | G21: Sí | H21: R6-Limitación de la ventana de acceso. – [op.acc.6.r6.1] Se definirán aquellos puntos en los que el sistema requerirá una renovación de la autenticación del usuario, mediante identificación singular, no bastando con la sesión establecida. | I21: Alternativa elegida: R2 para todo el personal y R4 para administradores. Cumple '[R1 o R2 o R3 o R4] + R5 + R6 + R7 + R8 + R9'.
A22: op.acc.6 | B22: Mecanismo de autenticación (usuarios de la organización) | C22: R7 | D22: Suspensión por no utilización | E22: ALTO | F22: ALTO | G22: Sí | H22: R7-Suspensión por no utilización. – [op.acc.6.r7.1] Las credenciales se suspenderán tras un periodo definido de no utilización. | I22: Alternativa elegida: R2 para todo el personal y R4 para administradores. Cumple '[R1 o R2 o R3 o R4] + R5 + R6 + R7 + R8 + R9'.
... A29: op.exp.4 | B29: Mantenimiento y actualizaciones de seguridad | C29: R2 | D29: Prevención de fallos | E29: ALTO | F29: ALTO | G29: Sí | H29: R2-Prevención de fallos. [op.exp.4.r2.1] Antes de la aplicación de las configuraciones, parches y actualizaciones de seguridad se preverá un mecanismo para revertirlos en caso de aparición de efectos adversos. | I29: R1+R2 exigidos → cumplidos.
A30: op.exp.5 | B30: Gestión de cambios | C30: R1 | D30: Prevención de fallos | E30: ALTO | F30: ALTO | G30: Sí | H30: R1-Prevención de fallos. – [op.exp.5.r1.1] Antes de la aplicación de los cambios, se deberá tener en cuenta la posibilidad de revertirlos en caso de la aparición de efectos adversos. – [op.exp.5.r1.2] Todos los fallos en el software y hardware deberán ser comunicados al responsable designado en la organización de la seguridad. – [op.exp.5.r1.3] Todos los cambios en el sistema deberán documentarse, incluyendo una valoración del impacto que dicho cambio supone en la seguridad del sistema.
A31: op.exp.6 | B31: Protección frente a código dañino | C31: R1 | D31: Escaneo periódico | E31: MEDIO/ALTO | F31: ALTO | G31: Sí | H31: R1-Escaneo periódico. – [op.exp.6.r1.1] Todo el sistema se escaneará regularmente para detectar código dañino. | I31: R1+R2+R3+R4 exigidos → cumplidos.
A32: op.exp.6 | B32: Protección frente a código dañino | C32: R2 | D32: Revisión preventiva del sistema | E32: MEDIO/ALTO | F32: ALTO | G32: Sí | H32: R2-Revisión preventiva del sistema. – [op.exp.6.r2.1] Las funciones críticas se analizarán al arrancar el sistema en prevención de modificaciones no autorizadas. | I32: R1+R2+R3+R4 exigidos → cumplidos.
A33: op.exp.6 | B33: Protección frente a código dañino | C33: R3 | D33: Lista blanca | E33: ALTO | F33: ALTO | G33: Sí | H33: R3 - Lista blanca. – [op.exp.6.r3.1] Solamente se podrán ejecutar aquellas aplicaciones previamente autorizadas. Se implementará una lista blanca para impedir la ejecución de aplicaciones no autorizadas. | I33: R1+R2+R3+R4 exigidos → cumplidos.
A34: op.exp.6 | B34: Protección frente a código dañino | C34: R4 | D34: Capacidad de respuesta en caso de incidente | E34: ALTO | F34: ALTO | G34: Sí | H34: R4-Capacidad de respuesta en caso de incidente. – [op.exp.6.r4.1] Se emplearán herramientas de seguridad orientadas a detectar, investigar y resolver actividades sospechosas en puestos de usuario y servidores (EDR - Endpoint Detection and Response). | I34: R1+R2+R3+R4 exigidos → cumplidos.
A35: op.exp.7 | B35: Gestión de incidentes | C35: R1 | D35: Notificación | E35: MEDIO/ALTO | F35: ALTO | G35: Sí | H35: R1-Notificación. – [op.exp.7.r1.1] Se dispondrá de soluciones de ventanilla única para la notificación de incidentes al CCN-CERT, que permita la distribución de notificaciones a las diferentes entidades de manera federada, utilizando para ello dependencias administrativas jerárquicas. | I35: R1+R2+R3 exigidos → cumplidos.
A36: op.exp.7 | B36: Gestión de incidentes | C36: R2 | D36: Detección y Respuesta | E36: MEDIO/ALTO | F36: ALTO | G36: Sí | H36: R2 –Detección y Respuesta. El proceso integral para hacer frente a los incidentes que puedan tener un impacto en la seguridad del sistema ([op.exp.7.1]) deberá incluir: – [op.exp.7.r2.1] Implantación de medidas urgentes, incluyendo la detención de servicios, el aislamiento del sistema afectado, la recogida de evidencias y protección de los registros, según convenga al caso. – [op.exp.7.r2.2] Asignación de recursos para investigar las causas, analizar las consecuencias y resolver el incidente. – [op.exp.7.r2.3] Informar del incidente a los responsables de la información y servicios afectados y de las actuaciones llevadas a cabo para su resolución. – [op.exp.7.r2.4] Medidas para: a) Prevenir que se repita el incidente. b) Incluir en los procedimientos de usuario la identificación y forma de tratar el incidente. c) Actualizar, extender, mejorar u optimizar los procedimientos de resolución de incidentes. | I36: R1+R2+R3 exigidos → cumplidos.
A37: op.exp.7 | B37: Gestión de incidentes | C37: R3 | D37: Reconfiguración dinámica | E37: ALTO | F37: ALTO | G37: Sí | H37: R3-Reconfiguración dinámica. La reconfiguración dinámica del sistema persigue detener, desviar o limitar ataques, acotando los daños. – [op.exp.7.r3.1] La reconfiguración dinámica incluye, por ejemplo, cambios en las reglas de los enrutadores (routers), listas de control de acceso, parámetros del sistema de detección / prevención de intrusiones y reglas en los cortafuegos y puertas de enlace, aislamiento de elementos críticos y aislamiento de las copias de seguridad. – [op.exp.7.r3.2] El organismo adaptará los procedimientos de reconfiguración dinámica reaccionando a los anuncios recibidos del CCN-CERT relativos a ciberamenazas sofisticadas y campañas de ataques. | I37: R1+R2+R3 exigidos → cumplidos.
A38: op.exp.8 | B38: Registro de la actividad | C38: R1 | D38: Revisión de los registros | E38: MEDIO/ALTO | F38: MEDIO | G38: Sí | H38: R1-Revisión de los registros. – [op.exp.8.r1.1] Se revisarán informalmente, de forma periódica, los registros de actividad, buscando patrones anormales. | I38: Dimensión T = MEDIO → exigidos R1-R4; R5 (revisión automática y correlación) no exigido pero implantado voluntariamente (exceso de cumplimiento).
A39: op.exp.8 | B39: Registro de la actividad | C39: R2 | D39: Sincronización del reloj del sistema | E39: MEDIO/ALTO | F39: MEDIO | G39: Sí | H39: R2-Sincronización del reloj del sistema. – [op.exp.8.r2.1] El sistema deberá disponer de una referencia de tiempo (timestamp) para facilitar las funciones de registro de eventos y auditoría. La modificación de la referencia de tiempo del sistema será una función de administración y, en caso de realizarse su sincronización con otros dispositivos, deberán utilizarse mecanismos de autenticación e integridad. | I39: Dimensión T = MEDIO → exigidos R1-R4; R5 (revisión automática y correlación) no exigido pero implantado voluntariamente (exceso de cumplimiento).
A40: op.exp.8 | B40: Registro de la actividad | C40: R3 | D40: Retención de registros | E40: MEDIO/ALTO | F40: MEDIO | G40: Sí | H40: R3-Retención de registros. – [op.exp.8.r3.1] En la documentación de seguridad del sistema se deberán indicar los eventos de seguridad que serán auditados y el tiempo de retención de los registros antes de ser eliminados. | I40: Dimensión T = MEDIO → exigidos R1-R4; R5 (revisión automática y correlación) no exigido pero implantado voluntariamente (exceso de cumplimiento).
A41: op.exp.8 | B41: Registro de la actividad | C41: R4 | D41: Control de acceso | E41: MEDIO/ALTO | F41: MEDIO | G41: Sí | H41: R4-Control de acceso. – [op.exp.8.r4.1] Los registros de actividad y, en su caso, las copias de seguridad de los mismos, solamente podrán ser accedidos o eliminarse por personal debidamente autorizado. | I41: Dimensión T = MEDIO → exigidos R1-R4; R5 (revisión automática y correlación) no exigido pero implantado voluntariamente (exceso de cumplimiento).
A42: op.exp.8 | B42: Registro de la actividad | C42: R5 | D42: Revisión automática y correlación de eventos | E42: ALTO | F42: MEDIO | G42: No | H42: R5-Revisión automática y correlación de eventos. – [op.exp.8.r5.1] El sistema deberá implementar herramientas para analizar y revisar la actividad del sistema y la información de auditoría, en búsqueda de comprometimientos de la seguridad posibles o reales. – [op.exp.8.r5.2] Se dispondrá de un sistema automático de recolección de registros, correlación de eventos y respuesta automática ante los mismos. | I42: —
... A93: mp.s.4 | B93: Protección frente a denegación de servicio | C93: R1 | D93: Detección y reacción | E93: ALTO | F93: ALTO | G93: Sí | H93: R1-Detección y reacción. – [mp.s.4.r1.1] Se establecerá un sistema de detección y tratamiento de ataques de denegación de servicio (DoS y DDoS). – [mp.s. 4.r1.2] Se establecerán procedimientos de reacción a los ataques, incluyendo la comunicación con el proveedor de comunicaciones. | I93: Dimensión D = ALTO → R1 exigido → cumplido.

Sheet Medidas compensatorias
A1: Registro de medidas compensatorias – art. 28.3 RD 311/2022 (“…podrán ser reemplazadas por otras compensatorias, siempre y cuando se justifique documentalmente que protegen igual o mejor el riesgo…”)
A3: ID | B3: Medida / refuerzo ENS sustituido | C3: Ámbito de aplicación | D3: Limitaciones o restricciones | E3: Objetivo de la medida original | F3: Riesgo identificado (AR-2026-01) | G3: Definición de la(s) medida(s) compensatoria(s) | H3: Validación de la medida compensatoria | I3: Mantenimiento / revisión | J3: Aprobación
A4: MC-01 | B4: op.pl.5 Componentes certificados | C4: Clúster de cortafuegos del CPD de respaldo (Tres Cantos): fabricante sin producto cualificado en el CPSTIC para la versión desplegada. | D4: El contrato de mantenimiento vence en 2027; la sustitución anticipada supone 180 k€ no presupuestados. El CPD de respaldo sólo está activo en contingencia. | E4: Garantizar que la funcionalidad de seguridad del perímetro de respaldo ofrece garantías equivalentes a un producto cualificado (op.pl.5). | F4: Vulnerabilidades no evaluadas en el firmware del cortafuegos; menor confianza en la robustez de la implementación (R-034 del AR-2026-01, riesgo residual MEDIO). | G4: 1) Bastionado según guía del fabricante y CCN-STIC 600-series; 2) doble capa: IPS/IDS de producto cualificado (CPSTIC) delante del clúster; 3) escaneo de vulnerabilidades semanal y parcheo ≤72 h para críticas; 4) reglas exportadas y revisadas trimestralmente; 5) plan de sustitución aprobado por producto CPSTIC en 2027 (PTR-2026-11). | H4: Pentest anual externo sobre el perímetro de respaldo; prueba de conmutación del CPD (op.cont.3) incluye verificación de reglas; revisión del CSI 30/06/2026. | I4: Revisión trimestral en el CSI; cierre al sustituir el equipo (fecha objetivo 30/06/2027). | J4: CSI – ACTA-CSI-2026-03; verificada por auditor en auditoría de certificación 2026
A5: MC-02 | B5: mp.if.6 Protección frente a inundaciones | C5: CPD principal (Alcobendas): sala técnica en planta baja de edificio arrendado; no es posible reubicar la sala ni instalar drenaje perimetral por restricciones del arrendador. | D5: Contrato de arrendamiento hasta 2029; el propietario no autoriza obras estructurales. | E5: Reducir la probabilidad e impacto de daño por agua a un nivel equivalente al exigido por [mp.if.6]. | F5: Inundación por rotura de conducción o lluvias torrenciales (amenaza [I.2]/[N.*] MAGERIT), R-051, riesgo inherente ALTO. | G5: 1) Suelo técnico elevado 40 cm y racks sobre bancada; 2) sensores de agua bajo suelo técnico con alarma al SOC y al NOC; 3) válvulas de corte automático en conducciones que atraviesan la planta; 4) ausencia de canalizaciones de agua sobre la sala (certificado del arrendador); 5) CPD de respaldo con RTO 4 h que absorbe la pérdida total de la sala. | H5: Prueba semestral de sensores; inspección anual de la propiedad; simulacro de conmutación anual (REG-CONT-03). | I5: Revisión anual y ante cualquier obra en el edificio; reevaluar en la renovación del arrendamiento (2029). | J5: CSI – ACTA-CSI-2026-03; verificada por auditor en auditoría de certificación 2026
A6: MC-03 | B6: mp.com.3 R3 Dispositivos hardware (cifrado) | C6: Túneles IPsec site-to-site entre el tenant IaaS (NubeAdmin) y los CPD: el proveedor cloud no ofrece terminación en HSM/dispositivo hardware dedicado. | D6: Limitación técnica del proveedor cloud; la alternativa (línea dedicada MPLS con cifrador hardware) triplica el coste y no está prevista hasta 2027. | E6: Proteger integridad y autenticidad de las comunicaciones al nivel exigido por [mp.com.3] R3 en categoría ALTA. | F6: Compromiso del material criptográfico en la pasarela software del lado cloud (R-062, residual MEDIO). | G6: 1) Terminación en los CPD sobre appliance cualificado CPSTIC (cumple R4) con claves en HSM; 2) lado cloud: pasarela con claves custodiadas en el KMS del proveedor con certificación ENS ALTA y rotación mensual; 3) algoritmos y parámetros CCN-STIC 807 (IKEv2, AES-256-GCM, SHA-384, DH grupo 19+); 4) doble capa: TLS 1.3 con mTLS extremo a extremo en las aplicaciones sobre el túnel. | H6: Auditoría de configuración anual (CCN-STIC 807); pruebas de intercepción en pentest; evidencia de rotación de claves. | I6: Revisión anual; migración a cifrador hardware dedicado planificada (PTR-2026-14, T3 2027). | J6: CSI – ACTA-CSI-2026-03; verificada por auditor en auditoría de certificación 2026
A7: MC-04 | B7: mp.si.2 R1 Productos certificados (cifrado de soportes) | C7: Cintas LTO-9 de copias de seguridad externalizadas: el software de cifrado del robot de cintas no figura en el CPSTIC. | D7: Plataforma de backup heredada del contrato anterior; sustitución prevista en la renovación 2027. | E7: Asegurar la confidencialidad e integridad de la información en soportes extraíbles al nivel de [mp.si.2] en ALTO. | F7: Pérdida o robo de cintas durante el transporte/custodia externa (R-070). | G7: 1) Cifrado AES-256 nativo de la unidad LTO con claves gestionadas en HSM cualificado; 2) transporte en maletines con cierre y precinto numerado, empresa de custodia con ISO 27001; 3) inventario y registro de movimientos (mp.si.3/mp.si.4); 4) copia adicional cifrada en el tenant cloud ENS ALTA (cumple R2). | H7: Prueba de restauración trimestral desde cinta cifrada; auditoría del proveedor de custodia anual. | I7: Revisión anual; cierre al migrar a plataforma de backup con producto cualificado. | J7: CSI – ACTA-CSI-2026-03; verificada por auditor en auditoría de certificación 2026

Sheet Resumen
A1: Resumen de la Declaración de Aplicabilidad – calculado con fórmulas sobre la hoja 'SoA ENS'
A3: Indicador | B3: Valor
A4: Medidas del Anexo II | B4: =COUNTIF('SoA ENS'!$M$2:$M$92,"SÍ*")+COUNTIF('SoA ENS'!$M$2:$M$92,"NO") -> 73
A5: Medidas aplicables (SÍ) | B5: =COUNTIF('SoA ENS'!$M$2:$M$92,"SÍ") -> 68
A6: Medidas aplicables con medida compensatoria | B6: =COUNTIF('SoA ENS'!$M$2:$M$92,"SÍ (compensada)") -> 4
A7: Medidas NO aplicables (exclusiones justificadas) | B7: =COUNTIF('SoA ENS'!$M$2:$M$92,"NO") -> 1
A8: Implantadas | B8: =COUNTIF('SoA ENS'!$R$2:$R$92,"Implantada") -> 66
A9: Parciales (incl. compensadas) | B9: =COUNTIF('SoA ENS'!$R$2:$R$92,"Parcial*") -> 6
A10: Planificadas / no implantadas | B10: =COUNTIF('SoA ENS'!$R$2:$R$92,"Planificada")+COUNTIF('SoA ENS'!$R$2:$R$92,"No implantada") -> 0
A11: Grado medio de implantación (medidas aplicables) | B11: =IFERROR(AVERAGEIF('SoA ENS'!$M$2:$M$92,"<>NO",'SoA ENS'!$S$2:$S$92),0) -> 0.98888889
A12: Refuerzos exigibles (Sí) | B12: =COUNTIF(Refuerzos!$G$2:$G$500,"Sí") -> 78
A13: Refuerzos en grupo alternativo | B13: =COUNTIF(Refuerzos!$G$2:$G$500,"Alternativa*") -> 9
A14: Medidas compensatorias registradas | B14: =COUNTA('Medidas compensatorias'!$A$4:$A$100) -> 4
A17: Marco | B17: Nº medidas | C17: Aplicables | D17: No aplicables | E17: Implantadas | F17: Grado medio implantación
A18: Marco organizativo | B18: =COUNTIF('SoA ENS'!$A$2:$A$92,A18) -> 4 | C18: =COUNTIFS('SoA ENS'!$A$2:$A$92,A18,'SoA ENS'!$M$2:$M$92,"SÍ*") -> 4 | D18: =COUNTIFS('SoA ENS'!$A$2:$A$92,A18,'SoA ENS'!$M$2:$M$92,"NO") -> 0 | E18: =COUNTIFS('SoA ENS'!$A$2:$A$92,A18,'SoA ENS'!$R$2:$R$92,"Implantada") -> 4 | F18: =IFERROR(AVERAGEIFS('SoA ENS'!$S$2:$S$92,'SoA ENS'!$A$2:$A$92,A18,'SoA ENS'!$M$2:$M$92,"<>NO"),0) -> 1
A19: Planificación | B19: =COUNTIF('SoA ENS'!$A$2:$A$92,A19) -> 5 | C19: =COUNTIFS('SoA ENS'!$A$2:$A$92,A19,'SoA ENS'!$M$2:$M$92,"SÍ*") -> 5 | D19: =COUNTIFS('SoA ENS'!$A$2:$A$92,A19,'SoA ENS'!$M$2:$M$92,"NO") -> 0 | E19: =COUNTIFS('SoA ENS'!$A$2:$A$92,A19,'SoA ENS'!$R$2:$R$92,"Implantada") -> 4 | F19: =IFERROR(AVERAGEIFS('SoA ENS'!$S$2:$S$92,'SoA ENS'!$A$2:$A$92,A19,'SoA ENS'!$M$2:$M$92,"<>NO"),0) -> 0.97
A20: Control de acceso | B20: =COUNTIF('SoA ENS'!$A$2:$A$92,A20) -> 6 | C20: =COUNTIFS('SoA ENS'!$A$2:$A$92,A20,'SoA ENS'!$M$2:$M$92,"SÍ*") -> 6 | D20: =COUNTIFS('SoA ENS'!$A$2:$A$92,A20,'SoA ENS'!$M$2:$M$92,"NO") -> 0 | E20: =COUNTIFS('SoA ENS'!$A$2:$A$92,A20,'SoA ENS'!$R$2:$R$92,"Implantada") -> 6 | F20: =IFERROR(AVERAGEIFS('SoA ENS'!$S$2:$S$92,'SoA ENS'!$A$2:$A$92,A20,'SoA ENS'!$M$2:$M$92,"<>NO"),0) -> 1
A21: Explotación | B21: =COUNTIF('SoA ENS'!$A$2:$A$92,A21) -> 10 | C21: =COUNTIFS('SoA ENS'!$A$2:$A$92,A21,'SoA ENS'!$M$2:$M$92,"SÍ*") -> 10 | D21: =COUNTIFS('SoA ENS'!$A$2:$A$92,A21,'SoA ENS'!$M$2:$M$92,"NO") -> 0 | E21: =COUNTIFS('SoA ENS'!$A$2:$A$92,A21,'SoA ENS'!$R$2:$R$92,"Implantada") -> 10 | F21: =IFERROR(AVERAGEIFS('SoA ENS'!$S$2:$S$92,'SoA ENS'!$A$2:$A$92,A21,'SoA ENS'!$M$2:$M$92,"<>NO"),0) -> 1
A22: Recursos externos | B22: =COUNTIF('SoA ENS'!$A$2:$A$92,A22) -> 4 | C22: =COUNTIFS('SoA ENS'!$A$2:$A$92,A22,'SoA ENS'!$M$2:$M$92,"SÍ*") -> 4 | D22: =COUNTIFS('SoA ENS'!$A$2:$A$92,A22,'SoA ENS'!$M$2:$M$92,"NO") -> 0 | E22: =COUNTIFS('SoA ENS'!$A$2:$A$92,A22,'SoA ENS'!$R$2:$R$92,"Implantada") -> 4 | F22: =IFERROR(AVERAGEIFS('SoA ENS'!$S$2:$S$92,'SoA ENS'!$A$2:$A$92,A22,'SoA ENS'!$M$2:$M$92,"<>NO"),0) -> 1
A23: Servicios en la nube | B23: =COUNTIF('SoA ENS'!$A$2:$A$92,A23) -> 1 | C23: =COUNTIFS('SoA ENS'!$A$2:$A$92,A23,'SoA ENS'!$M$2:$M$92,"SÍ*") -> 1 | D23: =COUNTIFS('SoA ENS'!$A$2:$A$92,A23,'SoA ENS'!$M$2:$M$92,"NO") -> 0 | E23: =COUNTIFS('SoA ENS'!$A$2:$A$92,A23,'SoA ENS'!$R$2:$R$92,"Implantada") -> 1 | F23: =IFERROR(AVERAGEIFS('SoA ENS'!$S$2:$S$92,'SoA ENS'!$A$2:$A$92,A23,'SoA ENS'!$M$2:$M$92,"<>NO"),0) -> 1
A24: Continuidad del servicio | B24: =COUNTIF('SoA ENS'!$A$2:$A$92,A24) -> 4 | C24: =COUNTIFS('SoA ENS'!$A$2:$A$92,A24,'SoA ENS'!$M$2:$M$92,"SÍ*") -> 4 | D24: =COUNTIFS('SoA ENS'!$A$2:$A$92,A24,'SoA ENS'!$M$2:$M$92,"NO") -> 0 | E24: =COUNTIFS('SoA ENS'!$A$2:$A$92,A24,'SoA ENS'!$R$2:$R$92,"Implantada") -> 4 | F24: =IFERROR(AVERAGEIFS('SoA ENS'!$S$2:$S$92,'SoA ENS'!$A$2:$A$92,A24,'SoA ENS'!$M$2:$M$92,"<>NO"),0) -> 1
A25: Monitorización del sistema | B25: =COUNTIF('SoA ENS'!$A$2:$A$92,A25) -> 3 | C25: =COUNTIFS('SoA ENS'!$A$2:$A$92,A25,'SoA ENS'!$M$2:$M$92,"SÍ*") -> 3 | D25: =COUNTIFS('SoA ENS'!$A$2:$A$92,A25,'SoA ENS'!$M$2:$M$92,"NO") -> 0 | E25: =COUNTIFS('SoA ENS'!$A$2:$A$92,A25,'SoA ENS'!$R$2:$R$92,"Implantada") -> 2 | F25: =IFERROR(AVERAGEIFS('SoA ENS'!$S$2:$S$92,'SoA ENS'!$A$2:$A$92,A25,'SoA ENS'!$M$2:$M$92,"<>NO"),0) -> 0.93333333
A26: Protección de las instalaciones e infraestructuras | B26: =COUNTIF('SoA ENS'!$A$2:$A$92,A26) -> 7 | C26: =COUNTIFS('SoA ENS'!$A$2:$A$92,A26,'SoA ENS'!$M$2:$M$92,"SÍ*") -> 7 | D26: =COUNTIFS('SoA ENS'!$A$2:$A$92,A26,'SoA ENS'!$M$2:$M$92,"NO") -> 0 | E26: =COUNTIFS('SoA ENS'!$A$2:$A$92,A26,'SoA ENS'!$R$2:$R$92,"Implantada") -> 6 | F26: =IFERROR(AVERAGEIFS('SoA ENS'!$S$2:$S$92,'SoA ENS'!$A$2:$A$92,A26,'SoA ENS'!$M$2:$M$92,"<>NO"),0) -> 0.98571429
A27: Gestión del personal | B27: =COUNTIF('SoA ENS'!$A$2:$A$92,A27) -> 4 | C27: =COUNTIFS('SoA ENS'!$A$2:$A$92,A27,'SoA ENS'!$M$2:$M$92,"SÍ*") -> 4 | D27: =COUNTIFS('SoA ENS'!$A$2:$A$92,A27,'SoA ENS'!$M$2:$M$92,"NO") -> 0 | E27: =COUNTIFS('SoA ENS'!$A$2:$A$92,A27,'SoA ENS'!$R$2:$R$92,"Implantada") -> 4 | F27: =IFERROR(AVERAGEIFS('SoA ENS'!$S$2:$S$92,'SoA ENS'!$A$2:$A$92,A27,'SoA ENS'!$M$2:$M$92,"<>NO"),0) -> 1
A28: Protección de los equipos | B28: =COUNTIF('SoA ENS'!$A$2:$A$92,A28) -> 4 | C28: =COUNTIFS('SoA ENS'!$A$2:$A$92,A28,'SoA ENS'!$M$2:$M$92,"SÍ*") -> 4 | D28: =COUNTIFS('SoA ENS'!$A$2:$A$92,A28,'SoA ENS'!$M$2:$M$92,"NO") -> 0 | E28: =COUNTIFS('SoA ENS'!$A$2:$A$92,A28,'SoA ENS'!$R$2:$R$92,"Implantada") -> 4 | F28: =IFERROR(AVERAGEIFS('SoA ENS'!$S$2:$S$92,'SoA ENS'!$A$2:$A$92,A28,'SoA ENS'!$M$2:$M$92,"<>NO"),0) -> 1
A29: Protección de las comunicaciones | B29: =COUNTIF('SoA ENS'!$A$2:$A$92,A29) -> 4 | C29: =COUNTIFS('SoA ENS'!$A$2:$A$92,A29,'SoA ENS'!$M$2:$M$92,"SÍ*") -> 4 | D29: =COUNTIFS('SoA ENS'!$A$2:$A$92,A29,'SoA ENS'!$M$2:$M$92,"NO") -> 0 | E29: =COUNTIFS('SoA ENS'!$A$2:$A$92,A29,'SoA ENS'!$R$2:$R$92,"Implantada") -> 3 | F29: =IFERROR(AVERAGEIFS('SoA ENS'!$S$2:$S$92,'SoA ENS'!$A$2:$A$92,A29,'SoA ENS'!$M$2:$M$92,"<>NO"),0) -> 0.975
... A33: Protección de los servicios | B33: =COUNTIF('SoA ENS'!$A$2:$A$92,A33) -> 4 | C33: =COUNTIFS('SoA ENS'!$A$2:$A$92,A33,'SoA ENS'!$M$2:$M$92,"SÍ*") -> 4 | D33: =COUNTIFS('SoA ENS'!$A$2:$A$92,A33,'SoA ENS'!$M$2:$M$92,"NO") -> 0 | E33: =COUNTIFS('SoA ENS'!$A$2:$A$92,A33,'SoA ENS'!$R$2:$R$92,"Implantada") -> 4 | F33: =IFERROR(AVERAGEIFS('SoA ENS'!$S$2:$S$92,'SoA ENS'!$A$2:$A$92,A33,'SoA ENS'!$M$2:$M$92,"<>NO"),0) -> 1
A34: TOTAL | B34: =SUM(B18:B33) -> 73 | C34: =SUM(C18:C33) -> 72 | D34: =SUM(D18:D33) -> 1 | E34: =SUM(E18:E33) -> 66
A36: Nota: la hoja 'SoA ENS' recalcula 'Nivel exigido' y 'Exigencia aplicable' a partir de la fila 'DECISIÓN CSI' de la hoja 'Categorización'. Si se cambia un nivel de dimensión, deben revisarse manualmente las columnas '¿Aplica?', 'Refuerzos exigidos' y 'Justificación' (son texto, no fórmula, porque requieren decisión y justificación humana).

Sheet Texto Anexo II
A1: Código | B1: Medida | C1: Dimensiones | D1: Bajo | E1: Medio | F1: Alto | G1: Texto de la medida (RD 311/2022, Anexo II) | H1: Refuerzos (texto)
A2: org.1 | B2: Política de seguridad | C2: Categoría | D2: aplica | E2: aplica | F2: aplica | G2: La política de seguridad, que se aprobará de conformidad con lo dispuesto en el artículo 12 de este real decreto, se plasmará en un documento en el que, de forma clara, se precise, al menos, lo siguiente: – [org.1.1] Los objetivos o misión de la organización. – [org.1.2] El marco legal y regulatorio en el que se desarrollarán las actividades. – [org.1.3] Los roles o funciones de seguridad, definiendo para cada uno los deberes y responsabilidades del cargo, así como el procedimiento para su designación y renovación. – [org.1.4] La estructura del comité o los comités para la gestión y coordinación de la seguridad, detallando su ámbito de responsabilidad, las personas integrantes y la relación con otros elementos de la organización. – [org.1.5] Las directrices para la estructuración de la documentación de seguridad del sistema, su gestión y acceso.
A3: org.2 | B3: Normativa de seguridad | C3: Categoría | D3: aplica | E3: aplica | F3: aplica | G3: Se dispondrá de una serie de documentos que describan: – [org.2.1] El uso correcto de equipos, servicios e instalaciones, así como lo que se considerará uso indebido. – [org.2.2] La responsabilidad del personal con respecto al cumplimiento o violación de la normativa: derechos, deberes y medidas disciplinarias de acuerdo con la legislación vigente.
A4: org.3 | B4: Procedimientos de seguridad | C4: Categoría | D4: aplica | E4: aplica | F4: aplica | G4: Se dispondrá de una serie de documentos que detallen de forma clara y precisa cómo operar los elementos del sistema de información: – [org.3.1] Cómo llevar a cabo las tareas habituales. – [org.3.2] Quién debe hacer cada tarea. – [org.3.3] Cómo identificar y reportar comportamientos anómalos. – [org.3.4.] La forma en que se ha de tratar la información en consideración al nivel de seguridad que requiere, precisando cómo efectuar: a) Su control de acceso. b) Su almacenamiento. c) La realización de copias. d) El etiquetado de soportes. e) Su transmisión telemática. f) Cualquier otra actividad relacionada con dicha información.
A5: org.4 | B5: Proceso de autorización | C5: Categoría | D5: aplica | E5: aplica | F5: aplica | G5: Se establecerá un proceso formal de autorizaciones que cubra todos los elementos del sistema de información concernidos: – [org.4.1] Utilización de instalaciones, habituales y alternativas. – [org.4.2] Entrada de equipos en producción, en particular, equipos que involucren criptografía. – [org.4.3] Entrada de aplicaciones en producción. – [org.4.4] Establecimiento de enlaces de comunicaciones con otros sistemas. – [org.4.5] Utilización de medios de comunicación, habituales y alternativos. – [org.4.6] Utilización de soportes de información. – [org.4.7] Utilización de equipos móviles. Se entenderá por equipos móviles ordenadores portátiles, tabletas, teléfonos móviles u otros de naturaleza análoga. – [org.4.8] Utilización de servicios de terceros, bajo contrato o convenio, concesión, encargo, etc.
A6: op.pl.1 | B6: Análisis de riesgos | C6: Categoría | D6: aplica | E6: + R1 | F6: + R2 | G6: Se realizará un análisis de riesgos informal, realizado en lenguaje natural. Es decir, una exposición textual que: – [op.pl.1.1] Identifique los activos más valiosos del sistema. (Ver op.exp.1). – [op.pl.1.2] Identifique las amenazas más probables. – [op.pl.1.3] Identifique las salvaguardas que protegen de dichas amenazas. – [op.pl.1.4] Identifique los principales riesgos residuales. | H6: R1-Análisis de riesgos semiformal. Se deberá realizar un análisis de riesgos semiformal, usando un lenguaje específico, con un catálogo básico de amenazas y una semántica definida. Es decir, una presentación con tablas que: – [op.pl.1.r1.1] Valore cualitativamente los activos más valiosos del sistema. – [op.pl.1.r1.2] Cuantifique las amenazas más probables. – [op.pl.1.r1.3] Valore las salvaguardas que protegen de dichas amenazas. – [op.pl.1.r1.4] Valore el riesgo residual. R2-Análisis de riesgos formal. Se deberá realizar un análisis formal, usando un lenguaje específico, con un fundamento matemático reconocido internacionalmente, que: – [op.pl.1.r2.1] Valore cualitativamente los activos más valiosos del sistema. – [op.pl.1.r2.2] Cuantifique las amenazas posibles. – [op.pl.1.r2.3] Valore y priorice las salvaguardas adecuadas. – [op.pl.1.r2.4] Valore y asuma formalmente el riesgo residual.
A7: op.pl.2 | B7: Arquitectura de Seguridad | C7: Categoría | D7: aplica | E7: + R1 | F7: + R1 + R2 + R3 | G7: La seguridad del sistema será objeto de un planteamiento integral detallando, al menos, los siguientes aspectos: – [op.pl.2.1] Documentación de las instalaciones, incluyendo áreas y puntos de acceso. – [op.pl.2.2] Documentación del sistema, incluyendo equipos, redes internas y conexiones al exterior, y puntos de acceso al sistema (puestos de trabajo y consolas de administración). – [op.pl.2.3] Esquema de líneas de defensa, incluyendo puntos de interconexión a otros sistemas o a otras redes (en especial, si se trata de internet o redes públicas en general); cortafuegos, DMZ, etc.; y la utilización de tecnologías diferentes para prevenir vulnerabilidades que pudieran perforar simultáneamente varias líneas de defensa. – [op.pl.2.4] Sistema de identificación y autenticación de usuarios, incluyendo el uso de claves concertadas, contraseñas, tarjetas de identificación, biometría, u otras de naturaleza análoga, y el uso de ficheros o directorios para autenticar al usuario y determinar sus derechos de acceso. | H7: R1-Sistema de gestión. [op.pl.2.r1.1] Sistema de gestión, relativo a la planificación, organización y control de los recursos relativos a la seguridad de la información. R2-Sistema de gestión de la seguridad con mejora continua. [op.pl.2.r2.1] Sistema de gestión de la seguridad de la información, con actualización y aprobación periódica. R3-Validación de datos. [op.pl.2.r3.1] Controles técnicos internos, incluyendo la validación de datos de entrada, salida y datos intermedios.
A8: op.pl.3 | B8: Adquisición de nuevos componentes | C8: Categoría | D8: aplica | E8: aplica | F8: aplica | G8: Se establecerá un proceso formal para planificar la adquisición de nuevos componentes del sistema, proceso que: – [op.pl.3.1] Atenderá a las conclusiones del análisis de riesgos ([op.pl.1]). – [op.pl.3.2] Será acorde a la arquitectura de seguridad escogida ([op.pl.2]). – [op.pl.3.3] Contemplará las necesidades técnicas, de formación y de financiación, de forma conjunta.
A9: op.pl.4 | B9: Dimensionamiento/gestión de la capacidad | C9: D | D9: aplica | E9: + R1 | F9: + R1 | G9: Con carácter previo a la puesta en explotación, se realizará un estudio que cubrirá los siguientes aspectos: – [op.pl.4.1] Necesidades de procesamiento. – [op.pl.4.2] Necesidades de almacenamiento de información: durante su procesamiento y durante el periodo que deba retenerse. – [op.pl.4.3] Necesidades de comunicación. – [op.pl.4.4] Necesidades de personal: cantidad y cualificación profesional. – [op.pl.4.5] Necesidades de instalaciones y medios auxiliares. | H9: R1 –Mejora continua de la gestión de la capacidad. – [op.pl.4.r1.1] Se realizará una previsión de la capacidad y se mantendrá actualizada durante todo el ciclo de vida del sistema. – [op.pl.4.r1.2] Se emplearán herramientas y recursos para la monitorización de la capacidad.
A10: op.pl.5 | B10: Componentes certificados | C10: Categoría | D10: n.a. | E10: aplica | F10: aplica | G10: – [op.pl.5.1]. Se utilizará el Catálogo de Productos y Servicios de Seguridad de las Tecnologías de la Información y Comunicación (CPSTIC) del CCN, para seleccionar los productos o servicios suministrados por un tercero que formen parte de la arquitectura de seguridad del sistema y aquellos que se referencien expresamente en las medidas de este real decreto. En caso de que no existan productos o servicios en el CPSTIC que implementen las funcionalidades requeridas, se utilizarán productos certificados de acuerdo a lo descrito en el artículo 19. Una Instrucción Técnica de Seguridad detallará los criterios relativos a la adquisición de productos de seguridad. – [op.pl.5.2] Si el sistema suministra un servicio de seguridad a un tercero bajo el alcance del ENS, el producto o productos que en los que se sustente dicho servicio debe superar un proceso de cualificación y ser incluido en el CPSTIC, o aportar una certificación que cumpla con los requisitos funcionales de seguridad y de aseguramiento de acuerdo a lo establecido en el artículo 19.
A11: op.acc.1 | B11: Identificación | C11: AT | D11: aplica | E11: + R1 | F11: + R1 | G11: La identificación de los usuarios del sistema se realizará de acuerdo con lo que se indica a continuación: – [op.acc.1.1] Se podrá utilizar como identificador único los sistemas de identificación previstos en la normativa de aplicación, entre ellos, los sistemas de clave concertada y cualquier otro sistema que las administraciones consideren válido en los términos y condiciones establecidos en la Ley 39/2015, de 1 de octubre, del Procedimiento Administrativo Común de las Administraciones Públicas. – [op.acc.1.2] Cuando el usuario tenga diferentes roles frente al sistema (como ciudadano o usuario final, como trabajador del organismo o como administrador de los sistemas, por ejemplo) recibirá identificadores singulares para cada perfil, de forma que se recaben siempre los correspondientes registros de actividad, delimitándose los privilegios correspondientes a cada perfil. – [op.acc.1.3] Cada entidad (entidad, usuario o proceso) que accede al sistema, contará con un identificador singular que permita conocer el destinatario de los mismos y los derechos de acceso que recibe, así como las acciones realizadas por cada entidad. – [op.acc.1.4] Las cuentas de usuario se gestionarán de la siguiente forma: a) Cada cuenta (de entidad, usuario o proceso) estará asociada a un identificador único. b) Las cuentas deben ser inhabilitadas en los siguientes casos: cuando el usuario deja la organización; cuando el usuario cesa en la función para la cual se requería la cuenta de usuario; o, cuando la persona que la autorizó da orden en sentido contrario. c) Las cuentas se retendrán durante el periodo necesario para atender a las necesidades de trazabilidad de los registros de actividad asociados a las mismas. A este periodo se le denominará «periodo de retención». – [op.acc.1.5] En los supuestos de comunicaciones electrónicas, las partes intervinientes se identificarán atendiendo a los mecanismos previstos en la legislación europea y nacional en la materia, con la siguiente correspondencia entre los niveles de la dimensión de autenticidad de los sistemas de información a los que se tiene acceso y los niveles de seguridad (bajo, sustancial, alto) de los sistemas de identificación electrónica previstos en el Reglamento (UE) n.º 910/2014, del Parlamento Europeo y del Consejo, de 23 de julio de 2014, relativo a la identificación electrónica y los servicios de confianza para las transacciones electrónicas en el mercado interior y por el que se deroga la Directiva 1999/93/CE y sus normas de desarrollo o ejecución que resulten de aplicación: a) Si se requiere un nivel BAJO en la dimensión de autenticidad (anexo I): Nivel de seguridad bajo, sustancial o alto (artículo 8 del Reglamento (UE) n.º 910/2014). b) Si se requiere un nivel MEDIO en la dimensión de autenticidad (anexo I): Nivel de seguridad sustancial o alto (artículo 8 del Reglamento (UE) n.º 910/2014). c) Si se requiere un nivel ALTO en la dimensión de autenticidad (anexo I): Nivel de seguridad alto (artículo 8 del Reglamento (UE) n.º 910/2014). | H11: R1-Identificación avanzada. – [op.acc.1.r1.1] La identificación del usuario permitirá al Responsable del Sistema, al Responsable de la Seguridad o a sus respectivos administradores delegados, singularizar a la persona asociada al mismo, así como sus responsabilidades en el sistema. – [op.acc.1.r1.2] Los datos de identificación serán utilizados por el sistema para determinar los privilegios del usuario conforme a los requisitos de control de acceso establecidos en la documentación de seguridad. – [op.acc.1.r1.3] Se asegurará la existencia de una lista actualizada de usuarios autorizados y mantenida por el administrador del sistema/de la seguridad del sistema.
A12: op.acc.2 | B12: Requisitos de acceso | C12: ICAT | D12: aplica | E12: aplica | F12: + R1 | G12: – [op.acc.2.1] Los recursos del sistema se protegerán con algún mecanismo que impida su utilización, salvo a las entidades que disfruten de derechos de acceso suficientes. – [op.acc.2.2] Los derechos de acceso de cada recurso, se establecerán según las decisiones de la persona responsable del recurso, ateniéndose a la política y normativa de seguridad del sistema. – [op.acc.2.3] Particularmente, se controlará el acceso a los componentes del sistema operativo y a sus ficheros o registros de configuración. | H12: R1-Privilegios de acceso. – [op.acc.2.r1.1] Todos los usuarios autorizados deben tener un conjunto de atributos de seguridad (privilegios) que puedan ser mantenidos individualmente. – [op.acc.2.r1.2] Los privilegios de acceso se implementarán para restringir el tipo de acceso que un usuario puede tener (lectura, escritura, modificación, borrado, etc.).
A13: op.acc.3 | B13: Segregación de funciones y tareas | C13: ICAT | D13: n.a. | E13: aplica | F13: + R1 | G13: El sistema de control de acceso se organizará de forma que se exija la concurrencia de dos o más personas para realizar tareas críticas, anulando la posibilidad de que un solo individuo autorizado pueda abusar de sus derechos para cometer alguna acción ilícita o no autorizada. – [op.acc.3.1] Siempre que sea posible, las capacidades de desarrollo y operación no recaerán en la misma persona. – [op.acc.3.2] Siempre que sea posible, las personas que autorizan y controlan el uso serán distintas. | H13: R1-Segregación rigurosa. – [op.acc.3.r1.1] Siempre que sea posible, la misma persona no aunará funciones de configuración y mantenimiento del sistema. – [op.acc.3.r1.2] La misma persona no puede aunar funciones de auditoría o supervisión con cualquier otra función.
A14: op.acc.4 | B14: Proceso de gestión de derechos de acceso | C14: ICAT | D14: aplica | E14: aplica | F14: aplica | G14: Los derechos de acceso de cada entidad, usuario o proceso se limitarán atendiendo a los siguientes principios: – [op.acc.4.1] Todo acceso estará prohibido, salvo autorización expresa. – [op.acc.4.2] Mínimo privilegio: los privilegios de cada entidad, usuario o proceso se reducirán al mínimo imprescindible para cumplir sus obligaciones o funciones. – [op.acc.4.3] Necesidad de conocer y responsabilidad de compartir: los privilegios se asignarán de forma que las entidades, usuarios o procesos sólo accederán al conocimiento de aquella información requerida para cumplir sus obligaciones o funciones. La información es patrimonio del organismo y toda aquella que resulte necesaria para el usuario estará a su disposición. – [op.acc.4.4] Capacidad de autorizar: Exclusivamente el personal con competencia para ello podrá conceder, alterar o anular la autorización de acceso a los recursos, conforme a los criterios establecidos por su responsable. Los permisos de acceso se revisarán de forma periódica. – [op.acc.4.5] Se establecerá una política específica de acceso remoto, requiriéndose autorización expresa.
A15: op.acc.5 | B15: Mecanismo de autenticación (usuarios externos) | C15: ICAT | D15: + [R1 o R2 o R3 o R4] | E15: + [R2 o R3 o R4] + R5 | F15: + [R2 o R3 o R4] + R5 | G15: – [op.acc.5.1] Antes de proporcionar las credenciales de autenticación a las entidades, usuarios o procesos, estos deberán haberse identificado y registrado de manera fidedigna ante el sistema o ante un Prestador Cualificado de Servicios de Confianza o un proveedor de identidad electrónica reconocido por las administraciones públicas, de conformidad con lo dispuesto en la Ley 39/2015, de 1 de octubre. – [op.acc.5.2] Antes de activar el mecanismo de autenticación, el usuario reconocerá que las ha recibido y que conoce y acepta las obligaciones que implica su tenencia, en particular, el deber de custodia diligente, la protección de su confidencialidad y el deber de notificación inmediata en caso de pérdida. – [op.acc.5.3] Las credenciales estarán bajo el control exclusivo del usuario y se activarán una vez estén bajo su control efectivo. – [op.acc.5.4] Las credenciales se cambiarán con una periodicidad marcada por la política de seguridad de la organización. – [op.acc.5.5] Las credenciales serán inhabilitadas -pudiendo ser regeneradas, en su caso-, cuando conste o se sospeche su pérdida, compromiso o revelación a entidades (personas, equipos o procesos) no autorizadas. – [op.acc.5.6] Las credenciales serán inhabilitadas cuando la entidad (persona, equipo o proceso) que autentican termina su relación con el sistema. – [op.acc.5.7] Antes de autorizar el acceso, la información presentada por el sistema será la mínima imprescindible para que el usuario se autentique, evitando todo aquello que pueda, directa o indirectamente, revelar información sobre el sistema o la cuenta, sus características, su operación o su estado. Las credenciales solamente se validarán cuando se tengan todos los datos necesarios y, si se rechaza, no se informará del motivo del rechazo. – [op.acc.5.8] El número de intentos permitidos será limitado, bloqueando la oportunidad de acceso una vez superado tal número, y requiriendo una intervención específica para reactivar la cuenta, que se describirá en la documentación. – [op.acc.5.9] El sistema informará al usuario de sus derechos u obligaciones inmediatamente después de obtener el acceso. | H15: R1-Contraseñas. – [op.acc.5.r1.1] Se empleará una contraseña como mecanismo de autenticación. – [op.acc.5.r1.2] Se impondrán normas de complejidad mínima y robustez frente a ataques de adivinación (ver guías CCN-STIC). R2-Contraseña + OTP. – [op.acc.5.r2.1] Se requerirá una contraseña de un solo uso (OTP, en inglés) como complemento a la contraseña de usuario. R3-Certificados. – [op.acc.5.r3.1] Se emplearán certificados cualificados como mecanismo de autenticación. – [op.acc.5.r3.2] El uso del certificado estará protegido por un segundo factor, del tipo PIN o biométrico. – [op.acc.5.r3.3] Las credenciales utilizadas deberán haber sido obtenidas tras un registro previo presencial, o bien telemático, usando un certificado electrónico cualificado. R4-Certificados en dispositivo físico. – [op.acc.5.r4.1] Se emplearán certificados cualificados como mecanismo de autenticación, en soporte físico (tarjeta o similar) usando algoritmos, parámetros y dispositivos autorizados por el CCN. – [op.acc.5.r4.2] El uso del certificado estará protegido por un segundo factor, del tipo PIN o biométrico. – [op.acc.5.r4.3] Las credenciales utilizadas deberán haber sido obtenidas tras un registro previo presencial, o bien telemático, usando certificado electrónico cualificado. R5-Registro. – [op.acc.5.r5.1] Se registrarán los accesos con éxito y los fallidos. – [op.acc.5.r5.2] Se informará al usuario del último acceso efectuado con su identidad.
A16: op.acc.6 | B16: Mecanismo de autenticación (usuarios de la organización) | C16: ICAT | D16: + [R1 o R2 o R3 o R4] + R8 + R9 | E16: + [R1 o R2 o R3 o R4] + R5 + R8 + R9 | F16: + [R1 o R2 o R3 o R4] + R5 + R6 + R7 + R8 + R9 | G16: Esta medida se refiere a personal del organismo, propio o contratado, estable o circunstancial, que pueda tener acceso a información contenida en el sistema. Las guías CCN-STIC desarrollarán los mecanismos y calidades exigibles a cada tipo de factor de autenticación, en función de los niveles de seguridad requeridos por el sistema de información el que se accede y los privilegios concedidos al usuario. – [op.acc.6.1] Antes de proporcionar las credenciales a los usuarios, estos deberán conocer y aceptar la política de seguridad del organismo en los aspectos que les afecten. – [op.acc.6.2] Antes de activar el mecanismo de autenticación, el usuario reconocerá que ha recibido las credenciales de acceso y que conoce y acepta las obligaciones que implica su tenencia, en particular, el deber de custodia diligente, la protección de su confidencialidad y el deber de notificación inmediata en caso de pérdida. – [op.acc.6.3] Las credenciales estarán bajo el control exclusivo del usuario y se activarán una vez estén bajo su control efectivo. – [op.acc.6.4] Las credenciales se cambiarán con una periodicidad marcada por la política de seguridad de la organización. – [op.acc.6.5] Las credenciales serán inhabilitadas -pudiendo ser regeneradas, en su caso-, cuando conste o se sospeche su pérdida, compromiso o revelación a entidades (personas, equipos o procesos) no autorizadas. – [op.acc.6.6] Las credenciales serán inhabilitadas cuando el usuario que autentican termina su relación con el sistema. – [op.acc.6.7] Antes de autorizar el acceso, la información presentada por el sistema será la mínima imprescindible para que el usuario se autentique, evitando todo aquello que pueda, directa o indirectamente, revelar información sobre el sistema o la cuenta, sus características, su operación o su estado. Las credenciales solamente se validarán cuando se tengan todos los datos necesarios y, si se rechaza, no se informará del motivo del rechazo. – [op.acc.6.8] El número de intentos permitidos será limitado, bloqueando la oportunidad de acceso una vez superado tal número, y requiriendo una intervención específica para reactivar la cuenta, que se describirá en la documentación. – [op.acc.6.9] El sistema informará al usuario de sus derechos u obligaciones inmediatamente después de obtener el acceso. | H16: R1-Contraseñas. – [op.acc.6.r1.1] Se empleará una contraseña como mecanismo de autenticación cuando el acceso se realiza desde zonas controladas y sin atravesar zonas no controladas (véase refuerzo R8). – [op.acc.6.r1.2] Se impondrán normas de complejidad mínima y robustez frente a ataques de adivinación (ver guías CCN-STIC). R2-Contraseña + otro factor de autenticación. – [op.acc.6.r2.1] Se requerirá un segundo factor tal como «algo que se tiene», es decir, un dispositivo, una contraseña de un solo uso (OTP, en inglés) como complemento a la contraseña de usuario, o «algo que se es». R3-Certificados. – [op.acc.6.r3.1] Se emplearán certificados cualificados como mecanismo de autenticación. – [op.acc.6.r3.2] El uso del certificado estará protegido por un segundo factor, del tipo PIN o biométrico. R4-Certificados en dispositivo físico. – [op.acc.6.r4.1] Se emplearán certificados cualificados como mecanismo de autenticación, en soporte físico (tarjeta o similar) usando algoritmos, parámetros y dispositivos autorizados por el CCN. – [op.acc.6.r4.2] El uso del certificado estará protegido por un segundo factor, del tipo PIN o biométrico. R5-Registro. – [op.acc.6.r5.1] Se registrarán los accesos con éxito y los fallidos. – [op.acc.6.r5.2] Se informará al usuario del último acceso efectuado con su identidad. R6-Limitación de la ventana de acceso. – [op.acc.6.r6.1] Se definirán aquellos puntos en los que el sistema requerirá una renovación de la autenticación del usuario, mediante identificación singular, no bastando con la sesión establecida. R7-Suspensión por no utilización. – [op.acc.6.r7.1] Las credenciales se suspenderán tras un periodo definido de no utilización. R8-Doble factor para acceso desde o a través de zonas no controladas. Se denomina «zona controlada» aquella que no es de acceso público, requiriéndose que el usuario, antes de tener acceso al equipo, se haya autenticado previamente de alguna forma (control de acceso a las instalaciones), diferente del mecanismo de autenticación lógica frente al sistema. Un ejemplo de zona no controlada es Internet. – [op.acc.6.r8.1] Para el acceso desde o a través de zonas no controladas se requerirá un doble factor de autenticación: R2, R3 o R4. R9-Acceso remoto (todos los niveles). – [op.acc.6.r9.1] Será de aplicación la ITS de Interconexión de sistemas de información. – [op.acc.6.r9.2] El acceso remoto deberá considerar los siguientes aspectos: a) Ser autorizado por la autoridad correspondiente. b) El tráfico deberá ser cifrado. c) Si la utilización no se produce de manera constante, el acceso remoto deberá encontrarse inhabilitado y habilitarse únicamente cuando sea necesario. d) Deberán recogerse registros de auditoría de este tipo de conexiones.
A17: op.exp.1 | B17: Inventario de activos | C17: Categoría | D17: aplica | E17: aplica | F17: aplica | G17: [op.exp.1.1] Se mantendrá un inventario actualizado de todos los elementos del sistema, detallando su naturaleza e identificando a su responsable; es decir, la persona que toma las decisiones relativas al mismo.
A18: op.exp.2 | B18: Configuración de seguridad | C18: Categoría | D18: aplica | E18: aplica | F18: aplica | G18: Se configurarán los equipos previamente a su entrada en operación, de forma que: – [op.exp.2.1] Se retiren cuentas y contraseñas estándar. – [op.exp.2.2] Se aplicará la regla de «mínima funcionalidad», es decir: a) El sistema debe proporcionar la funcionalidad mínima imprescindible para que la organización alcance sus objetivos. b) No proporcionará funciones injustificadas (de operación, administración o auditoría) al objeto de reducir al mínimo su perímetro de exposición, eliminándose o desactivándose aquellas funciones que sean innecesarias o inadecuadas al fin que se persigue. – [op.exp.2.3] Se aplicará la regla de «seguridad por defecto», es decir: a) Las medidas de seguridad serán respetuosas con el usuario y protegerán a éste, salvo que se exponga conscientemente a un riesgo. b) Para reducir la seguridad, el usuario tendrá que realizar acciones conscientes. c) El uso natural, en los casos que el usuario no ha consultado el manual, será un uso seguro. – [op.exp.2.4] Las máquinas virtuales estarán configuradas y gestionadas de un modo seguro. La gestión del parcheado, cuentas de usuarios, software antivirus, etc. se realizará como si se tratara de máquinas físicas, incluyendo la máquina anfitriona.
A19: op.exp.3 | B19: Gestión de la configuración de seguridad | C19: Categoría | D19: aplica | E19: + R1 | F19: + R1 + R2 + R3 | G19: Se gestionará de forma continua la configuración de los componentes del sistema, de forma que: – [op.exp.3.1] Se mantenga en todo momento la regla de "funcionalidad mínima" ([op.exp.2]). – [op.exp.3.2] Se mantenga en todo momento la regla de "mínimo privilegio" ([op.exp.2]). – [op.exp.3.3] El sistema se adapte a las nuevas necesidades, previamente autorizadas. (Ver [op.acc.4]). – [op.exp.3.4] El sistema reaccione a vulnerabilidades notificadas. (Ver [op.exp.4]). – [op.exp.3.5] El sistema reaccione a incidentes. (Ver [op.exp.7]). – [op.exp.3.6] La configuración de seguridad solamente podrá editarse por personal debidamente autorizado. | H19: R1-Mantenimiento regular de la configuración. – [op.exp.3.r1.1] Existirán configuraciones hardware/software, autorizadas y mantenidas regularmente, para los servidores, elementos de red y estaciones de trabajo. – [op.exp.3.r1.2] Se verificará periódicamente la configuración hardware/software del sistema para asegurar que no se han introducido ni instalado elementos no autorizados. – [op.exp.3.r1.3] Se mantendrá una lista de servicios autorizados para servidores y estaciones de trabajo. R2-Responsabilidad de la configuración. – [op.exp.3.r2.1] La configuración de seguridad del sistema operativo y aplicaciones, tanto de estaciones y servidores como de la electrónica de red del sistema, será responsabilidad de un número muy limitado de administradores del sistema. R3-Copias de seguridad. – [op.exp.3.r3.1] Se realizarán copias de seguridad de la configuración del sistema de forma que sea posible reconstruirlo en parte o en su totalidad tras un incidente.
A20: op.exp.4 | B20: Mantenimiento y actualizaciones de seguridad | C20: Categoría | D20: aplica | E20: + R1 | F20: + R1 + R2 | G20: Para mantener el equipamiento físico y lógico que constituye el sistema, se aplicará lo siguiente: – [op.exp.4.1] Se atenderá a las especificaciones de los fabricantes en lo relativo a instalación y mantenimiento de los sistemas, lo que incluirá un seguimiento continuo de los anuncios de defectos. – [op.exp.4.2] Se dispondrá de un procedimiento para analizar, priorizar y determinar cuándo aplicar las actualizaciones de seguridad, parches, mejoras y nuevas versiones. La priorización tendrá en cuenta la variación del riesgo en función de la implantación o no de la actualización. – [op.exp.4.3] El mantenimiento solo podrá realizarse por personal debidamente autorizado. | H20: R1-Pruebas en preproducción. [op.exp.4.r1.1] Antes de poner en producción una nueva versión o una versión parcheada, se comprobará en un entorno de prueba controlado y consistente en configuración al entorno de producción, que la nueva instalación funciona correctamente y no disminuye la eficacia de las funciones necesarias para el trabajo diario. R2-Prevención de fallos. [op.exp.4.r2.1] Antes de la aplicación de las configuraciones, parches y actualizaciones de seguridad se preverá un mecanismo para revertirlos en caso de aparición de efectos adversos.
A21: op.exp.5 | B21: Gestión de cambios | C21: Categoría | D21: n.a. | E21: aplica | F21: + R1 | G21: Se mantendrá un control continuo de los cambios realizados en el sistema, de forma que: – [op.exp.5.1] Los cambios se planificarán para reducir el impacto sobre la prestación de los servicios afectados. Para ello, todas las peticiones de cambio se registrarán asignando un número de referencia que permita su seguimiento, de forma equivalente al registro de los incidentes. – [op.exp.5.2] La información a registrar para cada petición de cambio será suficiente para que quien deba autorizarlos no tenga dudas al respecto y permita gestionarlo hasta su desestimación o implementación. – [op.exp.5.3] Las pruebas de preproducción, siempre que sea posible realizarlas, se efectuarán en equipos equivalentes a los de producción, al menos en los aspectos específicos del cambio. – [op.exp.5.4] Mediante un análisis de riesgos se determinará si los cambios son relevantes para la seguridad del sistema. Aquellos cambios que impliquen un riesgo de nivel ALTO deberán ser aprobados, explícitamente, de forma previa a su implantación, por el Responsable de la Seguridad. – [op.exp.5.5] Una vez implementado el cambio, se realizarán las pruebas de aceptación convenientes. Si son positivas, se actualizará la documentación de configuración (diagramas de red, manuales, el inventario, etc.), siempre que proceda. | H21: R1-Prevención de fallos. – [op.exp.5.r1.1] Antes de la aplicación de los cambios, se deberá tener en cuenta la posibilidad de revertirlos en caso de la aparición de efectos adversos. – [op.exp.5.r1.2] Todos los fallos en el software y hardware deberán ser comunicados al responsable designado en la organización de la seguridad. – [op.exp.5.r1.3] Todos los cambios en el sistema deberán documentarse, incluyendo una valoración del impacto que dicho cambio supone en la seguridad del sistema.
A22: op.exp.6 | B22: Protección frente a código dañino | C22: Categoría | D22: aplica | E22: + R1 + R2 | F22: + R1 + R2 + R3 + R4 | G22: – [op.exp.6.1] Se dispondrá de mecanismos de prevención y reacción frente a código dañino, incluyendo el correspondiente mantenimiento de acuerdo a las recomendaciones del fabricante. – [op.exp.6.2] Se instalará software de protección frente a código dañino en todos los equipos: puestos de usuario, servidores y elementos perimetrales. – [op.exp.6.3] Todo fichero procedente de fuentes externas será analizado antes de trabajar con él. – [op.exp.6.4] Las bases de datos de detección de código dañino permanecerán permanentemente actualizadas.v – [op.exp.6.5] El software de detección de código dañino instalado en los puestos de usuario deberá estar configurado de forma adecuada e implementará protección en tiempo real de acuerdo a las recomendaciones del fabricante. | H22: R1-Escaneo periódico. – [op.exp.6.r1.1] Todo el sistema se escaneará regularmente para detectar código dañino. R2-Revisión preventiva del sistema. – [op.exp.6.r2.1] Las funciones críticas se analizarán al arrancar el sistema en prevención de modificaciones no autorizadas. R3 - Lista blanca. – [op.exp.6.r3.1] Solamente se podrán ejecutar aquellas aplicaciones previamente autorizadas. Se implementará una lista blanca para impedir la ejecución de aplicaciones no autorizadas. R4-Capacidad de respuesta en caso de incidente. – [op.exp.6.r4.1] Se emplearán herramientas de seguridad orientadas a detectar, investigar y resolver actividades sospechosas en puestos de usuario y servidores (EDR - Endpoint Detection and Response).
A23: op.exp.7 | B23: Gestión de incidentes | C23: Categoría | D23: aplica | E23: + R1 + R2 | F23: + R1 + R2 + R3 | G23: – [op.exp.7.1] Se dispondrá de un proceso integral para hacer frente a los incidentes que puedan tener un impacto en la seguridad del sistema, que incluya el informe de eventos de seguridad y debilidades, detallando los criterios de clasificación y el escalado de la notificación. – [op.exp.7.2] La gestión de incidentes que afecten a datos personales tendrá en cuenta lo dispuesto en el Reglamento General de Protección de Datos; la Ley Orgánica 3/2018, de 5 de diciembre, en especial su disposición adicional primera, así como el resto de normativa de aplicación, sin perjuicio de los requisitos establecidos en este real decreto. | H23: R1-Notificación. – [op.exp.7.r1.1] Se dispondrá de soluciones de ventanilla única para la notificación de incidentes al CCN-CERT, que permita la distribución de notificaciones a las diferentes entidades de manera federada, utilizando para ello dependencias administrativas jerárquicas. R2 –Detección y Respuesta. El proceso integral para hacer frente a los incidentes que puedan tener un impacto en la seguridad del sistema ([op.exp.7.1]) deberá incluir: – [op.exp.7.r2.1] Implantación de medidas urgentes, incluyendo la detención de servicios, el aislamiento del sistema afectado, la recogida de evidencias y protección de los registros, según convenga al caso. – [op.exp.7.r2.2] Asignación de recursos para investigar las causas, analizar las consecuencias y resolver el incidente. – [op.exp.7.r2.3] Informar del incidente a los responsables de la información y servicios afectados y de las actuaciones llevadas a cabo para su resolución. – [op.exp.7.r2.4] Medidas para: a) Prevenir que se repita el incidente. b) Incluir en los procedimientos de usuario la identificación y forma de tratar el incidente. c) Actualizar, extender, mejorar u optimizar los procedimientos de resolución de incidentes. R3-Reconfiguración dinámica. La reconfiguración dinámica del sistema persigue detener, desviar o limitar ataques, acotando los daños. – [op.exp.7.r3.1] La reconfiguración dinámica incluye, por ejemplo, cambios en las reglas de los enrutadores (routers), listas de control de acceso, parámetros del sistema de detección / prevención de intrusiones y reglas en los cortafuegos y puertas de enlace, aislamiento de elementos críticos y aislamiento de las copias de seguridad. – [op.exp.7.r3.2] El organismo adaptará los procedimientos de reconfiguración dinámica reaccionando a los anuncios recibidos del CCN-CERT relativos a ciberamenazas sofisticadas y campañas de ataques.
A24: op.exp.8 | B24: Registro de la actividad | C24: T | D24: aplica | E24: + R1 + R2 + R3 + R4 | F24: + R1 + R2 + R3 + R4 + R5 | G24: Se registrarán las actividades en el sistema, de forma que: – [op.exp.8.1] Se generará un registro de auditoría, que incluirá, al menos, el identificador del usuario o entidad asociado al evento, fecha y hora, sobre qué información se realiza el evento, tipo de evento y el resultado del evento (fallo o éxito), según la política de seguridad y los procedimientos asociados a la misma. – [op.exp.8.2] Se activarán los registros de actividad en los servidores. | H24: R1-Revisión de los registros. – [op.exp.8.r1.1] Se revisarán informalmente, de forma periódica, los registros de actividad, buscando patrones anormales. R2-Sincronización del reloj del sistema. – [op.exp.8.r2.1] El sistema deberá disponer de una referencia de tiempo (timestamp) para facilitar las funciones de registro de eventos y auditoría. La modificación de la referencia de tiempo del sistema será una función de administración y, en caso de realizarse su sincronización con otros dispositivos, deberán utilizarse mecanismos de autenticación e integridad. R3-Retención de registros. – [op.exp.8.r3.1] En la documentación de seguridad del sistema se deberán indicar los eventos de seguridad que serán auditados y el tiempo de retención de los registros antes de ser eliminados. R4-Control de acceso. – [op.exp.8.r4.1] Los registros de actividad y, en su caso, las copias de seguridad de los mismos, solamente podrán ser accedidos o eliminarse por personal debidamente autorizado. R5-Revisión automática y correlación de eventos. – [op.exp.8.r5.1] El sistema deberá implementar herramientas para analizar y revisar la actividad del sistema y la información de auditoría, en búsqueda de comprometimientos de la seguridad posibles o reales. – [op.exp.8.r5.2] Se dispondrá de un sistema automático de recolección de registros, correlación de eventos y respuesta automática ante los mismos.
A25: op.exp.9 | B25: Registro de la gestión de incidentes | C25: Categoría | D25: aplica | E25: aplica | F25: aplica | G25: Se registrarán todas las actuaciones relacionadas con la gestión de incidentes, de forma que: – [op.exp.9.1] Se registrarán los reportes iniciales, intermedios y finales de los incidentes, las actuaciones de emergencia y las modificaciones del sistema derivadas del incidente. – [op.exp.9.2] Se registrará aquella evidencia que pueda dirimirse en un ámbito jurisdiccional, especialmente cuando el incidente pueda comportar acciones disciplinarias sobre el personal interno, sobre proveedores externos o en la persecución de delitos. En la determinación de la composición y detalle de estas evidencias, se recurrirá a asesoramiento legal especializado. – [op.exp.9.3] Como consecuencia del análisis de los incidentes, se revisará la determinación de los eventos auditables.
A26: op.exp.10 | B26: Protección de claves criptográficas | C26: Categoría | D26: aplica | E26: + R1 | F26: + R1 | G26: – [op.exp.10.1] Las claves criptográficas se protegerán durante todo su ciclo de vida: (1) generación, (2) transporte al punto de explotación, (3) custodia durante la explotación, (4) archivo posterior a su retirada de explotación activa y (5) destrucción final. – [op.exp.10.2] Los medios de generación estarán aislados de los medios de explotación. – [op.exp.10.3] Las claves retiradas de operación que deban ser archivadas, lo serán en medios aislados de los de explotación. | H26: R1-Algoritmos autorizados. – [op.exp.10.r1.1] Se emplearán algoritmos y parámetros autorizados por el CCN.
A27: op.ext.1 | B27: Contratación y acuerdos de nivel de servicio | C27: Categoría | D27: n.a. | E27: aplica | F27: aplica | G27: – [op.ext.1.1] Con anterioridad a la efectiva utilización de los recursos externos se establecerá contractualmente un Acuerdo de Nivel de Servicio, que incluirá las características del servicio prestado, lo que debe entenderse como «servicio mínimo admisible», así como, la responsabilidad del prestador y las consecuencias de eventuales incumplimientos.
A28: op.ext.2 | B28: Gestión diaria | C28: Categoría | D28: n.a. | E28: aplica | F28: aplica | G28: Se establecerá lo siguiente: – [op.ext.2.1] Un sistema rutinario para medir el cumplimiento de las obligaciones de servicio, incluyendo el procedimiento para neutralizar cualquier desviación fuera del margen de tolerancia acordado ([op.ext.1]). – [op.ext.2.2] El mecanismo y los procedimientos de coordinación para llevar a cabo las tareas de mantenimiento de los sistemas comprendidos en el acuerdo, que contemplarán los supuestos de incidentes y desastres (ver [op.exp.7]).
A29: op.ext.3 | B29: Protección de la cadena de suministro | C29: Categoría | D29: n.a. | E29: n.a. | F29: aplica | G29: – [op.ext.3.1] Se analizará el impacto que puede tener sobre el sistema un incidente accidental o deliberado que tenga su origen en la cadena de suministro. – [op.ext.3.2] Se estimará el riesgo sobre el sistema por causa del impacto estimado en el punto anterior. – [op.ext.3.3] Se tomarán medidas de contención de los impactos estimados en los puntos anteriores.
A30: op.ext.4 | B30: Interconexión de sistemas | C30: Categoría | D30: n.a. | E30: aplica | F30: + R1 | G30: Se denomina interconexión al establecimiento de enlaces con otros sistemas de información para el intercambio de información y servicios. – [op.ext.4.1] Todos los intercambios de información y prestación de servicios con otros sistemas deberán ser objeto de una autorización previa. Todo flujo de información estará prohibido salvo autorización expresa. – [op.ext.4.2] Para cada interconexión se documentará explícitamente: las características de la interfaz, los requisitos de seguridad y protección de datos y la naturaleza de la información intercambiada. | H30: R1-Coordinación de actividades. – [op.ext.4.r1.1] Cuando se interconecten sistemas en los que la identificación, autenticación y autorización tengan lugar en diferentes dominios de seguridad, bajo distintas responsabilidades, las medidas de seguridad locales se acompañarán de los correspondientes mecanismos y procedimientos de coordinación para la atribución y ejercicio efectivos de las responsabilidades de cada sistema.
A31: op.nub.1 | B31: Protección de servicios en la nube | C31: Categoría | D31: aplica | E31: + R1 | F31: + R1 + R2 | G31: – [op.nub.1.1] Los sistemas que suministran un servicio en la nube a organismos del sector público deberán cumplir con el conjunto de medidas de seguridad en función del modelo de servicio en la nube que presten: Software como Servicio (Software as a Service, SaaS), Plataforma como Servicio (Platform as a Service, PaaS) e Infraestructura como Servicio (Infrastructure as a Service, IaaS) definidas en las guías CCN-STIC que sean de aplicación. – [op.nub.1.2] Cuando se utilicen servicios en la nube suministrados por terceros, los sistemas de información que los soportan deberán ser conformes con el ENS o cumplir con las medidas desarrolladas en una guía CCN-STIC que incluirá, entre otros, requisitos relativos a: a) Auditoría de pruebas de penetración (pentesting). b) Transparencia. c) Cifrado y gestión de claves. d) Jurisdicción de los datos. | H31: R1- Servicios certificados. – [op.nub.1.r1.1] Cuando se utilicen servicios en la nube suministrados por terceros, estos deberán estar certificados bajo una metodología de certificación reconocida por el Organismo de Certificación del Esquema Nacional de Evaluación y Certificación de Seguridad de las Tecnologías de la Información. – [op.nub.1.r1.2] Si el servicio en la nube es un servicio de seguridad deberá cumplir con los requisitos establecidos en [op.pl.5]. R2-Guías de Configuración de Seguridad Específicas. – [op.nub.1.r2.1] La configuración de seguridad de los sistemas que proporcionan estos servicios deberá realizarse según la correspondiente guía CCN-STIC de Configuración de Seguridad Específica, orientadas tanto al usuario como al proveedor.
A32: op.cont.1 | B32: Análisis de impacto | C32: D | D32: n.a. | E32: aplica | F32: aplica | G32: – [op.cont.1.1] Se realizará un análisis de impacto que permita determinar los requisitos de disponibilidad de cada servicio (impacto de una interrupción durante un periodo de tiempo determinado), así como los elementos que son críticos para la prestación de cada servicio.
A33: op.cont.2 | B33: Plan de continuidad | C33: D | D33: n.a. | E33: n.a. | F33: aplica | G33: Se desarrollará un plan de continuidad que establezca las acciones a ejecutar en caso de interrupción de los servicios prestados con los medios habituales. Dicho plan contemplará los siguientes aspectos: – [op.cont.2.1] Se identificarán funciones, responsabilidades y actividades a realizar. – [op.cont.2.2] Existirá una previsión para coordinar la entrada en servicio de los medios alternativos de forma que se garantice poder seguir prestando los servicios esenciales de la organización. – [op.cont.2.3] Todos los medios alternativos estarán planificados y materializados en acuerdos o contratos con los proveedores correspondientes. – [op.cont.2.4] Las personas afectadas por el plan recibirán formación específica relativa a su papel en dicho plan. – [op.cont.2.5] El plan de continuidad será parte integral y armónica de los planes de continuidad de la organización en otras materias ajenas a la seguridad.
A34: op.cont.3 | B34: Pruebas periódicas | C34: D | D34: n.a. | E34: n.a. | F34: aplica | G34: – [op.cont.3.1] Se realizarán pruebas periódicas para localizar y, en su caso, corregir los errores o deficiencias que puedan existir en el plan de continuidad.
A35: op.cont.4 | B35: Medios alternativos | C35: D | D35: n.a. | E35: n.a. | F35: aplica | G35: – [op.cont.4.1] Estará prevista la disponibilidad de medios alternativos para poder seguir prestando servicio cuando los medios habituales no estén disponibles. En concreto, se cubrirán los siguientes elementos del sistema: a) Servicios contratados a terceros. b) Instalaciones alternativas. c) Personal alternativo. d) Equipamiento informático alternativo. e) Medios de comunicación alternativos. – [op.cont.4.2] Se establecerá un tiempo máximo para que los medios alternativos entren en funcionamiento. – [op.cont.4.3] Los medios alternativos estarán sometidos a las mismas garantías de seguridad que los originales.
A36: op.mon.1 | B36: Detección de intrusión | C36: Categoría | D36: aplica | E36: + R1 | F36: + R1 + R2 | G36: – [op.mon.1.1] Se dispondrá de herramientas de detección o prevención de intrusiones. | H36: R1-Detección basada en reglas. – [op.mon.1.r1.1] El sistema dispondrá de herramientas de detección o prevención de intrusiones basadas en reglas. R2-Procedimientos de respuesta. – [op.mon.1.r2.1] Existirán procedimientos de respuesta a las alertas generadas por el sistema de detección o prevención de intrusiones.
A37: op.mon.2 | B37: Sistema de métricas | C37: Categoría | D37: aplica | E37: + R1 + R2 | F37: + R1 + R2 | G37: – [op.mon.2.1] Atendiendo a la categoría de seguridad del sistema, se recopilarán los datos necesarios para conocer el grado de implantación de las medidas de seguridad que resulten aplicables y, en su caso, para proveer el informe anual requerido por el artículo 32. | H37: R1-Efectividad del sistema de gestión de incidentes. – [op.mon.2.r1.1] Se recopilarán los datos precisos que posibiliten evaluar el comportamiento del sistema de gestión de incidentes, de acuerdo con la Instrucción Técnica de Seguridad de Notificación de Incidentes de Seguridad y con la correspondiente guía CCN-STIC. R2-Eficiencia del sistema de gestión de la seguridad. – [op.mon.2.r2.1] Se recopilarán los datos precisos para conocer la eficiencia del sistema de seguridad, en relación con los recursos consumidos, en términos de horas y presupuesto.
A38: op.mon.3 | B38: Vigilancia | C38: Categoría | D38: aplica | E38: + R1 + R2 | F38: + R1 + R2 + R3 + R4 + R5 + R6 | G38: – [op.mon.3.1] Se dispondrá de un sistema automático de recolección de eventos de seguridad. | H38: R1-Correlación de eventos. – [op.mon.3.r1.1] Se dispondrá de un sistema automático de recolección de eventos de seguridad que permita la correlación de los mismos. R2-Análisis dinámico. – [op.mon.3.r2.1] Se dispondrá de soluciones de vigilancia que permitan determinar la superficie de exposición con relación a vulnerabilidades y deficiencias de configuración. R3-Ciberamenazas avanzadas. – [op.mon.3.r3.1] Se dispondrá de sistemas para detección de amenazas avanzadas y comportamientos anómalos. – [op.mon.3.r3.2] Se dispondrá de sistemas para la detección de amenazas persistentes avanzadas (Advanced Persistent Threat, APT) mediante la detección de anomalías significativas en el tráfico de la red. R4-Observatorios digitales. – [op.mon.3.r4.1] Se dispondrá de observatorios digitales con fines de cibervigilancia dedicados a la detección y seguimiento de anomalías que pudieran representar indicadores de amenaza en contenidos digitales. R5-Minería de datos. Se aplicarán medidas para prevenir, detectar y reaccionar frente a intentos de minería de datos: – [op.mon.3.r5.1] Limitación de las consultas, monitorizando volumen y frecuencia. – [op.mon.3.r5.2] Alerta a los administradores de seguridad de comportamientos sospechosos en tiempo real. R6-Inspecciones de seguridad. Periódicamente, o tras incidentes que hayan desvelado vulnerabilidades del sistema nuevas o subestimadas, se realizarán las siguientes inspecciones: – [op.mon.3.r6.1] Verificación de configuración. – [op.mon.3.r6.2] Análisis de vulnerabilidades. – [op.mon.3.r6.3] Pruebas de penetración.
A39: mp.if.1 | B39: Áreas separadas y con control de acceso | C39: Categoría | D39: aplica | E39: aplica | F39: aplica | G39: – [mp.if.1.1] El equipamiento del Centro de Proceso de Datos (CPD) se instalará, en la medida de lo posible, en áreas separadas, específicas para su función. – [mp.if.1.2] Se controlarán los accesos a las áreas indicadas de forma que sólo se pueda acceder por las entradas previstas.
A40: mp.if.2 | B40: Identificación de las personas | C40: Categoría | D40: aplica | E40: aplica | F40: aplica | G40: [mp.if.2.1] El procedimiento de control de acceso identificará a las personas que accedan a los locales donde hay equipamiento esencial que forme parte del sistema de información del CPD, registrando las correspondientes entradas y salidas.
A41: mp.if.3 | B41: Acondicionamiento de los locales | C41: Categoría | D41: aplica | E41: aplica | F41: aplica | G41: Los locales donde se ubiquen los sistemas de información y sus componentes esenciales dispondrán de elementos adecuados para el eficaz funcionamiento del equipamiento allí instalado, y, en especial, para asegurar: – [mp.if.3.1] Las condiciones de temperatura y humedad. – [mp.if.3.2] La protección frente a las amenazas identificadas en el análisis de riesgos. – [mp.if.3.3] La protección del cableado frente a incidentes fortuitos o deliberados.
A42: mp.if.4 | B42: Energía eléctrica | C42: D | D42: aplica | E42: + R1 | F42: + R1 | G42: – [mp.if.4.1] Los locales donde se ubiquen los sistemas de información y sus componentes esenciales dispondrán de tomas de energía eléctrica, de modo que se garantice el suministro y el correcto funcionamiento de las luces de emergencia. | H42: R1-Suministro eléctrico de emergencia. – [mp.if.4.r1.1] En caso de fallo del suministro principal, el abastecimiento eléctrico deberá estar garantizado durante el tiempo suficiente para una terminación ordenada de los procesos y la salvaguarda de la información.
A43: mp.if.5 | B43: Protección frente a incendios | C43: D | D43: aplica | E43: aplica | F43: aplica | G43: – [mp.if.5.1] Los locales donde se ubiquen los sistemas de información y sus componentes esenciales se protegerán frente a incendios atendiendo, al menos, a la normativa industrial de aplicación.
A44: mp.if.6 | B44: Protección frente a inundaciones | C44: D | D44: n.a. | E44: aplica | F44: aplica | G44: – [mp.if.6.1] Los locales donde se ubiquen los sistemas de información y sus componentes esenciales se protegerán frente a incidentes causados por el agua.
A45: mp.if.7 | B45: Registro de entrada y salida de equipamiento | C45: Categoría | D45: aplica | E45: aplica | F45: aplica | G45: – [mp.if.7.1] Se llevará un registro pormenorizado de cualquier entrada y salida de equipamiento esencial, incluyendo la identificación de la persona que autoriza el movimiento.
A46: mp.per.1 | B46: Caracterización del puesto de trabajo | C46: Categoría | D46: n.a. | E46: aplica | F46: aplica | G46: – [mp.per.1.1] Para cada puesto de trabajo, relacionado directamente con el manejo de información o servicios, se definirán las responsabilidades en materia de seguridad, que estarán basadas en el análisis de riesgos. – [mp.per.1.2] Se definirán los requisitos que deben satisfacer las personas que vayan a ocupar el puesto de trabajo, en particular, en términos de confidencialidad. Dichos requisitos se tendrán en cuenta en la selección de la persona que vaya a ocupar el puesto, incluyendo la verificación de sus antecedentes laborales, formación y otras referencias, de conformidad con el ordenamiento jurídico y el respeto a los derechos fundamentales.
A47: mp.per.2 | B47: Deberes y obligaciones | C47: Categoría | D47: aplica | E47: + R1 | F47: + R1 | G47: Se informará a cada persona que trabaje en el sistema de los deberes y responsabilidades de su puesto de trabajo en materia de seguridad, contemplando: – [mp.per.2.1] Las medidas disciplinarias a que haya lugar. – [mp.per.2.2] Contemplando tanto el periodo durante el cual se desempeña el puesto, como las obligaciones en caso de término de la asignación, o traslado a otro puesto de trabajo. – [mp.per.2.3] El deber de confidencialidad respecto de los datos a los que tenga acceso, tanto durante el periodo que esté adscrito al puesto de trabajo, como posteriormente a su terminación. – [mp.per.2.4] En caso de personal contratado a través de un tercero: • [mp.per.2.4.1] Se establecerán los deberes y obligaciones de cada parte y del personal contratado. • [mp.per.2.4.2] Se establecerá el procedimiento de resolución de incidentes relacionados con el incumplimiento de las obligaciones. | H47: R1-Confirmación expresa. – [mp.per.2.r1.1] Se ha de obtener la confirmación expresa de que los usuarios conocen las instrucciones de seguridad necesarias y obligatorias y su aceptación, así como los procedimientos necesarios para llevarlas a cabo de manera adecuada.
A48: mp.per.3 | B48: Concienciación | C48: Categoría | D48: aplica | E48: aplica | F48: aplica | G48: Se realizarán las acciones necesarias para concienciar regularmente al personal acerca de su papel y responsabilidad para que la seguridad del sistema alcance los niveles exigidos. En particular, se recordará periódicamente: – [mp.per.3.1] La normativa de seguridad relativa al buen uso de los equipos o sistemas y las técnicas de ingeniería social más habituales. – [mp.per.3.2] La identificación de incidentes, actividades o comportamientos sospechosos que deban ser reportados para su tratamiento por personal especializado. – [mp.per.3.3] El procedimiento para informar sobre incidentes de seguridad, sean reales o falsas alarmas.
